Projeto03/Calculator/Datapath/ALU/ALU.vhd

library ieee;
use ieee.std_logic_1164.all;
use ieee.numeric_std.all;  

entity ALU is
  port (
    OPERATOR : in std_logic_vector(1 downto 0);
    NUM1, NUM2 : in std_logic_vector(3 downto 0);
    RESULT : out std_logic_vector(3 downto 0)
  );
end ALU;

architecture arch_ALU of ALU is
  signal RESULT_INTERM : std_logic_vector(3 downto 0);
begin
  RESULT_INTERM <=
    std_logic_vector(unsigned(NUM1) + unsigned(NUM2)) when OPERATOR = "00" else
    std_logic_vector(unsigned(NUM1) - unsigned(NUM2)) when OPERATOR = "01" else
    std_logic_vector(shift_left(unsigned(NUM1), to_integer(unsigned(NUM2)))) when OPERATOR = "10" else
    std_logic_vector(shift_right(unsigned(NUM1), to_integer(unsigned(NUM2)))) when OPERATOR = "11" else
    RESULT_INTERM;

  RESULT <= RESULT_INTERM;
end arch_ALU;

Projeto03/Datapath/SelectorTwoStack/SelectorTwoStack.vhd

library ieee;
use ieee.std_logic_1164.all;
use ieee.numeric_std.all;

entity SelectorTwoStack is
  port (
    X0, X1, X2 : in std_logic_vector(3 downto 0);
    sel : in std_logic_vector(2 downto 0);
    Y0, Y1 : out std_logic_vector(3 downto 0)
  );
end SelectorTwoStack;

architecture arch_SelectorTwoStack of SelectorTwoStack is
begin
  Y1 <= X2 when sel = "110" else
    X1 when sel = "011";
  Y0 <= X1 when sel = "110" else
    X0 when sel = "011";

end arch_SelectorTwoStack;

Projeto03/Calculator/Datapath/StackRegister/StackRegister.vhd
-- O proprio registrador da stack e uma FSM

library IEEE;
use IEEE.std_logic_1164.all;

entity StackRegister is
  port (
    X : in std_logic_vector(3 downto 0);
    load, clear, clk : in std_logic;
    isEmpty : out std_logic;
    Z : out std_logic_vector(3 downto 0)
  );
end StackRegister;

architecture arch_StackRegister of StackRegister is
  type state_type is (HOLD_ST, LOAD_ST, CLEAR_ST);
  attribute ENUM_ENCODING : string;
  attribute ENUM_ENCODING of state_type : type is "00 01 10";
  signal PS, NS : state_type;

  signal Y : std_logic_vector(1 downto 0); -- para os estados da FSM
begin
  sync_process : process (CLK, NS)
  begin
    if (rising_edge(CLK)) then
      PS <= NS;
    end if;
  end process sync_process;

  comb_process : process (PS, load, clear, X)
  begin
    
    case PS is

      when HOLD_ST =>
        if (clear = '1') then
          NS <= CLEAR_ST;
        elsif (load = '1') then
          NS <= LOAD_ST;
        else
          NS <= HOLD_ST;
        end if;

      when LOAD_ST =>
        Z <= X;
        isEmpty <= '0'; 
        NS <= HOLD_ST;

      when CLEAR_ST =>
        Z <= "0000";
        isEmpty <= '1'; 

        if (clear = '0') then
          NS <= HOLD_ST;
        else 
          NS <= CLEAR_ST;
        end if;

      when others => -- catch all, nunca deve chegar aqui
        NS <= HOLD_ST;
    end case;
  end process comb_process;

  -- codificação dos estados Y
  with PS select
    Y <= "00" when HOLD_ST,
    "01" when LOAD_ST,
    "10" when CLEAR_ST,
    "00" when others;
end arch_StackRegister;

Projeto03/Calculator/Datapath/SelectorALU_NUM/SelectorALU_NUM.vhd

library ieee;
use ieee.std_logic_1164.all;
use ieee.numeric_std.all;

entity SelectorALU_NUM is
  port (
    X0, X1 : in std_logic_vector(3 downto 0);
    sel0 : in std_logic;
    sel1 : in std_logic_vector(2 downto 0);
    Y0, Y1, Y2 : out std_logic_vector(3 downto 0)
  );
end SelectorALU_NUM;

architecture arch_SelectorALU_NUM of SelectorALU_NUM is
begin
  Y2 <= X0 when (sel0 = '0' and sel1 = "100") else
    X1 when (sel0 = '1' and sel1 = "100");
  Y1 <= X0 when (sel0 = '0' and sel1 = "010") else
    X1 when (sel0 = '1' and sel1 = "010");
  Y0 <= X0 when (sel0 = '0' and sel1 = "001") else
    X1 when (sel0 = '1' and sel1 = "001");

end arch_SelectorALU_NUM;

Projeto03/Calculator/Datapath/Datapath.vhd
library IEEE;
use IEEE.std_logic_1164.all;

entity Datapath is
  port (
    clk : in std_logic;
    num : in std_logic_vector(3 downto 0);
    opr : in std_logic_vector(1 downto 0);
    sel_alu_num : in std_logic;
    sel_two_stack_pos, sel_stack_pos : in std_logic_vector(2 downto 0);
    clear_stack0, clear_stack1, clear_stack2, load_stack0, load_stack1, load_stack2 : in std_logic;

    isEmpty_stack0, isEmpty_stack1, isEmpty_stack2 : out std_logic;
    result_output : out std_logic_vector(3 downto 0)
  );
end Datapath;

architecture arch_Datapath of Datapath is
  type state_type is (RESET_BOOT, WAIT_ENTER, UPDATE_NUM, WAIT_ENTER_NUM_DOWN, EXECUTE_OPERATION, WAIT_ENTER_OPR_DOWN);
  attribute ENUM_ENCODING : string;
  attribute ENUM_ENCODING of state_type : type is
  "000 001 010 011 100 101";
  signal PS, NS : state_type;
  signal Y : std_logic_vector(2 downto 0); -- signal para os proximos estados da FSM

  -- signals internos do bloco datapath
  signal stack2_in, stack1_in, stack0_in, stack2_out, stack1_out, stack0_out : std_logic_vector(3 downto 0);
  signal alu_num1, alu_num2, result_alu : std_logic_vector(3 downto 0);

  component ALU is
    port (
      OPERATOR : in std_logic_vector(1 downto 0);
      NUM1, NUM2 : in std_logic_vector(3 downto 0);
      RESULT : out std_logic_vector(3 downto 0)
    );
  end component;

  component SelectorALU_NUM is
    port (
      X0, X1 : in std_logic_vector(3 downto 0);
      sel0 : in std_logic;
      sel1 : in std_logic_vector(2 downto 0);
      Y0, Y1, Y2 : out std_logic_vector(3 downto 0)
    );
  end component;

  component SelectorTwoStack is
    port (
      X0, X1, X2 : in std_logic_vector(3 downto 0);
      sel : in std_logic_vector(2 downto 0);
      Y0, Y1 : out std_logic_vector(3 downto 0)
    );
  end component;

  component StackRegister is
    port (
      X : in std_logic_vector(3 downto 0);
      load, clear, clk : in std_logic;
      isEmpty : out std_logic;
      Z : out std_logic_vector(3 downto 0)
    );
  end component;

begin
  inputSelector : SelectorALU_NUM port map(
    X0 => result_alu,
    X1 => num,
    sel0 => sel_alu_num,
    sel1 => sel_stack_pos,
    Y0 => stack0_in,
    Y1 => stack1_in,
    Y2 => stack2_in
  );

  stack0 : StackRegister port map(
    clk => clk,
    X => stack0_in,
    load => load_stack0,
    clear => clear_stack0,
    isEmpty => isEmpty_stack0,
    Z => stack0_out
  );

  stack1 : StackRegister port map(
    clk => clk,
    X => stack1_in,
    load => load_stack1,
    clear => clear_stack1,
    isEmpty => isEmpty_stack1,
    Z => stack1_out
  );

  stack2 : StackRegister port map(
    clk => clk,
    X => stack2_in,
    load => load_stack2,
    clear => clear_stack2,
    isEmpty => isEmpty_stack2,
    Z => stack2_out
  );

  outputSelector : SelectorTwoStack port map(
    X0 => stack0_out,
    X1 => stack1_out,
    X2 => stack2_out,
    sel => sel_two_stack_pos,
    Y0 => alu_num1,
    Y1 => alu_num2
  );

  stackALU : ALU port map(
    OPERATOR => opr,
    NUM1 => alu_num1, 
    NUM2 => alu_num2,
    RESULT => result_alu
  );

  result_output <= alu_num2;

end arch_Datapath;

Projeto03/ControlBlock/ControlBlock.vhd
library IEEE;
use IEEE.std_logic_1164.all;

entity ControlBlock is
  port (
    clk : in std_logic;
    enter_num, enter_opr, reset : in std_logic;
    is_empty0, is_empty1, is_empty2 : in std_logic;
    load_stack0, load_stack1, load_stack2 : out std_logic;
    clear_stack0, clear_stack1, clear_stack2 : out std_logic;
    select_alu_num : out std_logic;
    select_stack_pos, select_two_stack_pos : out std_logic_vector(2 downto 0)
  );
end ControlBlock;

architecture arch_ControlBlock of ControlBlock is
  type state_type is (RESET_BOOT, WAIT_ENTER, UPDATE_NUM, WAIT_ENTER_NUM_DOWN, EXECUTE_OPERATION, WAIT_ENTER_OPR_DOWN);
  attribute ENUM_ENCODING : string;
  attribute ENUM_ENCODING of state_type : type is
  "000 001 010 011 100 101";
  signal PS, NS : state_type;
  signal Y : std_logic_vector(2 downto 0); -- signal para os proximos estados da FSM
begin
  sync_process : process (clk, NS)
  begin
    if (rising_edge(clk)) then
      PS <= NS;
    end if;
  end process sync_process;

  comb_process : process (
    PS, 
    reset,
    enter_num,
    enter_opr,
    reset,
    is_empty0,
    is_empty1,
    is_empty2
  )
  begin
    -- pre-assign saidas, assim nao precisa definir todas em cada estado
    load_stack0 <= '0';
    load_stack1 <= '0';
    load_stack2 <= '0';

    clear_stack0 <= '0';
    clear_stack1 <= '0';
    clear_stack2 <= '0';

    select_alu_num <= '1'; -- seleciona das chaves default
    select_stack_pos <= "100";
    select_two_stack_pos <= "110";

    case PS is
      when RESET_BOOT =>
        if (reset = '1') then
          NS <= RESET_BOOT;
        else
          NS <= WAIT_ENTER;
        end if;

        clear_stack0 <= '1';
        clear_stack1 <= '1';
        clear_stack2 <= '1';

      when WAIT_ENTER =>
        if (reset = '1') then
          NS <= RESET_BOOT;
        elsif (enter_num = '1') then
          NS <= UPDATE_NUM;
        elsif (enter_opr = '1') then
          NS <= EXECUTE_OPERATION;
        else
          NS <= WAIT_ENTER;
        end if;

      when UPDATE_NUM =>
        NS <= WAIT_ENTER_NUM_DOWN;
        select_alu_num <= '1'; -- puxa do num conectado das chaves

        -- identifica a posicao da stack que precisa carregar o conteudo das chaves
        -- e sempre a mais alta que a stack permite
        -- se todas as posicoes estao cheias, nao faz nada (nao adiciona na stack)
        if (is_empty0 = '1') then
          select_stack_pos <= "001";
          select_two_stack_pos <= "011";
          load_stack0 <= '1';
        elsif (is_empty1 = '1') then
          select_stack_pos <= "010";
          select_two_stack_pos <= "011";
          load_stack1 <= '1';
        elsif (is_empty2 = '1') then
          select_stack_pos <= "100";
          select_two_stack_pos <= "110";
          load_stack2 <= '1';
        end if;

      when WAIT_ENTER_NUM_DOWN =>
        if (enter_num = '1') then
          NS <= WAIT_ENTER_NUM_DOWN;
        else
          NS <= WAIT_ENTER;
        end if;

      when EXECUTE_OPERATION =>
        NS <= WAIT_ENTER_OPR_DOWN;
        select_alu_num <= '0'; -- puxa da ALU do datapath

        -- identifica a posicao da stack que precisa carregar o conteudo das chaves
        -- e sempre a mais alta que a stack permite
        -- se todas as posicoes estao cheias, nao faz nada (nao adiciona na stack)
        if (is_empty0 = '1') then
          select_stack_pos <= "001";
          select_two_stack_pos <= "011";
          load_stack0 <= '1';
        elsif (is_empty1 = '1') then
          select_stack_pos <= "010";
          select_two_stack_pos <= "011";
          load_stack1 <= '1';
        elsif (is_empty2 = '1') then
          select_stack_pos <= "100";
          select_two_stack_pos <= "110";
          load_stack2 <= '1';
        end if;

      when WAIT_ENTER_OPR_DOWN =>
        if (enter_opr = '1') then
          NS <= WAIT_ENTER_OPR_DOWN;
        else
          NS <= WAIT_ENTER;
        end if;
        
      when others => -- catch all, nunca deve chegar aqui
        NS <= RESET_BOOT;
    end case;
end process comb_process;

-- codificação dos estados Y
with PS select
  Y <=
    "000" when RESET_BOOT,
    "001" when WAIT_ENTER,
    "010" when UPDATE_NUM,
    "011" when WAIT_ENTER_NUM_DOWN,
    "100" when EXECUTE_OPERATION,
    "101" when WAIT_ENTER_OPR_DOWN,
    "000" when others;
end arch_ControlBlock;

Projeto03/Calculator/Calculator.vhd
library IEEE;
use IEEE.std_logic_1164.all;

entity Calculator is
  port (
    CLK : in std_logic;
    RST, ENTER_NUM, ENTER_OPR : in std_logic;
    NUM : in std_logic_vector(3 downto 0);
    OPR : in std_logic_vector(1 downto 0);
    -- Z0, Z1, Z2, Z3 : out std_logic_vector(0 to 7));
    Z0 : out std_logic_vector(0 to 3)); -- para teste no projeto reduzido
end Calculator;

architecture arch_Calculator of Calculator is
  component ControlBlock is
    port (
      clk : in std_logic;
      enter_num, enter_opr, reset : in std_logic;
      is_empty0, is_empty1, is_empty2 : in std_logic;
      load_stack0, load_stack1, load_stack2 : out std_logic;
      clear_stack0, clear_stack1, clear_stack2 : out std_logic;
      select_alu_num : out std_logic;
      select_stack_pos, select_two_stack_pos : out std_logic_vector(2 downto 0)
    );
  end component;

  component Datapath is
    port (
      clk : in std_logic;
      num : in std_logic_vector(3 downto 0);
      opr : in std_logic_vector(1 downto 0);
      sel_alu_num : in std_logic;
      sel_two_stack_pos, sel_stack_pos : in std_logic_vector(2 downto 0);
      clear_stack0, clear_stack1, clear_stack2, load_stack0, load_stack1, load_stack2 : in std_logic;
  
      isEmpty_stack0, isEmpty_stack1, isEmpty_stack2 : out std_logic;
      result_output : out std_logic_vector(3 downto 0)
    );
  end component;

  -- signals intermediarios (conexao entre os blocos)
  signal interm_is_empty0 : std_logic;
  signal interm_is_empty1 : std_logic;
  signal interm_is_empty2 : std_logic;
  signal interm_load_stack0 : std_logic;
  signal interm_load_stack1 : std_logic;
  signal interm_load_stack2 : std_logic;
  signal interm_clear_stack0 : std_logic;
  signal interm_clear_stack1 : std_logic;
  signal interm_clear_stack2 : std_logic;
  signal interm_select_alu_num : std_logic;
  signal interm_select_stack_pos : std_logic_vector(2 downto 0);
  signal interm_select_two_stack_pos  : std_logic_vector(2 downto 0);

begin
  blocoDeControle : ControlBlock port map(
    clk => CLK,
    enter_num => ENTER_NUM,
    enter_opr => ENTER_OPR,
    reset => RST,

    is_empty0 => interm_is_empty0,
    is_empty1 => interm_is_empty1,
    is_empty2 => interm_is_empty2,
    load_stack0 => interm_load_stack0,
    load_stack1 => interm_load_stack1,
    load_stack2 => interm_load_stack2,
    clear_stack0 => interm_clear_stack0,
    clear_stack1 => interm_clear_stack1,
    clear_stack2 => interm_clear_stack2,
    select_alu_num => interm_select_alu_num,
    select_stack_pos => interm_select_stack_pos,
    select_two_stack_pos => interm_select_two_stack_pos
  );

  blocoOperacional : Datapath port map(
    clk => CLK,
    num => NUM,
    opr => OPR,
    result_output => Z0,

    sel_alu_num => interm_select_alu_num,
    sel_stack_pos => interm_select_stack_pos,
    sel_two_stack_pos => interm_select_two_stack_pos,
    clear_stack0 => interm_clear_stack0,
    clear_stack1 => interm_clear_stack1,
    clear_stack2 => interm_clear_stack2,
    load_stack0 => interm_load_stack0,
    load_stack1 => interm_load_stack1,
    load_stack2 => interm_load_stack2,

    isEmpty_stack0 => interm_is_empty0,
    isEmpty_stack1 => interm_is_empty1,
    isEmpty_stack2 => interm_is_empty2
  );


end arch_Calculator;

Projeto03/ClockDivider/ClockDivider.vhd
-- CLK_COUNTER_MAX = (1/2) * (fi / fo)
-- fi: freq de entrada do clock. fo: freq de saida do clock

library ieee;
use ieee.std_logic_1164.all;
use ieee.numeric_std.all;  

entity ClockDivider is
  generic (
    INPUT_FREQUENCY : integer := 50000000; -- 50MHz default
    OUTPUT_FREQUENCY : integer := 2 -- 2Hz default
  );
  port (
    CLK_INPUT : in std_logic;
    CLK_OUTPUT : out std_logic
  );
end ClockDivider;

architecture arch_ClockDivider of ClockDivider is
  signal CLK_AUX : std_logic := '0';

  -- constantes
  constant CLK_COUNTER_MAX : integer := integer(INPUT_FREQUENCY / (2 * OUTPUT_FREQUENCY));
begin

  process (CLK_INPUT, CLK_AUX)
    variable count : integer range 0 to 2 ** 26 - 1;
  begin
    if (rising_edge(CLK_INPUT)) then
      count := count + 1;
      if (count = CLK_COUNTER_MAX) then
        CLK_AUX <= not CLK_AUX;
        count := 0;
      end if;
    end if;
    CLK_OUTPUT <= CLK_AUX;
  end process;
end arch_ClockDivider;

Projeto03/Projeto03.vhd
library ieee;

use ieee.std_logic_1164.all;
use ieee.numeric_std.all;

entity Projeto03 is
  port (
    CLK_50MHz : in std_logic;
    RST, ENTER_NUM, ENTER_OPR : in std_logic;
    NUM : in std_logic_vector(3 downto 0);
    OPR : in std_logic_vector(1 downto 0);
    -- Z0, Z1, Z2, Z3 : out std_logic_vector(0 to 7));
    Z0 : out std_logic_vector(0 to 3)); -- para teste no projeto reduzido
end Projeto03;

architecture arch_Projeto03 of Projeto03 is
  -- puxa o divisor de clock
  component ClockDivider is
    generic (
      INPUT_FREQUENCY : integer := 50000000; -- 50MHz default
      OUTPUT_FREQUENCY : integer := 2 -- 2Hz default
    );
    port (
      CLK_INPUT : in std_logic;
      CLK_OUTPUT : out std_logic
    );
  end component;

  -- puxa a Calculator
  component Calculator is
    port (
      CLK : in std_logic;
      RST, ENTER_NUM, ENTER_OPR : in std_logic;
      NUM : in std_logic_vector(3 downto 0);
      OPR : in std_logic_vector(1 downto 0);
      -- Z0, Z1, Z2, Z3 : out std_logic_vector(0 to 7));
      Z0 : out std_logic_vector(0 to 3)); -- para teste no projeto reduzido
  end component Calculator;

  -- signals intermediarios (internos ao componente de alto nivel)
  signal INTERNAL_CLK : std_logic;

begin
  my_ClockDivider : ClockDivider 
  generic map(
    INPUT_FREQUENCY => 50000000, -- 50MHz
    OUTPUT_FREQUENCY => 25000000 -- 25MHz  -> PARA TESTBENCH  
    -- OUTPUT_FREQUENCY => 2 -- 2Hz -> PARA FPGA  
  )
  port map(
    CLK_INPUT => CLK_50MHz,
    CLK_OUTPUT => INTERNAL_CLK
  );

  my_Calculator : Calculator port map(
    CLK => INTERNAL_CLK,
    RST => RST,
    ENTER_NUM => ENTER_NUM,
    ENTER_OPR => ENTER_OPR,
    NUM => NUM,
    OPR => OPR,
    Z0 => Z0
    -- Z1 => SAI_Z1,
    -- Z2 => SAI_Z2,
    -- Z3 => SAI_Z3
  );

end arch_Projeto03;

Projeto03/tb_Projeto03.vhd
library IEEE;
use IEEE.STD_LOGIC_1164.all;
use ieee.numeric_std.all;

entity tb_Projeto03 is
end tb_Projeto03;

architecture arch_tb_Projeto03 of tb_Projeto03 is

  component Projeto03 is
    port (
      CLK_50MHz : in std_logic;
      RST, ENTER_NUM, ENTER_OPR : in std_logic;
      NUM : in std_logic_vector(3 downto 0);
      OPR : in std_logic_vector(1 downto 0);
      -- Z0, Z1, Z2, Z3 : out std_logic_vector(0 to 7));
      Z0 : out std_logic_vector(0 to 3)); -- para teste no projeto reduzido
  end component;

  constant PERIODO : time := 20 ns; -- 50 MHz
  signal ENT_CLK : std_logic := '0'; -- deve ser inicializado
  signal ENT_CLK_ENABLE : std_logic := '1'; -- Sinal de Enable do clock só para efeito de controle do fim da simulação


  signal tb_CLK_50MHz : std_logic;
  signal tb_RST, tb_ENTER_NUM, tb_ENTER_OPR : std_logic;
  signal tb_NUM : std_logic_vector(3 downto 0);
  signal tb_OPR : std_logic_vector(1 downto 0);
  -- Z0, Z1, Z2, Z3 : out std_logic_vector(0 to 7));
  signal tb_Z0 : std_logic_vector(0 to 3); -- para teste no projeto reduzido

begin
  -- geração do clock com periodo PERIODO
  ENT_CLK <= ENT_CLK_ENABLE and not ENT_CLK after PERIODO/2;
  ENT_CLK_ENABLE <= '1', '0' after 50 * PERIODO; -- a simulação termina após transcorrer 20 períodos de clock.

  -- instanciação do DUT
  DUT : Projeto03 port map(
    CLK_50MHz => ENT_CLK,
    RST => tb_RST, 
    ENTER_NUM => tb_ENTER_NUM, 
    ENTER_OPR => tb_ENTER_OPR,
    NUM => tb_NUM,
    OPR => tb_OPR,
    Z0 => tb_Z0
  );

  --  process para os estímulos das entradas
  stimulus : process
  begin
    tb_RST <= '0';
    tb_ENTER_NUM <= '0';
    tb_ENTER_OPR<= '0';

    tb_NUM <= "0010";
    tb_OPR <= "00";
    wait for 5 * PERIODO;

    tb_ENTER_NUM <= '1';
    wait for 5 * PERIODO;

    tb_ENTER_NUM <= '0';
    wait for 5 * PERIODO;

    tb_NUM <= "0011";
    wait for 5 * PERIODO;

    tb_ENTER_NUM <= '1';
    wait for 5 * PERIODO;

    tb_ENTER_NUM <= '0';
    wait for 5 * PERIODO;
    
    tb_ENTER_OPR <= '1';
    wait for 10 * PERIODO;

    wait;
  end process stimulus;

end arch_tb_Projeto03;

Projeto03/tb_Projeto03.vcd
$date
  Mon Dec 12 11:16:41 2022
$end
$version
  GHDL v0
$end
$timescale
  1 fs
$end
$scope module standard $end
$upscope $end
$scope module std_logic_1164 $end
$upscope $end
$scope module numeric_std $end
$upscope $end
$scope module tb_projeto03 $end
$var reg 1 ! ent_clk $end
$var reg 1 " ent_clk_enable $end
$var reg 1 # tb_clk_50mhz $end
$var reg 1 $ tb_rst $end
$var reg 1 % tb_enter_num $end
$var reg 1 & tb_enter_opr $end
$var reg 4 ' tb_num[3:0] $end
$var reg 2 ( tb_opr[1:0] $end
$var reg 4 ) tb_z0[0:3] $end
$scope module dut $end
$var reg 1 * clk_50mhz $end
$var reg 1 + rst $end
$var reg 1 , enter_num $end
$var reg 1 - enter_opr $end
$var reg 4 . num[3:0] $end
$var reg 2 / opr[1:0] $end
$var reg 4 0 z0[0:3] $end
$var reg 1 1 internal_clk $end
$scope module my_clockdivider $end
$var reg 1 2 clk_input $end
$var reg 1 3 clk_output $end
$var reg 1 4 clk_aux $end
$upscope $end
$scope module my_calculator $end
$var reg 1 5 clk $end
$var reg 1 6 rst $end
$var reg 1 7 enter_num $end
$var reg 1 8 enter_opr $end
$var reg 4 9 num[3:0] $end
$var reg 2 : opr[1:0] $end
$var reg 4 ; z0[0:3] $end
$var reg 1 < interm_is_empty0 $end
$var reg 1 = interm_is_empty1 $end
$var reg 1 > interm_is_empty2 $end
$var reg 1 ? interm_load_stack0 $end
$var reg 1 @ interm_load_stack1 $end
$var reg 1 A interm_load_stack2 $end
$var reg 1 B interm_clear_stack0 $end
$var reg 1 C interm_clear_stack1 $end
$var reg 1 D interm_clear_stack2 $end
$var reg 1 E interm_select_alu_num $end
$var reg 3 F interm_select_stack_pos[2:0] $end
$var reg 3 G interm_select_two_stack_pos[2:0] $end
$scope module blocodecontrole $end
$var reg 1 H clk $end
$var reg 1 I enter_num $end
$var reg 1 J enter_opr $end
$var reg 1 K reset $end
$var reg 1 L is_empty0 $end
$var reg 1 M is_empty1 $end
$var reg 1 N is_empty2 $end
$var reg 1 O load_stack0 $end
$var reg 1 P load_stack1 $end
$var reg 1 Q load_stack2 $end
$var reg 1 R clear_stack0 $end
$var reg 1 S clear_stack1 $end
$var reg 1 T clear_stack2 $end
$var reg 1 U select_alu_num $end
$var reg 3 V select_stack_pos[2:0] $end
$var reg 3 W select_two_stack_pos[2:0] $end
$comment ps is not handled $end
$comment ns is not handled $end
$var reg 3 X y[2:0] $end
$upscope $end
$scope module blocooperacional $end
$var reg 1 Y clk $end
$var reg 4 Z num[3:0] $end
$var reg 2 [ opr[1:0] $end
$var reg 1 \ sel_alu_num $end
$var reg 3 ] sel_two_stack_pos[2:0] $end
$var reg 3 ^ sel_stack_pos[2:0] $end
$var reg 1 _ clear_stack0 $end
$var reg 1 ` clear_stack1 $end
$var reg 1 a clear_stack2 $end
$var reg 1 b load_stack0 $end
$var reg 1 c load_stack1 $end
$var reg 1 d load_stack2 $end
$var reg 1 e isempty_stack0 $end
$var reg 1 f isempty_stack1 $end
$var reg 1 g isempty_stack2 $end
$var reg 4 h result_output[3:0] $end
$comment ps is not handled $end
$comment ns is not handled $end
$var reg 3 i y[2:0] $end
$var reg 4 j stack2_in[3:0] $end
$var reg 4 k stack1_in[3:0] $end
$var reg 4 l stack0_in[3:0] $end
$var reg 4 m stack2_out[3:0] $end
$var reg 4 n stack1_out[3:0] $end
$var reg 4 o stack0_out[3:0] $end
$var reg 4 p alu_num1[3:0] $end
$var reg 4 q alu_num2[3:0] $end
$var reg 4 r result_alu[3:0] $end
$scope module inputselector $end
$var reg 4 s x0[3:0] $end
$var reg 4 t x1[3:0] $end
$var reg 1 u sel0 $end
$var reg 3 v sel1[2:0] $end
$var reg 4 w y0[3:0] $end
$var reg 4 x y1[3:0] $end
$var reg 4 y y2[3:0] $end
$upscope $end
$scope module stack0 $end
$var reg 4 z x[3:0] $end
$var reg 1 { load $end
$var reg 1 | clear $end
$var reg 1 } clk $end
$var reg 1 !" isempty $end
$var reg 4 "" z[3:0] $end
$comment ps is not handled $end
$comment ns is not handled $end
$var reg 2 #" y[1:0] $end
$upscope $end
$scope module stack1 $end
$var reg 4 $" x[3:0] $end
$var reg 1 %" load $end
$var reg 1 &" clear $end
$var reg 1 '" clk $end
$var reg 1 (" isempty $end
$var reg 4 )" z[3:0] $end
$comment ps is not handled $end
$comment ns is not handled $end
$var reg 2 *" y[1:0] $end
$upscope $end
$scope module stack2 $end
$var reg 4 +" x[3:0] $end
$var reg 1 ," load $end
$var reg 1 -" clear $end
$var reg 1 ." clk $end
$var reg 1 /" isempty $end
$var reg 4 0" z[3:0] $end
$comment ps is not handled $end
$comment ns is not handled $end
$var reg 2 1" y[1:0] $end
$upscope $end
$scope module outputselector $end
$var reg 4 2" x0[3:0] $end
$var reg 4 3" x1[3:0] $end
$var reg 4 4" x2[3:0] $end
$var reg 3 5" sel[2:0] $end
$var reg 4 6" y0[3:0] $end
$var reg 4 7" y1[3:0] $end
$upscope $end
$scope module stackalu $end
$var reg 2 8" operator[1:0] $end
$var reg 4 9" num1[3:0] $end
$var reg 4 :" num2[3:0] $end
$var reg 4 ;" result[3:0] $end
$var reg 4 <" result_interm[3:0] $end
$upscope $end
$upscope $end
$upscope $end
$upscope $end
$upscope $end
$enddefinitions $end
#0
0!
1"
U#
0$
0%
0&
b0010 '
b00 (
bUUUU )
0*
0+
0,
0-
b0010 .
b00 /
bUUUU 0
01
02
03
04
05
06
07
08
b0010 9
b00 :
bUUUU ;
U<
U=
U>
0?
0@
0A
1B
1C
1D
1E
b100 F
b110 G
0H
0I
0J
0K
UL
UM
UN
0O
0P
0Q
1R
1S
1T
1U
b100 V
b110 W
b000 X
0Y
b0010 Z
b00 [
1\
b110 ]
b100 ^
1_
1`
1a
0b
0c
0d
Ue
Uf
Ug
bUUUU h
bUUU i
b0010 j
bUUUU k
bUUUU l
bUUUU m
bUUUU n
bUUUU o
bUUUU p
bUUUU q
bXXXX r
bXXXX s
b0010 t
1u
b100 v
bUUUU w
bUUUU x
b0010 y
bUUUU z
0{
1|
0}
U!"
bUUUU ""
b00 #"
bUUUU $"
0%"
1&"
0'"
U("
bUUUU )"
b00 *"
b0010 +"
0,"
1-"
0."
U/"
bUUUU 0"
b00 1"
bUUUU 2"
bUUUU 3"
bUUUU 4"
b110 5"
bUUUU 6"
bUUUU 7"
b00 8"
bUUUU 9"
bUUUU :"
bXXXX ;"
bXXXX <"
#10000000
1!
b0000 )
1*
b0000 0
11
12
13
14
15
b0000 ;
1<
1=
1>
0B
0C
0D
1H
1L
1M
1N
0R
0S
0T
b001 X
1Y
0_
0`
0a
1e
1f
1g
b0000 h
b0000 m
b0000 n
b0000 o
b0000 p
b0000 q
b0000 r
b0000 s
0|
1}
1!"
b0000 ""
b10 #"
0&"
1'"
1("
b0000 )"
b10 *"
0-"
1."
1/"
b0000 0"
b10 1"
b0000 2"
b0000 3"
b0000 4"
b0000 6"
b0000 7"
b0000 9"
b0000 :"
b0000 ;"
b0000 <"
#20000000
0!
0*
02
#30000000
1!
1*
01
12
03
04
05
0H
0Y
0}
0'"
0."
#40000000
0!
0*
02
#50000000
1!
1*
11
12
13
14
15
1H
1Y
1}
b00 #"
1'"
b00 *"
1."
b00 1"
#60000000
0!
0*
02
#70000000
1!
1*
01
12
03
04
05
0H
0Y
0}
0'"
0."
#80000000
0!
0*
02
#90000000
1!
1*
11
12
13
14
15
1H
1Y
1}
1'"
1."
#100000000
0!
1%
0*
1,
02
17
1I
#110000000
1!
1*
01
12
03
04
05
0H
0Y
0}
0'"
0."
#120000000
0!
0*
02
#130000000
1!
1*
11
12
13
14
15
1?
b001 F
b011 G
1H
1O
b001 V
b011 W
b010 X
1Y
b011 ]
b001 ^
1b
b0010 l
b001 v
b0010 w
b0010 z
1{
1}
1'"
1."
b011 5"
#140000000
0!
0*
02
#150000000
1!
1*
01
12
03
04
05
0H
0Y
0}
0'"
0."
#160000000
0!
0*
02
#170000000
1!
1*
11
12
13
14
15
0<
0?
b100 F
b110 G
1H
0L
0O
b100 V
b110 W
b011 X
1Y
b110 ]
b100 ^
0b
0e
b0010 o
b100 v
0{
1}
0!"
b0010 ""
b01 #"
1'"
1."
b0010 2"
b110 5"
#180000000
0!
0*
02
#190000000
1!
1*
01
12
03
04
05
0H
0Y
0}
0'"
0."
#200000000
0!
0%
0*
0,
02
07
0I
#210000000
1!
1*
11
12
13
14
15
1H
b001 X
1Y
1}
b00 #"
1'"
1."
#220000000
0!
0*
02
#230000000
1!
1*
01
12
03
04
05
0H
0Y
0}
0'"
0."
#240000000
0!
0*
02
#250000000
1!
1*
11
12
13
14
15
1H
1Y
1}
1'"
1."
#260000000
0!
0*
02
#270000000
1!
1*
01
12
03
04
05
0H
0Y
0}
0'"
0."
#280000000
0!
0*
02
#290000000
1!
1*
11
12
13
14
15
1H
1Y
1}
1'"
1."
#300000000
0!
b0011 '
0*
b0011 .
02
b0011 9
b0011 Z
b0011 j
b0011 t
b0011 y
b0011 +"
#310000000
1!
1*
01
12
03
04
05
0H
0Y
0}
0'"
0."
#320000000
0!
0*
02
#330000000
1!
1*
11
12
13
14
15
1H
1Y
1}
1'"
1."
#340000000
0!
0*
02
#350000000
1!
1*
01
12
03
04
05
0H
0Y
0}
0'"
0."
#360000000
0!
0*
02
#370000000
1!
1*
11
12
13
14
15
1H
1Y
1}
1'"
1."
#380000000
0!
0*
02
#390000000
1!
1*
01
12
03
04
05
0H
0Y
0}
0'"
0."
#400000000
0!
1%
0*
1,
02
17
1I
#410000000
1!
b0010 )
1*
b0010 0
11
12
13
14
15
b0010 ;
1@
b010 F
b011 G
1H
1P
b010 V
b011 W
b010 X
1Y
b011 ]
b010 ^
1c
b0010 h
b0011 k
b0010 p
b0010 r
b0010 s
b010 v
b0011 x
1}
b0011 $"
1%"
1'"
1."
b011 5"
b0010 6"
b0010 9"
b0010 ;"
b0010 <"
#420000000
0!
0*
02
#430000000
1!
1*
01
12
03
04
05
0H
0Y
0}
0'"
0."
#440000000
0!
0*
02
