Projeto03/Calculator/Calculator.vhd
library IEEE;
use IEEE.std_logic_1164.all;

entity Calculator is
  port (
    CLK : in std_logic;
    RST : in std_logic; -- entrada da FSM
    Z0, Z1, Z2, Z3, Z4, Z5 : out std_logic_vector(0 to 7)); -- saidas efetivas da FSM
end Calculator;

architecture arch_Calculator of Calculator is
  type state_type is (ST0, ST1, ST2, ST3, ST4, ST5, ST6, ST7, ST8, ST9, ST10, ST11, ST12, ST13, ST14, ST15, ST16, ST17, ST18, ST19, ST20, ST21);
  attribute ENUM_ENCODING : string;
  attribute ENUM_ENCODING of state_type : type is
  "00000 00001 00010 00011 00100 00101 00110 00111 01000 01001 01010 01011 01100 01101 01110 01111 10000 10001 10010 10011 10100 10101";
  signal PS, NS : state_type;
  signal Y : std_logic_vector(4 downto 0); -- signal para os proximos estados da FSM
begin
  sync_process : process (CLK, NS)
  begin
    if (rising_edge(CLK)) then
      PS <= NS;
    end if;
  end process sync_process;

  comb_process : process (PS, RST)
  begin
    -- pre-assign saidas, assim nao precisa definir todas em cada estado
    Z0 <= "11111111";
    Z1 <= "11111111";
    Z2 <= "11111111";
    Z3 <= "11111111";
    Z4 <= "11111111";
    Z5 <= "11111111";

    -- condicao de RESET e a mesma para todos os estados, pode ir fora dos CASES
    if (RST /= '0') then
      NS <= ST0;
      Z0 <= "10111111";
    else
      case PS is
        when ST0 =>
          NS <= ST1;
          Z0 <= "10111111";

        when ST1 =>
          NS <= ST2;
          Z0 <= "01111111";

        when ST2 =>
          NS <= ST3;
          Z1 <= "01111111";

        when ST3 =>
          NS <= ST4;
          Z2 <= "01111111";

        when ST4 =>
          NS <= ST5;
          Z3 <= "01111111";

        when ST5 =>
          NS <= ST6;
          Z4 <= "01111111";

        when ST6 =>
          NS <= ST7;
          Z5 <= "01111111";

        when ST7 =>
          NS <= ST8;
          Z5 <= "11111011";

        when ST8 =>
          NS <= ST9;
          Z5 <= "11110111";

        when ST9 =>
          NS <= ST10;
          Z5 <= "11101111";

        when ST10 =>
          NS <= ST11;
          Z4 <= "11101111";

        when ST11 =>
          NS <= ST12;
          Z3 <= "11101111";

        when ST12 =>
          NS <= ST13;
          Z2 <= "11101111";

        when ST13 =>
          NS <= ST14;
          Z1 <= "11101111";

        when ST14 =>
          NS <= ST15;
          Z0 <= "11101111";

        when ST15 =>
          NS <= ST16;
          Z0 <= "11011111";

        when ST16 =>
          NS <= ST17;
          Z0 <= "11111101";

        when ST17 =>
          NS <= ST18;
          Z1 <= "11111101";

        when ST18 =>
          NS <= ST19;
          Z2 <= "11111101";

        when ST19 =>
          NS <= ST20;
          Z3 <= "11111101";

        when ST20 =>
          NS <= ST21;
          Z4 <= "11111101";

        when ST21 =>
          NS <= ST0;
          Z5 <= "11111101";

        when others => -- catch all, nunca deve chegar aqui
          NS <= ST0;
          Z0 <= "10111111";
      end case;
    end if;
  end process comb_process;

  -- codificação dos estados Y
  with PS select
    Y <=
    "00000" when ST0,
    "00001" when ST1,
    "00010" when ST2,
    "00011" when ST3,
    "00100" when ST4,
    "00101" when ST5,
    "00110" when ST6,
    "00111" when ST7,
    "01000" when ST8,
    "01001" when ST9,
    "01010" when ST10,
    "01011" when ST11,
    "01100" when ST12,
    "01101" when ST13,
    "01110" when ST14,
    "01111" when ST15,
    "10000" when ST16,
    "10001" when ST17,
    "10010" when ST18,
    "10011" when ST19,
    "10100" when ST20,
    "10101" when ST21,
    "00000" when others;
end arch_Calculator;

Projeto03/ClockDivider/ClockDivider.vhd
-- CLK_COUNTER_MAX = (1/2) * (fi / fo)
-- fi: freq de entrada do clock. fo: freq de saida do clock

library ieee;
use ieee.std_logic_1164.all;
use ieee.numeric_std.all;  

entity ClockDivider is
  generic (
    INPUT_FREQUENCY : integer := 50000000; -- 50MHz default
    OUTPUT_FREQUENCY : integer := 2 -- 2Hz default
  );
  port (
    CLK_INPUT : in std_logic;
    CLK_OUTPUT : out std_logic
  );
end ClockDivider;

architecture arch_ClockDivider of ClockDivider is
  signal CLK_AUX : std_logic := '0';

  -- constantes
  constant CLK_COUNTER_MAX : integer := integer(INPUT_FREQUENCY / (2 * OUTPUT_FREQUENCY));
begin

  process (CLK_INPUT, CLK_AUX)
    variable count : integer range 0 to 2 ** 26 - 1;
  begin
    if (rising_edge(CLK_INPUT)) then
      count := count + 1;
      if (count = CLK_COUNTER_MAX) then
        CLK_AUX <= not CLK_AUX;
        count := 0;
      end if;
    end if;
    CLK_OUTPUT <= CLK_AUX;
  end process;
end arch_ClockDivider;

Projeto03/Projeto03.vhd
library ieee;

use ieee.std_logic_1164.all;
use ieee.numeric_std.all;

entity Projeto03 is
  port (
    CLK_50MHz, RESET : in std_logic;
    DISP0, DISP1, DISP2, DISP3, DISP4, DISP5 : out std_logic_vector(0 to 7)
  );
end Projeto03;

architecture arch_Projeto03 of Projeto03 is
  -- puxa o divisor de clock
  component ClockDivider is
    generic (
      INPUT_FREQUENCY : integer := 50000000; -- 50MHz default
      OUTPUT_FREQUENCY : integer := 2 -- 2Hz default
    );
    port (
      CLK_INPUT : in std_logic;
      CLK_OUTPUT : out std_logic
    );
  end component;

  -- puxa a Calculator
  component Calculator is
    port (
      CLK : in std_logic;
      RST : in std_logic; -- entrada da FSM
      Z0, Z1, Z2, Z3, Z4, Z5 : out std_logic_vector(0 to 7)); -- saidas efetivas da FSM
  end component Calculator;

  -- signals intermediarios (internos ao componente de alto nivel)
  signal INTERNAL_CLK : std_logic;

begin
  my_ClockDivider : ClockDivider 
  generic map(
    INPUT_FREQUENCY => 50000000, -- 50MHz
    OUTPUT_FREQUENCY => 5000000 -- 5MHz  -> PARA TESTBENCH  
    -- OUTPUT_FREQUENCY => 2 -- 2Hz -> PARA FPGA  
  )
  port map(
    CLK_INPUT => CLK_50MHz,
    CLK_OUTPUT => INTERNAL_CLK
  );

  my_Calculator : Calculator port map(
    CLK => INTERNAL_CLK,
    RST => RESET,
    Z0 => DISP0,
    Z1 => DISP1,
    Z2 => DISP2,
    Z3 => DISP3,
    Z4 => DISP4,
    Z5 => DISP5
  );

end arch_Projeto03;

Projeto03/tb_Projeto03.vhd
library IEEE;
use IEEE.STD_LOGIC_1164.all;
use ieee.numeric_std.all;

entity tb_Projeto03 is
end tb_Projeto03;

architecture arch_tb_Projeto03 of tb_Projeto03 is

  component Projeto03 is
    port (
      CLK_50MHz, RESET : in std_logic;
      DISP0, DISP1, DISP2, DISP3, DISP4, DISP5 : out std_logic_vector(0 to 7)
    );
  end component;

  constant PERIODO : time := 20 ns; -- 50 MHz
  signal ENT_CLK : std_logic := '0'; -- deve ser inicializado
  signal ENT_CLK_ENABLE : std_logic := '1'; -- Sinal de Enable do clock só para efeito de controle do fim da simulação
  signal SAI_DISP0, SAI_DISP1, SAI_DISP2, SAI_DISP3, SAI_DISP4, SAI_DISP5 : std_logic_vector(0 to 7);
  signal ENT_RESET : std_logic;

begin
  -- geração do clock com periodo PERIODO
  ENT_CLK <= ENT_CLK_ENABLE and not ENT_CLK after PERIODO/2;
  ENT_CLK_ENABLE <= '1', '0' after 300 * PERIODO; -- a simulação termina após transcorrer 20 períodos de clock.

  -- instanciação do DUT
  DUT : Projeto03 port map(
    CLK_50MHz => ENT_CLK,
    RESET => ENT_RESET,
    DISP0 => SAI_DISP0,
    DISP1 => SAI_DISP1,
    DISP2 => SAI_DISP2,
    DISP3 => SAI_DISP3,
    DISP4 => SAI_DISP4,
    DISP5 => SAI_DISP5
  );

  --  process para os estímulos das entradas
  stimulus : process
  begin
    ENT_RESET <= '0';
    wait for 220 * PERIODO;
    ENT_RESET <= '1';
    wait for 15 * PERIODO;
    ENT_RESET <= '0';

    wait;
  end process stimulus;

end arch_tb_Projeto03;

Projeto03/tb_Projeto03.vcd
$date
  Tue Dec 06 15:32:04 2022
$end
$version
  GHDL v0
$end
$timescale
  1 fs
$end
$scope module standard $end
$upscope $end
$scope module std_logic_1164 $end
$upscope $end
$scope module numeric_std $end
$upscope $end
$scope module tb_projeto03 $end
$var reg 1 ! ent_clk $end
$var reg 1 " ent_clk_enable $end
$var reg 8 # sai_disp0[0:7] $end
$var reg 8 $ sai_disp1[0:7] $end
$var reg 8 % sai_disp2[0:7] $end
$var reg 8 & sai_disp3[0:7] $end
$var reg 8 ' sai_disp4[0:7] $end
$var reg 8 ( sai_disp5[0:7] $end
$var reg 1 ) ent_reset $end
$scope module dut $end
$var reg 1 * clk_50mhz $end
$var reg 1 + reset $end
$var reg 8 , disp0[0:7] $end
$var reg 8 - disp1[0:7] $end
$var reg 8 . disp2[0:7] $end
$var reg 8 / disp3[0:7] $end
$var reg 8 0 disp4[0:7] $end
$var reg 8 1 disp5[0:7] $end
$var reg 1 2 internal_clk $end
$scope module my_clockdivider $end
$var reg 1 3 clk_input $end
$var reg 1 4 clk_output $end
$var reg 1 5 clk_aux $end
$upscope $end
$scope module my_calculator $end
$var reg 1 6 clk $end
$var reg 1 7 rst $end
$var reg 8 8 z0[0:7] $end
$var reg 8 9 z1[0:7] $end
$var reg 8 : z2[0:7] $end
$var reg 8 ; z3[0:7] $end
$var reg 8 < z4[0:7] $end
$var reg 8 = z5[0:7] $end
$comment ps is not handled $end
$comment ns is not handled $end
$var reg 5 > y[4:0] $end
$upscope $end
$upscope $end
$upscope $end
$enddefinitions $end
#0
0!
1"
b10111111 #
b11111111 $
b11111111 %
b11111111 &
b11111111 '
b11111111 (
0)
0*
0+
b10111111 ,
b11111111 -
b11111111 .
b11111111 /
b11111111 0
b11111111 1
02
03
04
05
06
07
b10111111 8
b11111111 9
b11111111 :
b11111111 ;
b11111111 <
b11111111 =
b00000 >
#10000000
1!
1*
13
#20000000
0!
0*
03
#30000000
1!
1*
13
#40000000
0!
0*
03
#50000000
1!
1*
13
#60000000
0!
0*
03
#70000000
1!
1*
13
#80000000
0!
0*
03
#90000000
1!
b01111111 #
1*
b01111111 ,
12
13
14
15
16
b01111111 8
b00001 >
#100000000
0!
0*
03
#110000000
1!
1*
13
#120000000
0!
0*
03
#130000000
1!
1*
13
#140000000
0!
0*
03
#150000000
1!
1*
13
#160000000
0!
0*
03
#170000000
1!
1*
13
#180000000
0!
0*
03
#190000000
1!
1*
02
13
04
05
06
#200000000
0!
0*
03
#210000000
1!
1*
13
#220000000
0!
0*
03
#230000000
1!
1*
13
#240000000
0!
0*
03
#250000000
1!
1*
13
#260000000
0!
0*
03
#270000000
1!
1*
13
#280000000
0!
0*
03
#290000000
1!
b11111111 #
b01111111 $
1*
b11111111 ,
b01111111 -
12
13
14
15
16
b11111111 8
b01111111 9
b00010 >
#300000000
0!
0*
03
#310000000
1!
1*
13
#320000000
0!
0*
03
#330000000
1!
1*
13
#340000000
0!
0*
03
#350000000
1!
1*
13
#360000000
0!
0*
03
#370000000
1!
1*
13
#380000000
0!
0*
03
#390000000
1!
1*
02
13
04
05
06
#400000000
0!
0*
03
#410000000
1!
1*
13
#420000000
0!
0*
03
#430000000
1!
1*
13
#440000000
0!
0*
03
#450000000
1!
1*
13
#460000000
0!
0*
03
#470000000
1!
1*
13
#480000000
0!
0*
03
#490000000
1!
b11111111 $
b01111111 %
1*
b11111111 -
b01111111 .
12
13
14
15
16
b11111111 9
b01111111 :
b00011 >
#500000000
0!
0*
03
#510000000
1!
1*
13
#520000000
0!
0*
03
#530000000
1!
1*
13
#540000000
0!
0*
03
#550000000
1!
1*
13
#560000000
0!
0*
03
#570000000
1!
1*
13
#580000000
0!
0*
03
#590000000
1!
1*
02
13
04
05
06
#600000000
0!
0*
03
#610000000
1!
1*
13
#620000000
0!
0*
03
#630000000
1!
1*
13
#640000000
0!
0*
03
#650000000
1!
1*
13
#660000000
0!
0*
03
#670000000
1!
1*
13
#680000000
0!
0*
03
#690000000
1!
b11111111 %
b01111111 &
1*
b11111111 .
b01111111 /
12
13
14
15
16
b11111111 :
b01111111 ;
b00100 >
#700000000
0!
0*
03
#710000000
1!
1*
13
#720000000
0!
0*
03
#730000000
1!
1*
13
#740000000
0!
0*
03
#750000000
1!
1*
13
#760000000
0!
0*
03
#770000000
1!
1*
13
#780000000
0!
0*
03
#790000000
1!
1*
02
13
04
05
06
#800000000
0!
0*
03
#810000000
1!
1*
13
#820000000
0!
0*
03
#830000000
1!
1*
13
#840000000
0!
0*
03
#850000000
1!
1*
13
#860000000
0!
0*
03
#870000000
1!
1*
13
#880000000
0!
0*
03
#890000000
1!
b11111111 &
b01111111 '
1*
b11111111 /
b01111111 0
12
13
14
15
16
b11111111 ;
b01111111 <
b00101 >
#900000000
0!
0*
03
#910000000
1!
1*
13
#920000000
0!
0*
03
#930000000
1!
1*
13
#940000000
0!
0*
03
#950000000
1!
1*
13
#960000000
0!
0*
03
#970000000
1!
1*
13
#980000000
0!
0*
03
#990000000
1!
1*
02
13
04
05
06
#1000000000
0!
0*
03
#1010000000
1!
1*
13
#1020000000
0!
0*
03
#1030000000
1!
1*
13
#1040000000
0!
0*
03
#1050000000
1!
1*
13
#1060000000
0!
0*
03
#1070000000
1!
1*
13
#1080000000
0!
0*
03
#1090000000
1!
b11111111 '
b01111111 (
1*
b11111111 0
b01111111 1
12
13
14
15
16
b11111111 <
b01111111 =
b00110 >
#1100000000
0!
0*
03
#1110000000
1!
1*
13
#1120000000
0!
0*
03
#1130000000
1!
1*
13
#1140000000
0!
0*
03
#1150000000
1!
1*
13
#1160000000
0!
0*
03
#1170000000
1!
1*
13
#1180000000
0!
0*
03
#1190000000
1!
1*
02
13
04
05
06
#1200000000
0!
0*
03
#1210000000
1!
1*
13
#1220000000
0!
0*
03
#1230000000
1!
1*
13
#1240000000
0!
0*
03
#1250000000
1!
1*
13
#1260000000
0!
0*
03
#1270000000
1!
1*
13
#1280000000
0!
0*
03
#1290000000
1!
b11111011 (
1*
b11111011 1
12
13
14
15
16
b11111011 =
b00111 >
#1300000000
0!
0*
03
#1310000000
1!
1*
13
#1320000000
0!
0*
03
#1330000000
1!
1*
13
#1340000000
0!
0*
03
#1350000000
1!
1*
13
#1360000000
0!
0*
03
#1370000000
1!
1*
13
#1380000000
0!
0*
03
#1390000000
1!
1*
02
13
04
05
06
#1400000000
0!
0*
03
#1410000000
1!
1*
13
#1420000000
0!
0*
03
#1430000000
1!
1*
13
#1440000000
0!
0*
03
#1450000000
1!
1*
13
#1460000000
0!
0*
03
#1470000000
1!
1*
13
#1480000000
0!
0*
03
#1490000000
1!
b11110111 (
1*
b11110111 1
12
13
14
15
16
b11110111 =
b01000 >
#1500000000
0!
0*
03
#1510000000
1!
1*
13
#1520000000
0!
0*
03
#1530000000
1!
1*
13
#1540000000
0!
0*
03
#1550000000
1!
1*
13
#1560000000
0!
0*
03
#1570000000
1!
1*
13
#1580000000
0!
0*
03
#1590000000
1!
1*
02
13
04
05
06
#1600000000
0!
0*
03
#1610000000
1!
1*
13
#1620000000
0!
0*
03
#1630000000
1!
1*
13
#1640000000
0!
0*
03
#1650000000
1!
1*
13
#1660000000
0!
0*
03
#1670000000
1!
1*
13
#1680000000
0!
0*
03
#1690000000
1!
b11101111 (
1*
b11101111 1
12
13
14
15
16
b11101111 =
b01001 >
#1700000000
0!
0*
03
#1710000000
1!
1*
13
#1720000000
0!
0*
03
#1730000000
1!
1*
13
#1740000000
0!
0*
03
#1750000000
1!
1*
13
#1760000000
0!
0*
03
#1770000000
1!
1*
13
#1780000000
0!
0*
03
#1790000000
1!
1*
02
13
04
05
06
#1800000000
0!
0*
03
#1810000000
1!
1*
13
#1820000000
0!
0*
03
#1830000000
1!
1*
13
#1840000000
0!
0*
03
#1850000000
1!
1*
13
#1860000000
0!
0*
03
#1870000000
1!
1*
13
#1880000000
0!
0*
03
#1890000000
1!
b11101111 '
b11111111 (
1*
b11101111 0
b11111111 1
12
13
14
15
16
b11101111 <
b11111111 =
b01010 >
#1900000000
0!
0*
03
#1910000000
1!
1*
13
#1920000000
0!
0*
03
#1930000000
1!
1*
13
#1940000000
0!
0*
03
#1950000000
1!
1*
13
#1960000000
0!
0*
03
#1970000000
1!
1*
13
#1980000000
0!
0*
03
#1990000000
1!
1*
02
13
04
05
06
#2000000000
0!
0*
03
#2010000000
1!
1*
13
#2020000000
0!
0*
03
#2030000000
1!
1*
13
#2040000000
0!
0*
03
#2050000000
1!
1*
13
#2060000000
0!
0*
03
#2070000000
1!
1*
13
#2080000000
0!
0*
03
#2090000000
1!
b11101111 &
b11111111 '
1*
b11101111 /
b11111111 0
12
13
14
15
16
b11101111 ;
b11111111 <
b01011 >
#2100000000
0!
0*
03
#2110000000
1!
1*
13
#2120000000
0!
0*
03
#2130000000
1!
1*
13
#2140000000
0!
0*
03
#2150000000
1!
1*
13
#2160000000
0!
0*
03
#2170000000
1!
1*
13
#2180000000
0!
0*
03
#2190000000
1!
1*
02
13
04
05
06
#2200000000
0!
0*
03
#2210000000
1!
1*
13
#2220000000
0!
0*
03
#2230000000
1!
1*
13
#2240000000
0!
0*
03
#2250000000
1!
1*
13
#2260000000
0!
0*
03
#2270000000
1!
1*
13
#2280000000
0!
0*
03
#2290000000
1!
b11101111 %
b11111111 &
1*
b11101111 .
b11111111 /
12
13
14
15
16
b11101111 :
b11111111 ;
b01100 >
#2300000000
0!
0*
03
#2310000000
1!
1*
13
#2320000000
0!
0*
03
#2330000000
1!
1*
13
#2340000000
0!
0*
03
#2350000000
1!
1*
13
#2360000000
0!
0*
03
#2370000000
1!
1*
13
#2380000000
0!
0*
03
#2390000000
1!
1*
02
13
04
05
06
#2400000000
0!
0*
03
#2410000000
1!
1*
13
#2420000000
0!
0*
03
#2430000000
1!
1*
13
#2440000000
0!
0*
03
#2450000000
1!
1*
13
#2460000000
0!
0*
03
#2470000000
1!
1*
13
#2480000000
0!
0*
03
#2490000000
1!
b11101111 $
b11111111 %
1*
b11101111 -
b11111111 .
12
13
14
15
16
b11101111 9
b11111111 :
b01101 >
#2500000000
0!
0*
03
#2510000000
1!
1*
13
#2520000000
0!
0*
03
#2530000000
1!
1*
13
#2540000000
0!
0*
03
#2550000000
1!
1*
13
#2560000000
0!
0*
03
#2570000000
1!
1*
13
#2580000000
0!
0*
03
#2590000000
1!
1*
02
13
04
05
06
#2600000000
0!
0*
03
#2610000000
1!
1*
13
#2620000000
0!
0*
03
#2630000000
1!
1*
13
#2640000000
0!
0*
03
#2650000000
1!
1*
13
#2660000000
0!
0*
03
#2670000000
1!
1*
13
#2680000000
0!
0*
03
#2690000000
1!
b11101111 #
b11111111 $
1*
b11101111 ,
b11111111 -
12
13
14
15
16
b11101111 8
b11111111 9
b01110 >
#2700000000
0!
0*
03
#2710000000
1!
1*
13
#2720000000
0!
0*
03
#2730000000
1!
1*
13
#2740000000
0!
0*
03
#2750000000
1!
1*
13
#2760000000
0!
0*
03
#2770000000
1!
1*
13
#2780000000
0!
0*
03
#2790000000
1!
1*
02
13
04
05
06
#2800000000
0!
0*
03
#2810000000
1!
1*
13
#2820000000
0!
0*
03
#2830000000
1!
1*
13
#2840000000
0!
0*
03
#2850000000
1!
1*
13
#2860000000
0!
0*
03
#2870000000
1!
1*
13
#2880000000
0!
0*
03
#2890000000
1!
b11011111 #
1*
b11011111 ,
12
13
14
15
16
b11011111 8
b01111 >
#2900000000
0!
0*
03
#2910000000
1!
1*
13
#2920000000
0!
0*
03
#2930000000
1!
1*
13
#2940000000
0!
0*
03
#2950000000
1!
1*
13
#2960000000
0!
0*
03
#2970000000
1!
1*
13
#2980000000
0!
0*
03
#2990000000
1!
1*
02
13
04
05
06
#3000000000
0!
0*
03
#3010000000
1!
1*
13
#3020000000
0!
0*
03
#3030000000
1!
1*
13
#3040000000
0!
0*
03
#3050000000
1!
1*
13
#3060000000
0!
0*
03
#3070000000
1!
1*
13
#3080000000
0!
0*
03
#3090000000
1!
b11111101 #
1*
b11111101 ,
12
13
14
15
16
b11111101 8
b10000 >
#3100000000
0!
0*
03
#3110000000
1!
1*
13
#3120000000
0!
0*
03
#3130000000
1!
1*
13
#3140000000
0!
0*
03
#3150000000
1!
1*
13
#3160000000
0!
0*
03
#3170000000
1!
1*
13
#3180000000
0!
0*
03
#3190000000
1!
1*
02
13
04
05
06
#3200000000
0!
0*
03
#3210000000
1!
1*
13
#3220000000
0!
0*
03
#3230000000
1!
1*
13
#3240000000
0!
0*
03
#3250000000
1!
1*
13
#3260000000
0!
0*
03
#3270000000
1!
1*
13
#3280000000
0!
0*
03
#3290000000
1!
b11111111 #
b11111101 $
1*
b11111111 ,
b11111101 -
12
13
14
15
16
b11111111 8
b11111101 9
b10001 >
#3300000000
0!
0*
03
#3310000000
1!
1*
13
#3320000000
0!
0*
03
#3330000000
1!
1*
13
#3340000000
0!
0*
03
#3350000000
1!
1*
13
#3360000000
0!
0*
03
#3370000000
1!
1*
13
#3380000000
0!
0*
03
#3390000000
1!
1*
02
13
04
05
06
#3400000000
0!
0*
03
#3410000000
1!
1*
13
#3420000000
0!
0*
03
#3430000000
1!
1*
13
#3440000000
0!
0*
03
#3450000000
1!
1*
13
#3460000000
0!
0*
03
#3470000000
1!
1*
13
#3480000000
0!
0*
03
#3490000000
1!
b11111111 $
b11111101 %
1*
b11111111 -
b11111101 .
12
13
14
15
16
b11111111 9
b11111101 :
b10010 >
#3500000000
0!
0*
03
#3510000000
1!
1*
13
#3520000000
0!
0*
03
#3530000000
1!
1*
13
#3540000000
0!
0*
03
#3550000000
1!
1*
13
#3560000000
0!
0*
03
#3570000000
1!
1*
13
#3580000000
0!
0*
03
#3590000000
1!
1*
02
13
04
05
06
#3600000000
0!
0*
03
#3610000000
1!
1*
13
#3620000000
0!
0*
03
#3630000000
1!
1*
13
#3640000000
0!
0*
03
#3650000000
1!
1*
13
#3660000000
0!
0*
03
#3670000000
1!
1*
13
#3680000000
0!
0*
03
#3690000000
1!
b11111111 %
b11111101 &
1*
b11111111 .
b11111101 /
12
13
14
15
16
b11111111 :
b11111101 ;
b10011 >
#3700000000
0!
0*
03
#3710000000
1!
1*
13
#3720000000
0!
0*
03
#3730000000
1!
1*
13
#3740000000
0!
0*
03
#3750000000
1!
1*
13
#3760000000
0!
0*
03
#3770000000
1!
1*
13
#3780000000
0!
0*
03
#3790000000
1!
1*
02
13
04
05
06
#3800000000
0!
0*
03
#3810000000
1!
1*
13
#3820000000
0!
0*
03
#3830000000
1!
1*
13
#3840000000
0!
0*
03
#3850000000
1!
1*
13
#3860000000
0!
0*
03
#3870000000
1!
1*
13
#3880000000
0!
0*
03
#3890000000
1!
b11111111 &
b11111101 '
1*
b11111111 /
b11111101 0
12
13
14
15
16
b11111111 ;
b11111101 <
b10100 >
#3900000000
0!
0*
03
#3910000000
1!
1*
13
#3920000000
0!
0*
03
#3930000000
1!
1*
13
#3940000000
0!
0*
03
#3950000000
1!
1*
13
#3960000000
0!
0*
03
#3970000000
1!
1*
13
#3980000000
0!
0*
03
#3990000000
1!
1*
02
13
04
05
06
#4000000000
0!
0*
03
#4010000000
1!
1*
13
#4020000000
0!
0*
03
#4030000000
1!
1*
13
#4040000000
0!
0*
03
#4050000000
1!
1*
13
#4060000000
0!
0*
03
#4070000000
1!
1*
13
#4080000000
0!
0*
03
#4090000000
1!
b11111111 '
b11111101 (
1*
b11111111 0
b11111101 1
12
13
14
15
16
b11111111 <
b11111101 =
b10101 >
#4100000000
0!
0*
03
#4110000000
1!
1*
13
#4120000000
0!
0*
03
#4130000000
1!
1*
13
#4140000000
0!
0*
03
#4150000000
1!
1*
13
#4160000000
0!
0*
03
#4170000000
1!
1*
13
#4180000000
0!
0*
03
#4190000000
1!
1*
02
13
04
05
06
#4200000000
0!
0*
03
#4210000000
1!
1*
13
#4220000000
0!
0*
03
#4230000000
1!
1*
13
#4240000000
0!
0*
03
#4250000000
1!
1*
13
#4260000000
0!
0*
03
#4270000000
1!
1*
13
#4280000000
0!
0*
03
#4290000000
1!
b10111111 #
b11111111 (
1*
b10111111 ,
b11111111 1
12
13
14
15
16
b10111111 8
b11111111 =
b00000 >
#4300000000
0!
0*
03
#4310000000
1!
1*
13
#4320000000
0!
0*
03
#4330000000
1!
1*
13
#4340000000
0!
0*
03
#4350000000
1!
1*
13
#4360000000
0!
0*
03
#4370000000
1!
1*
13
#4380000000
0!
0*
03
#4390000000
1!
1*
02
13
04
05
06
#4400000000
0!
1)
0*
1+
b10111111 ,
03
17
b10111111 8
#4410000000
1!
1*
13
#4420000000
0!
0*
03
#4430000000
1!
1*
13
#4440000000
0!
0*
03
#4450000000
1!
1*
13
#4460000000
0!
0*
03
#4470000000
1!
1*
13
#4480000000
0!
0*
03
#4490000000
1!
1*
12
13
14
15
16
#4500000000
0!
0*
03
#4510000000
1!
1*
13
#4520000000
0!
0*
03
#4530000000
1!
1*
13
#4540000000
0!
0*
03
#4550000000
1!
1*
13
#4560000000
0!
0*
03
#4570000000
1!
1*
13
#4580000000
0!
0*
03
#4590000000
1!
1*
02
13
04
05
06
#4600000000
0!
0*
03
#4610000000
1!
1*
13
#4620000000
0!
0*
03
#4630000000
1!
1*
13
#4640000000
0!
0*
03
#4650000000
1!
1*
13
#4660000000
0!
0*
03
#4670000000
1!
1*
13
#4680000000
0!
0*
03
#4690000000
1!
1*
12
13
14
15
16
#4700000000
0!
0)
0*
0+
b10111111 ,
03
07
b10111111 8
#4710000000
1!
1*
13
#4720000000
0!
0*
03
#4730000000
1!
1*
13
#4740000000
0!
0*
03
#4750000000
1!
1*
13
#4760000000
0!
0*
03
#4770000000
1!
1*
13
#4780000000
0!
0*
03
#4790000000
1!
1*
02
13
04
05
06
#4800000000
0!
0*
03
#4810000000
1!
1*
13
#4820000000
0!
0*
03
#4830000000
1!
1*
13
#4840000000
0!
0*
03
#4850000000
1!
1*
13
#4860000000
0!
0*
03
#4870000000
1!
1*
13
#4880000000
0!
0*
03
#4890000000
1!
b01111111 #
1*
b01111111 ,
12
13
14
15
16
b01111111 8
b00001 >
#4900000000
0!
0*
03
#4910000000
1!
1*
13
#4920000000
0!
0*
03
#4930000000
1!
1*
13
#4940000000
0!
0*
03
#4950000000
1!
1*
13
#4960000000
0!
0*
03
#4970000000
1!
1*
13
#4980000000
0!
0*
03
#4990000000
1!
1*
02
13
04
05
06
#5000000000
0!
0*
03
#5010000000
1!
1*
13
#5020000000
0!
0*
03
#5030000000
1!
1*
13
#5040000000
0!
0*
03
#5050000000
1!
1*
13
#5060000000
0!
0*
03
#5070000000
1!
1*
13
#5080000000
0!
0*
03
#5090000000
1!
b11111111 #
b01111111 $
1*
b11111111 ,
b01111111 -
12
13
14
15
16
b11111111 8
b01111111 9
b00010 >
#5100000000
0!
0*
03
#5110000000
1!
1*
13
#5120000000
0!
0*
03
#5130000000
1!
1*
13
#5140000000
0!
0*
03
#5150000000
1!
1*
13
#5160000000
0!
0*
03
#5170000000
1!
1*
13
#5180000000
0!
0*
03
#5190000000
1!
1*
02
13
04
05
06
#5200000000
0!
0*
03
#5210000000
1!
1*
13
#5220000000
0!
0*
03
#5230000000
1!
1*
13
#5240000000
0!
0*
03
#5250000000
1!
1*
13
#5260000000
0!
0*
03
#5270000000
1!
1*
13
#5280000000
0!
0*
03
#5290000000
1!
b11111111 $
b01111111 %
1*
b11111111 -
b01111111 .
12
13
14
15
16
b11111111 9
b01111111 :
b00011 >
#5300000000
0!
0*
03
#5310000000
1!
1*
13
#5320000000
0!
0*
03
#5330000000
1!
1*
13
#5340000000
0!
0*
03
#5350000000
1!
1*
13
#5360000000
0!
0*
03
#5370000000
1!
1*
13
#5380000000
0!
0*
03
#5390000000
1!
1*
02
13
04
05
06
#5400000000
0!
0*
03
#5410000000
1!
1*
13
#5420000000
0!
0*
03
#5430000000
1!
1*
13
#5440000000
0!
0*
03
#5450000000
1!
1*
13
#5460000000
0!
0*
03
#5470000000
1!
1*
13
#5480000000
0!
0*
03
#5490000000
1!
b11111111 %
b01111111 &
1*
b11111111 .
b01111111 /
12
13
14
15
16
b11111111 :
b01111111 ;
b00100 >
#5500000000
0!
0*
03
#5510000000
1!
1*
13
#5520000000
0!
0*
03
#5530000000
1!
1*
13
#5540000000
0!
0*
03
#5550000000
1!
1*
13
#5560000000
0!
0*
03
#5570000000
1!
1*
13
#5580000000
0!
0*
03
#5590000000
1!
1*
02
13
04
05
06
#5600000000
0!
0*
03
#5610000000
1!
1*
13
#5620000000
0!
0*
03
#5630000000
1!
1*
13
#5640000000
0!
0*
03
#5650000000
1!
1*
13
#5660000000
0!
0*
03
#5670000000
1!
1*
13
#5680000000
0!
0*
03
#5690000000
1!
b11111111 &
b01111111 '
1*
b11111111 /
b01111111 0
12
13
14
15
16
b11111111 ;
b01111111 <
b00101 >
#5700000000
0!
0*
03
#5710000000
1!
1*
13
#5720000000
0!
0*
03
#5730000000
1!
1*
13
#5740000000
0!
0*
03
#5750000000
1!
1*
13
#5760000000
0!
0*
03
#5770000000
1!
1*
13
#5780000000
0!
0*
03
#5790000000
1!
1*
02
13
04
05
06
#5800000000
0!
0*
03
#5810000000
1!
1*
13
#5820000000
0!
0*
03
#5830000000
1!
1*
13
#5840000000
0!
0*
03
#5850000000
1!
1*
13
#5860000000
0!
0*
03
#5870000000
1!
1*
13
#5880000000
0!
0*
03
#5890000000
1!
b11111111 '
b01111111 (
1*
b11111111 0
b01111111 1
12
13
14
15
16
b11111111 <
b01111111 =
b00110 >
