Aula08/Ex8/ComponentEx8.vhd
-- Atividade pratica da Guia de Aula 08
-- Exercicio 8, pagina 114 do livro Free Range VHDL (2018)

library IEEE;
use IEEE.std_logic_1164.all;

entity ComponentEx8 is
  port (
    CLK : in std_logic;
    X : in std_logic; -- entradas da FSM
    Y : out std_logic_vector(2 downto 0); -- saidas para os proximos estados da FSM
    Z : out std_logic_vector(1 downto 0)); -- saida efetiva da FSM
end ComponentEx8;

architecture arch_ComponentEx8 of ComponentEx8 is
  type state_type is (ST0, ST1, ST2, ST3, ST4, ST5, ST6, ST7);
  attribute ENUM_ENCODING : string;
  attribute ENUM_ENCODING of state_type : type is "000 001 010 011 100 101 110 111";
  signal PS, NS : state_type;
begin
  sync_process : process (CLK, NS)
  begin
    if (rising_edge(CLK)) then
      PS <= NS;
    end if;
  end process sync_process;

  comb_process : process (PS, X)
  begin
    Z <= "00"; -- pre-assing saidas

    case PS is
      when ST0 =>
        Z <= "00";

        if (X = '0') then
          NS <= ST0;
        else NS <= ST1;
        end if;

      when ST1 =>
        Z <= "00";

        if (X = '0') then
          NS <= ST1;
        else NS <= ST2;
        end if;

      when ST2 =>
        Z <= "00";

        if (X = '0') then
          NS <= ST2;
        else NS <= ST3;
        end if;

      when ST3 =>
        Z <= "10";

        if (X = '0') then
          NS <= ST3;
        else NS <= ST4;
        end if;

      when ST4 =>
        Z <= "01";

        if (X = '0') then
          NS <= ST0;
        else NS <= ST5;
        end if;

      when ST5 =>
        Z <= "11";

        if (X = '0') then
          NS <= ST5;
        else NS <= ST6;
        end if;

      when ST6 =>
        Z <= "11";

        if (X = '0') then
          NS <= ST6;
        else NS <= ST7;
        end if;

      when ST7 =>
        Z <= "11";

        if (X = '0') then
          NS <= ST7;
        else NS <= ST0;
        end if;

      when others => -- catch all, nunca deve chegar aqui
        Z <= "00";
        NS <= ST0;
    end case;
  end process comb_process;

  -- codificação dos estados Y
  with PS select
    Y <=
    "000" when ST0,
    "001" when ST1,
    "010" when ST2,
    "011" when ST3,
    "100" when ST4,
    "101" when ST5,
    "110" when ST6,
    "111" when ST7,
    "000" when others;
end arch_ComponentEx8;

Aula08/Ex8/tb_ComponentEx8.vhd
library IEEE;
use IEEE.STD_LOGIC_1164.all;
use ieee.numeric_std.all;

entity tb_ComponentEx8 is
end tb_ComponentEx8;

architecture arch_tb_ComponentEx8 of tb_ComponentEx8 is

  component ComponentEx8 is
    port (
      CLK : in std_logic;
      X : in std_logic; -- entradas da FSM
      Y : out std_logic_vector(2 downto 0); -- saidas para os proximos estados da FSM
      Z : out std_logic_vector(1 downto 0)); -- saida efetiva da FSM
  end component;

  constant PERIODO : time := 10 ns;
  signal ENT_CLK : std_logic := '0'; -- deve ser inicializado
  signal ENT_CLK_ENABLE : std_logic := '1'; -- Sinal de Enable do clock só para efeito de controle do fim da simulação
  signal ENT_X : std_logic; 
  signal SAI_Y : std_logic_vector(2 downto 0);
  signal SAI_Z : std_logic_vector(1 downto 0);

begin
  -- geração do clock com periodo PERIODO
  ENT_CLK <= ENT_CLK_ENABLE and not ENT_CLK after PERIODO/2;
  ENT_CLK_ENABLE <= '1', '0' after 20 * PERIODO; -- a simulação termina após transcorrer 20 períodos de clock.

  -- instanciação do DUT, que nesse exemplo é um ffd
  DUT : ComponentEx8 port map(
    CLK => ENT_CLK,
    X => ENT_X,
    Y => SAI_Y,
    Z => SAI_Z
  );

  --  process para os estímulos das entradas
  stimulus : process
  begin
    ENT_X <= '0';
    wait for 4 * PERIODO;
    ENT_X <= '1';
    wait for 4 * PERIODO;
    ENT_X <= '0';
    wait for 4 * PERIODO;
    ENT_X <= '1';
    wait for 4 * PERIODO;
    wait;
  end process stimulus;
end arch_tb_ComponentEx8;

Aula08/Ex8/tb_ComponentEx8.vcd
$date
  Tue Oct 25 09:08:13 2022
$end
$version
  GHDL v0
$end
$timescale
  1 fs
$end
$scope module standard $end
$upscope $end
$scope module std_logic_1164 $end
$upscope $end
$scope module numeric_std $end
$upscope $end
$scope module tb_componentex8 $end
$var reg 1 ! ent_clk $end
$var reg 1 " ent_clk_enable $end
$var reg 1 # ent_x $end
$var reg 3 $ sai_y[2:0] $end
$var reg 2 % sai_z[1:0] $end
$scope module dut $end
$var reg 1 & clk $end
$var reg 1 ' x $end
$var reg 3 ( y[2:0] $end
$var reg 2 ) z[1:0] $end
$comment ps is not handled $end
$comment ns is not handled $end
$upscope $end
$upscope $end
$enddefinitions $end
#0
0!
1"
0#
b000 $
b00 %
0&
0'
b000 (
b00 )
#5000000
1!
1&
#10000000
0!
0&
#15000000
1!
1&
#20000000
0!
0&
#25000000
1!
1&
#30000000
0!
0&
#35000000
1!
1&
#40000000
0!
1#
0&
1'
#45000000
1!
b001 $
1&
b001 (
#50000000
0!
0&
#55000000
1!
b010 $
1&
b010 (
#60000000
0!
0&
#65000000
1!
b011 $
b10 %
1&
b011 (
b10 )
#70000000
0!
0&
#75000000
1!
b100 $
b01 %
1&
b100 (
b01 )
#80000000
0!
0#
0&
0'
b01 )
#85000000
1!
b000 $
b00 %
1&
b000 (
b00 )
#90000000
0!
0&
#95000000
1!
1&
#100000000
0!
0&
#105000000
1!
1&
#110000000
0!
0&
#115000000
1!
1&
#120000000
0!
1#
0&
1'
#125000000
1!
b001 $
1&
b001 (
#130000000
0!
0&
#135000000
1!
b010 $
1&
b010 (
#140000000
0!
0&
#145000000
1!
b011 $
b10 %
1&
b011 (
b10 )
#150000000
0!
0&
#155000000
1!
b100 $
b01 %
1&
b100 (
b01 )
#160000000
0!
0&
#165000000
1!
b101 $
b11 %
1&
b101 (
b11 )
#170000000
0!
0&
#175000000
1!
b110 $
1&
b110 (
b11 )
#180000000
0!
0&
#185000000
1!
b111 $
1&
b111 (
b11 )
#190000000
0!
0&
#195000000
1!
b000 $
b00 %
1&
b000 (
b00 )
