Projeto03/Datapath/Datapath.vhd
library IEEE;
use IEEE.std_logic_1164.all;

entity Datapath is
  port (
    clk : in std_logic;
    enter_num, enter_opr, reset : in std_logic;
    is_empty0, is_empty1, is_empty2 : in std_logic;
    load_stack0, load_stack1, load_stack2 : out std_logic;
    clear_stack0, clear_stack1, clear_stack2 : out std_logic;
    select_alu_num : out std_logic;
    select_stack_pos, select_two_stack_pos : out std_logic_vector(2 downto 0)
  );
end Datapath;

architecture arch_Datapath of Datapath is
  type state_type is (RESET_BOOT, WAIT_ENTER, UPDATE_NUM, WAIT_ENTER_NUM_DOWN, EXECUTE_OPERATION, WAIT_ENTER_OPR_DOWN);
  attribute ENUM_ENCODING : string;
  attribute ENUM_ENCODING of state_type : type is
  "000 001 010 011 100 101";
  signal PS, NS : state_type;
  signal Y : std_logic_vector(2 downto 0); -- signal para os proximos estados da FSM
begin
  sync_process : process (clk, NS)
  begin
    if (rising_edge(clk)) then
      PS <= NS;
    end if;
  end process sync_process;

  comb_process : process (
    PS, 
    reset,
    enter_num,
    enter_opr,
    reset,
    is_empty0,
    is_empty1,
    is_empty2
  )
  begin
    -- pre-assign saidas, assim nao precisa definir todas em cada estado
    load_stack0 <= '0';
    load_stack1 <= '0';
    load_stack2 <= '0';

    clear_stack0 <= '0';
    clear_stack1 <= '0';
    clear_stack2 <= '0';

    select_alu_num <= '1'; -- seleciona das chaves default
    select_stack_pos <= "100";
    select_two_stack_pos <= "110";

    case PS is
      when RESET_BOOT =>
        if (reset = '1') then
          NS <= RESET_BOOT;
        else
          NS <= WAIT_ENTER;
        end if;

        clear_stack0 <= '1';
        clear_stack1 <= '1';
        clear_stack2 <= '1';

      when WAIT_ENTER =>
        if (reset = '1') then
          NS <= RESET_BOOT;
        elsif (enter_num = '1') then
          NS <= UPDATE_NUM;
        elsif (enter_opr = '1') then
          NS <= EXECUTE_OPERATION;
        else
          NS <= WAIT_ENTER;
        end if;

      when UPDATE_NUM =>
        NS <= WAIT_ENTER_NUM_DOWN;
        select_alu_num <= '1'; -- puxa do num conectado das chaves

        -- identifica a posicao da stack que precisa carregar o conteudo das chaves
        -- e sempre a mais alta que a stack permite
        -- se todas as posicoes estao cheias, nao faz nada (nao adiciona na stack)
        if (is_empty0 = '1') then
          select_stack_pos <= "001";
          select_two_stack_pos <= "011";
          load_stack0 <= '1';
        elsif (is_empty1 = '1') then
          select_stack_pos <= "010";
          select_two_stack_pos <= "011";
          load_stack1 <= '1';
        elsif (is_empty2 = '1') then
          select_stack_pos <= "100";
          select_two_stack_pos <= "110";
          load_stack2 <= '1';
        end if;

      when WAIT_ENTER_NUM_DOWN =>
        if (enter_num = '1') then
          NS <= WAIT_ENTER_NUM_DOWN;
        else
          NS <= WAIT_ENTER;
        end if;

      when EXECUTE_OPERATION =>
        NS <= WAIT_ENTER_OPR_DOWN;
        select_alu_num <= '0'; -- puxa da ALU do datapath

        -- identifica a posicao da stack que precisa carregar o conteudo das chaves
        -- e sempre a mais alta que a stack permite
        -- se todas as posicoes estao cheias, nao faz nada (nao adiciona na stack)
        if (is_empty0 = '1') then
          select_stack_pos <= "001";
          select_two_stack_pos <= "011";
          load_stack0 <= '1';
        elsif (is_empty1 = '1') then
          select_stack_pos <= "010";
          select_two_stack_pos <= "011";
          load_stack1 <= '1';
        elsif (is_empty2 = '1') then
          select_stack_pos <= "100";
          select_two_stack_pos <= "110";
          load_stack2 <= '1';
        end if;

      when WAIT_ENTER_OPR_DOWN =>
        if (enter_opr = '1') then
          NS <= WAIT_ENTER_OPR_DOWN;
        else
          NS <= WAIT_ENTER;
        end if;
        
      when others => -- catch all, nunca deve chegar aqui
        NS <= RESET_BOOT;
    end case;
end process comb_process;

-- codificação dos estados Y
with PS select
  Y <=
    "000" when RESET_BOOT,
    "001" when WAIT_ENTER,
    "010" when UPDATE_NUM,
    "011" when WAIT_ENTER_NUM_DOWN,
    "100" when EXECUTE_OPERATION,
    "101" when WAIT_ENTER_OPR_DOWN,
    "000" when others;
end arch_Datapath;

Projeto03/Calculator/Datapath/tb_Datapath.vhd
library IEEE;
use IEEE.STD_LOGIC_1164.all;
use ieee.numeric_std.all;

entity tb_Datapath is
end tb_Datapath;

architecture arch_tb_Datapath of tb_Datapath is

  component Datapath is
    port (
      clk : in std_logic;
      enter_num, enter_opr, reset : in std_logic;
      is_empty0, is_empty1, is_empty2 : in std_logic;
      load_stack0, load_stack1, load_stack2 : out std_logic;
      clear_stack0, clear_stack1, clear_stack2 : out std_logic;
      select_alu_num : out std_logic;
      select_stack_pos, select_two_stack_pos : out std_logic_vector(2 downto 0)
    );
  end component;

  constant PERIODO : time := 20 ns; -- 50MHz
  signal ENT_CLK : std_logic := '0'; -- deve ser inicializado
  signal ENT_CLK_ENABLE : std_logic := '1'; -- Sinal de Enable do clock só para efeito de controle do fim da simulação
  signal tb_enter_num, tb_enter_opr, tb_reset : std_logic;
  signal tb_is_empty0, tb_is_empty1, tb_is_empty2 : std_logic;
  signal tb_load_stack0, tb_load_stack1, tb_load_stack2 : std_logic;
  signal tb_clear_stack0, tb_clear_stack1, tb_clear_stack2 : std_logic;
  signal tb_select_alu_num : std_logic;
  signal tb_select_stack_pos, tb_select_two_stack_pos : std_logic_vector(2 downto 0);

begin
  -- geração do clock com periodo PERIODO
  ENT_CLK <= ENT_CLK_ENABLE and not ENT_CLK after PERIODO/2;
  ENT_CLK_ENABLE <= '1', '0' after 80 * PERIODO;

  -- instanciação do DUT
  DUT : Datapath port map(
    clk => ENT_CLK,
    enter_num => tb_enter_num,
    enter_opr => tb_enter_opr,
    reset => tb_reset,
    is_empty0 => tb_is_empty0,
    is_empty1 => tb_is_empty1,
    is_empty2 => tb_is_empty2,
    load_stack0 => tb_load_stack0,
    load_stack1 => tb_load_stack1,
    load_stack2 => tb_load_stack2,
    clear_stack0 => tb_clear_stack0,
    clear_stack1 => tb_clear_stack1,
    clear_stack2 => tb_clear_stack2,
    select_alu_num => tb_select_alu_num,
    select_stack_pos => tb_select_stack_pos,
    select_two_stack_pos => tb_select_two_stack_pos
  );

  --  process para os estímulos das entradas
  stimulus : process
  begin
    -- inicializa entradas tudas para remover variaveis de erro
    tb_enter_num <= '0';
    tb_enter_opr <= '0';
    tb_reset <= '0';
    tb_is_empty0 <= '0';
    tb_is_empty1 <= '0';
    tb_is_empty2 <= '0';

    wait for 5 * PERIODO;
    -- entro com um numero
    tb_enter_num <= '1';
    wait for 5 * PERIODO;
    tb_enter_num <= '0';
    wait for 5 * PERIODO;

    -- entro com outro numero
    tb_enter_num <= '1';
    wait for 5 * PERIODO;
    tb_enter_num <= '0';
    wait for 5 * PERIODO;

    -- operacao
    tb_enter_opr <= '1';
    wait for 5 * PERIODO;
    tb_enter_opr <= '0';
    wait for 5 * PERIODO;

    tb_reset <= '1';

    wait;
  end process stimulus;
end arch_tb_Datapath;

Projeto03/Datapath/tb_Datapath.vcd
$date
  Sun Dec 11 21:45:27 2022
$end
$version
  GHDL v0
$end
$timescale
  1 fs
$end
$scope module standard $end
$upscope $end
$scope module std_logic_1164 $end
$upscope $end
$scope module numeric_std $end
$upscope $end
$scope module tb_datapath $end
$var reg 1 ! ent_clk $end
$var reg 1 " ent_clk_enable $end
$var reg 1 # tb_enter_num $end
$var reg 1 $ tb_enter_opr $end
$var reg 1 % tb_reset $end
$var reg 1 & tb_is_empty0 $end
$var reg 1 ' tb_is_empty1 $end
$var reg 1 ( tb_is_empty2 $end
$var reg 1 ) tb_load_stack0 $end
$var reg 1 * tb_load_stack1 $end
$var reg 1 + tb_load_stack2 $end
$var reg 1 , tb_clear_stack0 $end
$var reg 1 - tb_clear_stack1 $end
$var reg 1 . tb_clear_stack2 $end
$var reg 1 / tb_select_alu_num $end
$var reg 3 0 tb_select_stack_pos[2:0] $end
$var reg 3 1 tb_select_two_stack_pos[2:0] $end
$scope module dut $end
$var reg 1 2 clk $end
$var reg 1 3 enter_num $end
$var reg 1 4 enter_opr $end
$var reg 1 5 reset $end
$var reg 1 6 is_empty0 $end
$var reg 1 7 is_empty1 $end
$var reg 1 8 is_empty2 $end
$var reg 1 9 load_stack0 $end
$var reg 1 : load_stack1 $end
$var reg 1 ; load_stack2 $end
$var reg 1 < clear_stack0 $end
$var reg 1 = clear_stack1 $end
$var reg 1 > clear_stack2 $end
$var reg 1 ? select_alu_num $end
$var reg 3 @ select_stack_pos[2:0] $end
$var reg 3 A select_two_stack_pos[2:0] $end
$comment ps is not handled $end
$comment ns is not handled $end
$var reg 3 B y[2:0] $end
$upscope $end
$upscope $end
$enddefinitions $end
#0
0!
1"
0#
0$
0%
0&
0'
0(
0)
0*
0+
1,
1-
1.
1/
b100 0
b110 1
02
03
04
05
06
07
08
09
0:
0;
1<
1=
1>
1?
b100 @
b110 A
b000 B
#10000000
1!
0,
0-
0.
12
0<
0=
0>
b001 B
#20000000
0!
02
#30000000
1!
12
#40000000
0!
02
#50000000
1!
12
#60000000
0!
02
#70000000
1!
12
#80000000
0!
02
#90000000
1!
12
#100000000
0!
1#
02
13
#110000000
1!
12
b010 B
#120000000
0!
02
#130000000
1!
12
b011 B
#140000000
0!
02
#150000000
1!
12
#160000000
0!
02
#170000000
1!
12
#180000000
0!
02
#190000000
1!
12
#200000000
0!
0#
02
03
#210000000
1!
12
b001 B
#220000000
0!
02
#230000000
1!
12
#240000000
0!
02
#250000000
1!
12
#260000000
0!
02
#270000000
1!
12
#280000000
0!
02
#290000000
1!
12
#300000000
0!
1#
02
13
#310000000
1!
12
b010 B
#320000000
0!
02
#330000000
1!
12
b011 B
#340000000
0!
02
#350000000
1!
12
#360000000
0!
02
#370000000
1!
12
#380000000
0!
02
#390000000
1!
12
#400000000
0!
0#
02
03
#410000000
1!
12
b001 B
#420000000
0!
02
#430000000
1!
12
#440000000
0!
02
#450000000
1!
12
#460000000
0!
02
#470000000
1!
12
#480000000
0!
02
#490000000
1!
12
#500000000
0!
1$
02
14
#510000000
1!
0/
12
0?
b100 B
#520000000
0!
02
#530000000
1!
1/
12
1?
b101 B
#540000000
0!
02
#550000000
1!
12
#560000000
0!
02
#570000000
1!
12
#580000000
0!
02
#590000000
1!
12
#600000000
0!
0$
02
04
#610000000
1!
12
b001 B
#620000000
0!
02
#630000000
1!
12
#640000000
0!
02
#650000000
1!
12
#660000000
0!
02
#670000000
1!
12
#680000000
0!
02
#690000000
1!
12
#700000000
0!
1%
02
15
#710000000
1!
1,
1-
1.
12
1<
1=
1>
b000 B
