Aula07/mean_4_clocks_master/mean_4_clocks.vhd
-- mean_4_clocks - A system that calculates the mean over four clocks
-- Copyright (C) 2018  Digital Systems Group - UFMG
-- 
-- This program is free software; you can redistribute it and/or modify
-- it under the terms of the GNU General Public License as published by
-- the Free Software Foundation; either version 3 of the License, or
-- (at your option) any later version.
-- 
-- This program is distributed in the hope that it will be useful,
-- but WITHOUT ANY WARRANTY; without even the implied warranty of
-- MERCHANTABILITY or FITNESS FOR A PARTICULAR PURPOSE.  See the
-- GNU General Public License for more details.
-- 
-- You should have received a copy of the GNU General Public License
-- along with this program; if not, see <https://www.gnu.org/licenses/>.
--

library ieee;
use ieee.std_logic_1164.all;
use ieee.numeric_std.all;

entity mean_4_clocks is
    generic (
        W       :       integer := 32
    );
    port (
        CLK     : in    std_logic;
        RESET   : in    std_logic;
        INPUT   : in    std_logic_vector(W - 1 downto 0);
        OUTPUT  : out   std_logic_vector(W - 1 downto 0)
    );
end mean_4_clocks;

-- Implement the testbench and find the errors in this model.
-- Consider the following expected behavior:
--      Every rising edge of CLK input, the content of INPUT
--      is added to a register chain and used to calculate the
--      mean value over 4 clock periods

architecture arch of mean_4_clocks is
begin
    process(CLK, RESET) is
        variable var1 : unsigned(W - 1 downto 0);
        variable var2 : unsigned(W - 1 downto 0);
        variable var3 : unsigned(W - 1 downto 0);
        variable var4 : unsigned(W - 1 downto 0);
        variable total : unsigned(W - 1 downto 0);
    begin
        if (RESET = '1') then
            var1 := to_unsigned(0,W);
            var2 := to_unsigned(0,W);
            var3 := to_unsigned(0,W);
            var4 := to_unsigned(0,W);
        elsif (rising_edge(CLK)) then
            var4 := var3;
            var3 := var2;
            var2 := var1;
            var1 := unsigned(INPUT);
        end if;
        
        total := var1 + var2 + var3 + var4;

        OUTPUT <= std_logic_vector(unsigned("00" & total(W-1 downto 2)));
    end process;
    
end arch;

Aula07/mean_4_clocks_master/tb_mean_4_clocks.vhd
library IEEE;
use IEEE.STD_LOGIC_1164.all;
use ieee.numeric_std.all;

entity tb_mean_4_clocks is
end tb_mean_4_clocks;

architecture arch_tb_mean_4_clocks of tb_mean_4_clocks is

  component mean_4_clocks is
    generic (
      W : integer := 32
    );
    port (
      CLK : in std_logic;
      RESET : in std_logic;
      INPUT : in std_logic_vector(W - 1 downto 0);
      OUTPUT : out std_logic_vector(W - 1 downto 0)
    );
  end component;

  constant PERIODO : time := 10 ns;
  constant W : integer := 32;
  signal ENT_CLK : std_logic := '0'; -- deve ser inicializado
  signal ENT_CLK_ENABLE : std_logic := '1'; -- Sinal de Enable do clock só para efeito de controle do fim da simulação
  signal ENT_RESET : std_logic;
  signal ENT_INPUT : std_logic_vector(W - 1 downto 0);
  signal SAI_OUPUT : std_logic_vector(W - 1 downto 0);

begin
  -- geração do clock com periodo PERIODO
  ENT_CLK <= ENT_CLK_ENABLE and not ENT_CLK after PERIODO/2;
  ENT_CLK_ENABLE <= '1', '0' after 20 * PERIODO; -- a simulação termina após transcorrer 20 períodos de clock.

  -- instanciação do DUT, que nesse exemplo é um ffd
  DUT : mean_4_clocks port map(
    CLK => ENT_CLK,
    RESET => ENT_RESET,
    INPUT => ENT_INPUT,
    OUTPUT => SAI_OUPUT);
  -- a partir daqui declaro os estímulos de entrada, ou a injecao de sinais
  -- um process para o reset
  reset : process
  begin
    ENT_RESET <= '0';
    wait for 2 * PERIODO; -- um reset de duração de 2 períodos de clock
    ENT_RESET <= '1';
    wait for 4 * PERIODO;
    ENT_RESET <= '0';
    wait for 4 * PERIODO;
    ENT_RESET <= '0';

    wait;
  end process reset;
  -- um outro process para os estímulos da entrada D
  stimulus : process
  begin
    ENT_INPUT <= x"00000001";
    wait for 4 * PERIODO;
    ENT_INPUT <= x"00000002";
    wait for 4 * PERIODO;
    ENT_INPUT <= x"00000003";
    wait for 4 * PERIODO;
    ENT_INPUT <= x"00000004";
    wait;
  end process stimulus;
end arch_tb_mean_4_clocks;

Aula07/mean_4_clocks_master/tb_mean_4_clocks.vcd
$date
  Mon Oct 17 12:06:01 2022
$end
$version
  GHDL v0
$end
$timescale
  1 fs
$end
$scope module standard $end
$upscope $end
$scope module std_logic_1164 $end
$upscope $end
$scope module numeric_std $end
$upscope $end
$scope module tb_mean_4_clocks $end
$var reg 1 ! ent_clk $end
$var reg 1 " ent_clk_enable $end
$var reg 1 # ent_reset $end
$var reg 32 $ ent_input[31:0] $end
$var reg 32 % sai_ouput[31:0] $end
$scope module dut $end
$var reg 1 & clk $end
$var reg 1 ' reset $end
$var reg 32 ( input[31:0] $end
$var reg 32 ) output[31:0] $end
$upscope $end
$upscope $end
$enddefinitions $end
#0
0!
1"
0#
b00000000000000000000000000000001 $
bXXXXXXXXXXXXXXXXXXXXXXXXXXXXXXXX %
0&
0'
b00000000000000000000000000000001 (
bXXXXXXXXXXXXXXXXXXXXXXXXXXXXXXXX )
#5000000
1!
b00000000000000000000000000000000 %
1&
b00000000000000000000000000000000 )
#10000000
0!
0&
#15000000
1!
1&
#20000000
0!
1#
0&
1'
#25000000
1!
1&
#30000000
0!
0&
#35000000
1!
1&
#40000000
0!
b00000000000000000000000000000010 $
0&
b00000000000000000000000000000010 (
#45000000
1!
1&
#50000000
0!
0&
#55000000
1!
1&
#60000000
0!
0#
0&
0'
#65000000
1!
1&
#70000000
0!
0&
#75000000
1!
1&
#80000000
0!
b00000000000000000000000000000011 $
0&
b00000000000000000000000000000011 (
#85000000
1!
1&
#90000000
0!
0&
#95000000
1!
1&
#100000000
0!
0&
#105000000
1!
1&
#110000000
0!
0&
#115000000
1!
1&
#120000000
0!
b00000000000000000000000000000100 $
0&
b00000000000000000000000000000100 (
#125000000
1!
b00000000000000000000000000000100 %
1&
b00000000000000000000000000000100 )
