Projeto03/Calculator/Datapath/StackRegister/StackRegister.vhd
-- O proprio registrador da stack e uma FSM

library IEEE;
use IEEE.std_logic_1164.all;

entity StackRegister is
  port (
    X : in std_logic_vector(3 downto 0);
    load, clear, clk : in std_logic;
    isEmpty : out std_logic;
    Z : out std_logic_vector(3 downto 0)
  );
end StackRegister;

architecture arch_StackRegister of StackRegister is
  type state_type is (HOLD_ST, LOAD_ST, CLEAR_ST);
  attribute ENUM_ENCODING : string;
  attribute ENUM_ENCODING of state_type : type is "00 01 10";
  signal PS, NS : state_type;

  signal Y : std_logic_vector(1 downto 0); -- para os estados da FSM
begin
  sync_process : process (CLK, NS)
  begin
    if (rising_edge(CLK)) then
      PS <= NS;
    end if;
  end process sync_process;

  comb_process : process (PS, load, clear, X)
  begin
    
    case PS is

      when HOLD_ST =>
        if (clear = '1') then
          NS <= CLEAR_ST;
        elsif (load = '1') then
          NS <= LOAD_ST;
        else
          NS <= HOLD_ST;
        end if;

      when LOAD_ST =>
        Z <= X;
        isEmpty <= '0'; 
        NS <= HOLD_ST;

      when CLEAR_ST =>
        Z <= "0000";
        isEmpty <= '1'; 

        if (clear = '0') then
          NS <= HOLD_ST;
        else 
          NS <= CLEAR_ST;
        end if;

      when others => -- catch all, nunca deve chegar aqui
        NS <= HOLD_ST;
    end case;
  end process comb_process;

  -- codificação dos estados Y
  with PS select
    Y <= "00" when HOLD_ST,
    "01" when LOAD_ST,
    "10" when CLEAR_ST,
    "00" when others;
end arch_StackRegister;

Projeto03/Calculator/Datapath/StackRegister/tb_StackRegister.vhd
library IEEE;
use IEEE.STD_LOGIC_1164.all;
use ieee.numeric_std.all;

entity tb_StackRegister is
end tb_StackRegister;

architecture arch_tb_StackRegister of tb_StackRegister is

  component StackRegister is
    port (
      X : in std_logic_vector(3 downto 0);
      load, clear, clk : in std_logic;
      isEmpty : out std_logic;
      Z : out std_logic_vector(3 downto 0)
    );
  end component;

  constant PERIODO : time := 20 ns; -- 50 MHz
  signal ENT_CLK : std_logic := '0'; -- deve ser inicializado
  signal ENT_CLK_ENABLE : std_logic := '1'; -- Sinal de Enable do clock só para efeito de controle do fim da simulação

  signal tb_X : std_logic_vector(3 downto 0);
  signal tb_load, tb_clear, tb_isEmpty : std_logic;
  signal tb_Z : std_logic_vector(3 downto 0);

begin
  -- geração do clock com periodo PERIODO
  ENT_CLK <= ENT_CLK_ENABLE and not ENT_CLK after PERIODO/2;
  ENT_CLK_ENABLE <= '1', '0' after 40 * PERIODO; -- a simulação termina após transcorrer 20 períodos de clock.

  DUT : StackRegister port map(
    clk => ENT_CLK,
    X => tb_X,
    load => tb_load,
    clear => tb_clear,
    isEmpty => tb_isEmpty,
    Z => tb_Z
  );

  --  process para os estímulos das entradas
  stimulus : process
  begin
    tb_load <= '1';
    tb_clear <= '0';
    tb_X <= "0010";
    wait for 10 * PERIODO;
    tb_load <= '0';
    tb_clear <= '1';
    wait for 2 * PERIODO;
    tb_X <= "1010";
    wait for 10 * PERIODO;
    tb_clear <= '0';
    wait for 5 * PERIODO;
    tb_load <= '1';
    wait for 5 * PERIODO;
    tb_X <= "1111";

    wait;
  end process stimulus;
end arch_tb_StackRegister;

Projeto03/Calculator/Datapath/StackRegister/tb_StackRegister.vcd
$date
  Mon Dec 12 00:00:57 2022
$end
$version
  GHDL v0
$end
$timescale
  1 fs
$end
$scope module standard $end
$upscope $end
$scope module std_logic_1164 $end
$upscope $end
$scope module numeric_std $end
$upscope $end
$scope module tb_stackregister $end
$var reg 1 ! ent_clk $end
$var reg 1 " ent_clk_enable $end
$var reg 4 # tb_x[3:0] $end
$var reg 1 $ tb_load $end
$var reg 1 % tb_clear $end
$var reg 1 & tb_isempty $end
$var reg 4 ' tb_z[3:0] $end
$scope module dut $end
$var reg 4 ( x[3:0] $end
$var reg 1 ) load $end
$var reg 1 * clear $end
$var reg 1 + clk $end
$var reg 1 , isempty $end
$var reg 4 - z[3:0] $end
$comment ps is not handled $end
$comment ns is not handled $end
$var reg 2 . y[1:0] $end
$upscope $end
$upscope $end
$enddefinitions $end
#0
0!
1"
b0010 #
1$
0%
U&
bUUUU '
b0010 (
1)
0*
0+
U,
bUUUU -
b00 .
#10000000
1!
0&
b0010 '
1+
0,
b0010 -
b01 .
#20000000
0!
0+
#30000000
1!
1+
b00 .
#40000000
0!
0+
#50000000
1!
1+
b01 .
#60000000
0!
0+
#70000000
1!
1+
b00 .
#80000000
0!
0+
#90000000
1!
1+
b01 .
#100000000
0!
0+
#110000000
1!
1+
b00 .
#120000000
0!
0+
#130000000
1!
1+
b01 .
#140000000
0!
0+
#150000000
1!
1+
b00 .
#160000000
0!
0+
#170000000
1!
1+
b01 .
#180000000
0!
0+
#190000000
1!
1+
b00 .
#200000000
0!
0$
1%
0)
1*
0+
#210000000
1!
1&
b0000 '
1+
1,
b0000 -
b10 .
#220000000
0!
0+
#230000000
1!
1+
#240000000
0!
b1010 #
b1010 (
0+
#250000000
1!
1+
#260000000
0!
0+
#270000000
1!
1+
#280000000
0!
0+
#290000000
1!
1+
#300000000
0!
0+
#310000000
1!
1+
#320000000
0!
0+
#330000000
1!
1+
#340000000
0!
0+
#350000000
1!
1+
#360000000
0!
0+
#370000000
1!
1+
#380000000
0!
0+
#390000000
1!
1+
#400000000
0!
0+
#410000000
1!
1+
#420000000
0!
0+
#430000000
1!
1+
#440000000
0!
0%
0*
0+
#450000000
1!
1+
b00 .
#460000000
0!
0+
#470000000
1!
1+
#480000000
0!
0+
#490000000
1!
1+
#500000000
0!
0+
#510000000
1!
1+
#520000000
0!
0+
#530000000
1!
1+
#540000000
0!
1$
1)
0+
#550000000
1!
0&
b1010 '
1+
0,
b1010 -
b01 .
#560000000
0!
0+
#570000000
1!
1+
b00 .
#580000000
0!
0+
#590000000
1!
1+
b01 .
#600000000
0!
0+
#610000000
1!
1+
b00 .
#620000000
0!
0+
#630000000
1!
1+
b01 .
#640000000
0!
b1111 #
b1111 '
b1111 (
0+
b1111 -
#650000000
1!
1+
b00 .
#660000000
0!
0+
#670000000
1!
1+
b01 .
#680000000
0!
0+
#690000000
1!
1+
b00 .
#700000000
0!
0+
#710000000
1!
1+
b01 .
#720000000
0!
0+
#730000000
1!
1+
b00 .
#740000000
0!
0+
#750000000
1!
1+
b01 .
#760000000
0!
0+
#770000000
1!
1+
b00 .
#780000000
0!
0+
#790000000
1!
1+
b01 .
