Aula06/Ex/ComponentEx.vhd
-- Componente da Atividade pratica da Guia de Aula 06
-- ULA de 8 bits com 6 operacoes selecionaveis

library ieee;
use ieee.std_logic_1164.all;
use ieee.numeric_std.all;

entity ComponentEx is
  port (
    a, b : in std_logic_vector(7 downto 0);
    s : in std_logic_vector(2 downto 0);
    o : out std_logic_vector(7 downto 0)
  );
end ComponentEx;

architecture arch_ComponentEx of ComponentEx is
begin
  process_ComponentEx1 : process (a, b, s)
    begin
    -- ainda falta entender o que fazer com o carry out CO da ALU

    case (s) is
      when "000" =>
        -- somador com sinal
        o <= std_logic_vector(signed(a) + signed(b));
        
      when "001" =>
        -- somador sem sinal
        o <= std_logic_vector(unsigned(a) + unsigned(b));
        
      when "010" =>
        -- subtrator
        o <= std_logic_vector(signed(a) - signed(b));

      when "011" =>
        -- OR bit a bit
        o <= a or b;

      when "100" =>
        -- AND bit a bit
        o <= a and b;

      when "101" =>
        -- XOR bit a bit
        o <= a xor b;

      when others =>
        -- faz XOR bit a bit para os outros casos
        o <= a xor b;
    end case;
  end process process_ComponentEx1;
end arch_ComponentEx;

Aula07/Ex/tb_ComponentEx.vhd
library IEEE;
use IEEE.STD_LOGIC_1164.all;
use ieee.numeric_std.all;

entity tb_ComponentEx is
end tb_ComponentEx;

architecture arch_tb_ComponentEx of tb_ComponentEx is

  component ComponentEx is
    port (
      a, b : in std_logic_vector(7 downto 0);
      s    : in std_logic_vector(2 downto 0);
      o    : out std_logic_vector(7 downto 0)
    );
  end component;

  signal A, B, O : std_logic_vector(7 downto 0);
  signal S : std_logic_vector(2 downto 0);
begin
  instancia_ComponentEx : ComponentEx port map(a => A, b => B, s => S, o => O);
  S <= "000", "001" after 30 ns, "010" after 60 ns, "011" after 90 ns, "100" after 120 ns, "101" after 150 ns, "110" after 180 ns, "111" after 210 ns, "000" after 250 ns;
  A <= x"00", x"25" after 20 ns, x"25" after 50 ns, x"25" after 80 ns, x"25" after 110 ns, x"25" after 140 ns, x"25" after 170 ns, x"25" after 200 ns;
  B <= x"00", x"30" after 20 ns, x"30" after 50 ns, x"30" after 80 ns, x"30" after 110 ns, x"30" after 140 ns, x"30" after 170 ns, x"30" after 200 ns;
end arch_tb_ComponentEx;

Aula07/Ex/tb_ComponentEx.vcd
$date
  Mon Oct 03 20:05:44 2022
$end
$version
  GHDL v0
$end
$timescale
  1 fs
$end
$scope module standard $end
$upscope $end
$scope module std_logic_1164 $end
$upscope $end
$scope module numeric_std $end
$upscope $end
$scope module tb_componentex $end
$var reg 8 ! a[7:0] $end
$var reg 8 " b[7:0] $end
$var reg 8 # o[7:0] $end
$var reg 3 $ s[2:0] $end
$scope module instancia_componentex $end
$var reg 8 % a[7:0] $end
$var reg 8 & b[7:0] $end
$var reg 3 ' s[2:0] $end
$var reg 8 ( o[7:0] $end
$upscope $end
$upscope $end
$enddefinitions $end
#0
b00000000 !
b00000000 "
b00000000 #
b000 $
b00000000 %
b00000000 &
b000 '
b00000000 (
#20000000
b00100101 !
b00110000 "
b01010101 #
b00100101 %
b00110000 &
b01010101 (
#30000000
b001 $
b001 '
#50000000
#60000000
b11110101 #
b010 $
b010 '
b11110101 (
#80000000
#90000000
b00110101 #
b011 $
b011 '
b00110101 (
#110000000
#120000000
b00100000 #
b100 $
b100 '
b00100000 (
#140000000
#150000000
b00010101 #
b101 $
b101 '
b00010101 (
#170000000
#180000000
b110 $
b110 '
#200000000
#210000000
b111 $
b111 '
#250000000
b01010101 #
b000 $
b000 '
b01010101 (
