Projeto02/FSM/FSM.vhd
-- Atividade pratica da Guia de Aula 08
-- Exercicio 8, pagina 114 do livro Free Range VHDL (2018)

library IEEE;
use IEEE.std_logic_1164.all;

entity FSM is
  port (
    CLK_FSM : in std_logic;
    X : in std_logic; -- entrada da FSM
    Y : out std_logic_vector(2 downto 0); -- saidas para os proximos estados da FSM
    Z0 : out std_logic_vector(0 to 7)); -- saidas efetivas da FSM
end FSM;

architecture arch_FSM of FSM is
  type state_type is (ST0, ST1, ST2, ST3, ST4, ST5);
  attribute ENUM_ENCODING : string;
  attribute ENUM_ENCODING of state_type : type is "000 001 010 011 100 101";
  signal PS, NS : state_type;
begin
  sync_process : process (CLK_FSM, NS)
  begin
    if (rising_edge(CLK_FSM)) then
      PS <= NS;
    end if;
  end process sync_process;

  comb_process : process (PS, X)
  begin
    Z0 <= "01111111";

    case PS is
      when ST0 =>
        if (X = '1') then
          NS <= ST0;
          Z0 <= "01111111";
        elsif (X = '0') then
          NS <= ST1;
          Z0 <= "01111111";
        else -- catch all
          NS <= ST0;
          Z0 <= "01111111";
        end if;

      when ST1 =>
        if (X = '1') then
          NS <= ST0;
          Z0 <= "01111111";
        elsif (X = '0') then
          NS <= ST2;
          Z0 <= "10111111";
        else -- catch all
          NS <= ST0;
          Z0 <= "01111111";
        end if;

      when ST2 =>
        if (X = '1') then
          NS <= ST0;
          Z0 <= "01111111";
        elsif (X = '0') then
          NS <= ST0;
          Z0 <= "11011111";
        else -- catch all
          NS <= ST0;
          Z0 <= "01111111";
        end if;

      when others => -- catch all, nunca deve chegar aqui
        NS <= ST0;
        Z0 <= "01111111";
    end case;
  end process comb_process;

  -- codificação dos estados Y
  with PS select
    Y <=
    "000" when ST0,
    "001" when ST1,
    "010" when ST2,
    "011" when ST3,
    "100" when ST4,
    "101" when ST5,
    "000" when others;
end arch_FSM;

Projeto02/ClockDivider/ClockDivider.vhd
-- CLK_COUNTER_MAX = (1/2) * (fo / fd)
-- fo: freq original do clock. fd: freq desejada do clock

library ieee;
use ieee.std_logic_1164.all;

entity ClockDivider is
  port (
    CLK_INPUT : in std_logic;
    CLK_OUTPUT : out std_logic
  );
end ClockDivider;

architecture arch_ClockDivider of ClockDivider is
  signal CLK_AUX : std_logic := '0';

  -- constantes
  constant CLK_COUNTER_MAX : integer := 12499999;
  constant TESTBENCH_CLK_COUNTER_MAX : integer := 5;
begin

  -- converte clock de 50Mhz na entrada para 2Hz na saida
  -- process (CLK_INPUT, CLK_AUX)
  --   variable count : integer range 0 to 2 ** 26 - 1;
  -- begin
  --   if (rising_edge(CLK_INPUT)) then
  --     count := count + 1;
  --     if (count = CLK_COUNTER_MAX) then
  --       CLK_AUX <= not CLK_AUX;
  --       count := 0;
  --     end if;
  --   end if;
  --   CLK_OUTPUT <= CLK_AUX;
  -- end process;

  -- para fins exclusivos de testbench: converte clock de 50Mhz na entrada para 5MHz na saida
  process (CLK_INPUT, CLK_AUX)
    variable count : integer range 0 to 2 ** 26 - 1;
  begin
    if (rising_edge(CLK_INPUT)) then
      count := count + 1;
      if (count = TESTBENCH_CLK_COUNTER_MAX) then
        CLK_AUX <= not CLK_AUX;
        count := 0;
      end if;
    end if;
    CLK_OUTPUT <= CLK_AUX;
  end process;
end arch_ClockDivider;

Projeto02/Projeto02.vhd
library ieee;

use ieee.std_logic_1164.all;
use ieee.numeric_std.all;

entity Projeto02 is
  port (
    CLK_50MHz, RESET : in std_logic;
    DISP0 : out std_logic_vector(0 to 7)
  );
end Projeto02;

architecture arch_Projeto02 of Projeto02 is
  -- puxa o divisor de clock
  component ClockDivider is
    port (
      CLK_INPUT : in std_logic;
      CLK_OUTPUT : out std_logic
    );
  end component;

  -- puxa a FSM
  component FSM is
    port (
      CLK_FSM : in std_logic;
      X : in std_logic; -- entrada da FSM
      Y : out std_logic_vector(2 downto 0); -- saidas para os proximos estados da FSM
      Z0 : out std_logic_vector(0 to 7)); -- saidas efetivas da FSM
  end component FSM;

  -- signals intermediarios (internos ao componente de alto nivel)
  signal INTERNAL_CLK_2Hz : std_logic;

begin
  my_ClockDivider : ClockDivider port map(
    CLK_INPUT => CLK_50MHz,
    CLK_OUTPUT => INTERNAL_CLK_2Hz
  );

  my_FSM : FSM port map(
    CLK_FSM => INTERNAL_CLK_2Hz,
    X => RESET,
    Y => open, -- nao e usado pelo componente de alto nivel, apenas pela FSM internamente
    Z0 => DISP0
  );

end arch_Projeto02;

Projeto02/tb_Projeto02.vhd
library IEEE;
use IEEE.STD_LOGIC_1164.all;
use ieee.numeric_std.all;

entity tb_Projeto02 is
end tb_Projeto02;

architecture arch_tb_Projeto02 of tb_Projeto02 is

  component Projeto02 is
    port (
      CLK_50MHz, RESET : in std_logic;
      DISP0 : out std_logic_vector(0 to 7)
    );
  end component;

  constant PERIODO : time := 20 ns; -- 50 MHz
  signal ENT_CLK : std_logic := '0'; -- deve ser inicializado
  signal ENT_CLK_ENABLE : std_logic := '1'; -- Sinal de Enable do clock só para efeito de controle do fim da simulação
  signal SAI_DISP0 : std_logic_vector(0 to 7);
  signal ENT_RESET : std_logic;

begin
  -- geração do clock com periodo PERIODO
  ENT_CLK <= ENT_CLK_ENABLE and not ENT_CLK after PERIODO/2;
  ENT_CLK_ENABLE <= '1', '0' after 200 * PERIODO; -- a simulação termina após transcorrer 20 períodos de clock.

  -- instanciação do DUT
  DUT : Projeto02 port map(
    CLK_50MHz => ENT_CLK,
    RESET => ENT_RESET,
    DISP0 => SAI_DISP0
  );

  --  process para os estímulos das entradas
  stimulus : process
  begin
    ENT_RESET <= '0';
    wait for 140 * PERIODO;
    ENT_RESET <= '1';
    wait;
  end process stimulus;

end arch_tb_Projeto02;

Projeto02/tb_Projeto02.vcd
$date
  Wed Nov 23 17:46:59 2022
$end
$version
  GHDL v0
$end
$timescale
  1 fs
$end
$scope module standard $end
$upscope $end
$scope module std_logic_1164 $end
$upscope $end
$scope module numeric_std $end
$upscope $end
$scope module tb_projeto02 $end
$var reg 1 ! ent_clk $end
$var reg 1 " ent_clk_enable $end
$var reg 8 # sai_disp0[0:7] $end
$var reg 1 $ ent_reset $end
$scope module dut $end
$var reg 1 % clk_50mhz $end
$var reg 1 & reset $end
$var reg 8 ' disp0[0:7] $end
$var reg 1 ( internal_clk_2hz $end
$scope module my_clockdivider $end
$var reg 1 ) clk_input $end
$var reg 1 * clk_output $end
$var reg 1 + clk_aux $end
$upscope $end
$scope module my_fsm $end
$var reg 1 , clk_fsm $end
$var reg 1 - x $end
$var reg 3 . y[2:0] $end
$var reg 8 / z0[0:7] $end
$comment ps is not handled $end
$comment ns is not handled $end
$upscope $end
$upscope $end
$upscope $end
$enddefinitions $end
#0
0!
1"
b01111111 #
0$
0%
0&
b01111111 '
0(
0)
0*
0+
0,
0-
b000 .
b01111111 /
#10000000
1!
1%
1)
#20000000
0!
0%
0)
#30000000
1!
1%
1)
#40000000
0!
0%
0)
#50000000
1!
1%
1)
#60000000
0!
0%
0)
#70000000
1!
1%
1)
#80000000
0!
0%
0)
#90000000
1!
b10111111 #
1%
b10111111 '
1(
1)
1*
1+
1,
b001 .
b10111111 /
#100000000
0!
0%
0)
#110000000
1!
1%
1)
#120000000
0!
0%
0)
#130000000
1!
1%
1)
#140000000
0!
0%
0)
#150000000
1!
1%
1)
#160000000
0!
0%
0)
#170000000
1!
1%
1)
#180000000
0!
0%
0)
#190000000
1!
1%
0(
1)
0*
0+
0,
#200000000
0!
0%
0)
#210000000
1!
1%
1)
#220000000
0!
0%
0)
#230000000
1!
1%
1)
#240000000
0!
0%
0)
#250000000
1!
1%
1)
#260000000
0!
0%
0)
#270000000
1!
1%
1)
#280000000
0!
0%
0)
#290000000
1!
b11011111 #
1%
b11011111 '
1(
1)
1*
1+
1,
b010 .
b11011111 /
#300000000
0!
0%
0)
#310000000
1!
1%
1)
#320000000
0!
0%
0)
#330000000
1!
1%
1)
#340000000
0!
0%
0)
#350000000
1!
1%
1)
#360000000
0!
0%
0)
#370000000
1!
1%
1)
#380000000
0!
0%
0)
#390000000
1!
1%
0(
1)
0*
0+
0,
#400000000
0!
0%
0)
#410000000
1!
1%
1)
#420000000
0!
0%
0)
#430000000
1!
1%
1)
#440000000
0!
0%
0)
#450000000
1!
1%
1)
#460000000
0!
0%
0)
#470000000
1!
1%
1)
#480000000
0!
0%
0)
#490000000
1!
b01111111 #
1%
b01111111 '
1(
1)
1*
1+
1,
b000 .
b01111111 /
#500000000
0!
0%
0)
#510000000
1!
1%
1)
#520000000
0!
0%
0)
#530000000
1!
1%
1)
#540000000
0!
0%
0)
#550000000
1!
1%
1)
#560000000
0!
0%
0)
#570000000
1!
1%
1)
#580000000
0!
0%
0)
#590000000
1!
1%
0(
1)
0*
0+
0,
#600000000
0!
0%
0)
#610000000
1!
1%
1)
#620000000
0!
0%
0)
#630000000
1!
1%
1)
#640000000
0!
0%
0)
#650000000
1!
1%
1)
#660000000
0!
0%
0)
#670000000
1!
1%
1)
#680000000
0!
0%
0)
#690000000
1!
b10111111 #
1%
b10111111 '
1(
1)
1*
1+
1,
b001 .
b10111111 /
#700000000
0!
0%
0)
#710000000
1!
1%
1)
#720000000
0!
0%
0)
#730000000
1!
1%
1)
#740000000
0!
0%
0)
#750000000
1!
1%
1)
#760000000
0!
0%
0)
#770000000
1!
1%
1)
#780000000
0!
0%
0)
#790000000
1!
1%
0(
1)
0*
0+
0,
#800000000
0!
0%
0)
#810000000
1!
1%
1)
#820000000
0!
0%
0)
#830000000
1!
1%
1)
#840000000
0!
0%
0)
#850000000
1!
1%
1)
#860000000
0!
0%
0)
#870000000
1!
1%
1)
#880000000
0!
0%
0)
#890000000
1!
b11011111 #
1%
b11011111 '
1(
1)
1*
1+
1,
b010 .
b11011111 /
#900000000
0!
0%
0)
#910000000
1!
1%
1)
#920000000
0!
0%
0)
#930000000
1!
1%
1)
#940000000
0!
0%
0)
#950000000
1!
1%
1)
#960000000
0!
0%
0)
#970000000
1!
1%
1)
#980000000
0!
0%
0)
#990000000
1!
1%
0(
1)
0*
0+
0,
#1000000000
0!
0%
0)
#1010000000
1!
1%
1)
#1020000000
0!
0%
0)
#1030000000
1!
1%
1)
#1040000000
0!
0%
0)
#1050000000
1!
1%
1)
#1060000000
0!
0%
0)
#1070000000
1!
1%
1)
#1080000000
0!
0%
0)
#1090000000
1!
b01111111 #
1%
b01111111 '
1(
1)
1*
1+
1,
b000 .
b01111111 /
#1100000000
0!
0%
0)
#1110000000
1!
1%
1)
#1120000000
0!
0%
0)
#1130000000
1!
1%
1)
#1140000000
0!
0%
0)
#1150000000
1!
1%
1)
#1160000000
0!
0%
0)
#1170000000
1!
1%
1)
#1180000000
0!
0%
0)
#1190000000
1!
1%
0(
1)
0*
0+
0,
#1200000000
0!
0%
0)
#1210000000
1!
1%
1)
#1220000000
0!
0%
0)
#1230000000
1!
1%
1)
#1240000000
0!
0%
0)
#1250000000
1!
1%
1)
#1260000000
0!
0%
0)
#1270000000
1!
1%
1)
#1280000000
0!
0%
0)
#1290000000
1!
b10111111 #
1%
b10111111 '
1(
1)
1*
1+
1,
b001 .
b10111111 /
#1300000000
0!
0%
0)
#1310000000
1!
1%
1)
#1320000000
0!
0%
0)
#1330000000
1!
1%
1)
#1340000000
0!
0%
0)
#1350000000
1!
1%
1)
#1360000000
0!
0%
0)
#1370000000
1!
1%
1)
#1380000000
0!
0%
0)
#1390000000
1!
1%
0(
1)
0*
0+
0,
#1400000000
0!
0%
0)
#1410000000
1!
1%
1)
#1420000000
0!
0%
0)
#1430000000
1!
1%
1)
#1440000000
0!
0%
0)
#1450000000
1!
1%
1)
#1460000000
0!
0%
0)
#1470000000
1!
1%
1)
#1480000000
0!
0%
0)
#1490000000
1!
b11011111 #
1%
b11011111 '
1(
1)
1*
1+
1,
b010 .
b11011111 /
#1500000000
0!
0%
0)
#1510000000
1!
1%
1)
#1520000000
0!
0%
0)
#1530000000
1!
1%
1)
#1540000000
0!
0%
0)
#1550000000
1!
1%
1)
#1560000000
0!
0%
0)
#1570000000
1!
1%
1)
#1580000000
0!
0%
0)
#1590000000
1!
1%
0(
1)
0*
0+
0,
#1600000000
0!
0%
0)
#1610000000
1!
1%
1)
#1620000000
0!
0%
0)
#1630000000
1!
1%
1)
#1640000000
0!
0%
0)
#1650000000
1!
1%
1)
#1660000000
0!
0%
0)
#1670000000
1!
1%
1)
#1680000000
0!
0%
0)
#1690000000
1!
b01111111 #
1%
b01111111 '
1(
1)
1*
1+
1,
b000 .
b01111111 /
#1700000000
0!
0%
0)
#1710000000
1!
1%
1)
#1720000000
0!
0%
0)
#1730000000
1!
1%
1)
#1740000000
0!
0%
0)
#1750000000
1!
1%
1)
#1760000000
0!
0%
0)
#1770000000
1!
1%
1)
#1780000000
0!
0%
0)
#1790000000
1!
1%
0(
1)
0*
0+
0,
#1800000000
0!
0%
0)
#1810000000
1!
1%
1)
#1820000000
0!
0%
0)
#1830000000
1!
1%
1)
#1840000000
0!
0%
0)
#1850000000
1!
1%
1)
#1860000000
0!
0%
0)
#1870000000
1!
1%
1)
#1880000000
0!
0%
0)
#1890000000
1!
b10111111 #
1%
b10111111 '
1(
1)
1*
1+
1,
b001 .
b10111111 /
#1900000000
0!
0%
0)
#1910000000
1!
1%
1)
#1920000000
0!
0%
0)
#1930000000
1!
1%
1)
#1940000000
0!
0%
0)
#1950000000
1!
1%
1)
#1960000000
0!
0%
0)
#1970000000
1!
1%
1)
#1980000000
0!
0%
0)
#1990000000
1!
1%
0(
1)
0*
0+
0,
#2000000000
0!
0%
0)
#2010000000
1!
1%
1)
#2020000000
0!
0%
0)
#2030000000
1!
1%
1)
#2040000000
0!
0%
0)
#2050000000
1!
1%
1)
#2060000000
0!
0%
0)
#2070000000
1!
1%
1)
#2080000000
0!
0%
0)
#2090000000
1!
b11011111 #
1%
b11011111 '
1(
1)
1*
1+
1,
b010 .
b11011111 /
#2100000000
0!
0%
0)
#2110000000
1!
1%
1)
#2120000000
0!
0%
0)
#2130000000
1!
1%
1)
#2140000000
0!
0%
0)
#2150000000
1!
1%
1)
#2160000000
0!
0%
0)
#2170000000
1!
1%
1)
#2180000000
0!
0%
0)
#2190000000
1!
1%
0(
1)
0*
0+
0,
#2200000000
0!
0%
0)
#2210000000
1!
1%
1)
#2220000000
0!
0%
0)
#2230000000
1!
1%
1)
#2240000000
0!
0%
0)
#2250000000
1!
1%
1)
#2260000000
0!
0%
0)
#2270000000
1!
1%
1)
#2280000000
0!
0%
0)
#2290000000
1!
b01111111 #
1%
b01111111 '
1(
1)
1*
1+
1,
b000 .
b01111111 /
#2300000000
0!
0%
0)
#2310000000
1!
1%
1)
#2320000000
0!
0%
0)
#2330000000
1!
1%
1)
#2340000000
0!
0%
0)
#2350000000
1!
1%
1)
#2360000000
0!
0%
0)
#2370000000
1!
1%
1)
#2380000000
0!
0%
0)
#2390000000
1!
1%
0(
1)
0*
0+
0,
#2400000000
0!
0%
0)
#2410000000
1!
1%
1)
#2420000000
0!
0%
0)
#2430000000
1!
1%
1)
#2440000000
0!
0%
0)
#2450000000
1!
1%
1)
#2460000000
0!
0%
0)
#2470000000
1!
1%
1)
#2480000000
0!
0%
0)
#2490000000
1!
b10111111 #
1%
b10111111 '
1(
1)
1*
1+
1,
b001 .
b10111111 /
#2500000000
0!
0%
0)
#2510000000
1!
1%
1)
#2520000000
0!
0%
0)
#2530000000
1!
1%
1)
#2540000000
0!
0%
0)
#2550000000
1!
1%
1)
#2560000000
0!
0%
0)
#2570000000
1!
1%
1)
#2580000000
0!
0%
0)
#2590000000
1!
1%
0(
1)
0*
0+
0,
#2600000000
0!
0%
0)
#2610000000
1!
1%
1)
#2620000000
0!
0%
0)
#2630000000
1!
1%
1)
#2640000000
0!
0%
0)
#2650000000
1!
1%
1)
#2660000000
0!
0%
0)
#2670000000
1!
1%
1)
#2680000000
0!
0%
0)
#2690000000
1!
b11011111 #
1%
b11011111 '
1(
1)
1*
1+
1,
b010 .
b11011111 /
#2700000000
0!
0%
0)
#2710000000
1!
1%
1)
#2720000000
0!
0%
0)
#2730000000
1!
1%
1)
#2740000000
0!
0%
0)
#2750000000
1!
1%
1)
#2760000000
0!
0%
0)
#2770000000
1!
1%
1)
#2780000000
0!
0%
0)
#2790000000
1!
1%
0(
1)
0*
0+
0,
#2800000000
0!
b01111111 #
1$
0%
1&
b01111111 '
0)
1-
b01111111 /
#2810000000
1!
1%
1)
#2820000000
0!
0%
0)
#2830000000
1!
1%
1)
#2840000000
0!
0%
0)
#2850000000
1!
1%
1)
#2860000000
0!
0%
0)
#2870000000
1!
1%
1)
#2880000000
0!
0%
0)
#2890000000
1!
1%
1(
1)
1*
1+
1,
b000 .
