Projeto02/FSM/FSM.vhd
-- Atividade pratica da Guia de Aula 08
-- Exercicio 8, pagina 114 do livro Free Range VHDL (2018)

library IEEE;
use IEEE.std_logic_1164.all;

entity FSM is
  port (
    CLK_FSM : in std_logic;
    X : in std_logic; -- entradas da FSM
    Y : out std_logic_vector(2 downto 0); -- saidas para os proximos estados da FSM
    Z : out std_logic_vector(1 downto 0)); -- saida efetiva da FSM
end FSM;

architecture arch_FSM of FSM is
  type state_type is (ST0, ST1, ST2, ST3, ST4, ST5, ST6, ST7);
  attribute ENUM_ENCODING : string;
  attribute ENUM_ENCODING of state_type : type is "000 001 010 011 100 101 110 111";
  signal PS, NS : state_type;
begin
  sync_process : process (CLK_FSM, NS)
  begin
    if (rising_edge(CLK_FSM)) then
      PS <= NS;
    end if;
  end process sync_process;

  comb_process : process (PS, X)
  begin
    Z <= "00"; -- pre-assing saidas

    case PS is
      when ST0 =>
        Z <= "00";

        if (X = '0') then
          NS <= ST0;
        else NS <= ST1;
        end if;

      when ST1 =>
        Z <= "00";

        if (X = '0') then
          NS <= ST1;
        else NS <= ST2;
        end if;

      when ST2 =>
        Z <= "00";

        if (X = '0') then
          NS <= ST2;
        else NS <= ST3;
        end if;

      when ST3 =>
        Z <= "10";

        if (X = '0') then
          NS <= ST3;
        else NS <= ST4;
        end if;

      when ST4 =>
        Z <= "01";

        if (X = '0') then
          NS <= ST0;
        else NS <= ST5;
        end if;

      when ST5 =>
        Z <= "11";

        if (X = '0') then
          NS <= ST5;
        else NS <= ST6;
        end if;

      when ST6 =>
        Z <= "11";

        if (X = '0') then
          NS <= ST6;
        else NS <= ST7;
        end if;

      when ST7 =>
        Z <= "11";

        if (X = '0') then
          NS <= ST7;
        else NS <= ST0;
        end if;

      when others => -- catch all, nunca deve chegar aqui
        Z <= "00";
        NS <= ST0;
    end case;
  end process comb_process;

  -- codificação dos estados Y
  with PS select
    Y <=
    "000" when ST0,
    "001" when ST1,
    "010" when ST2,
    "011" when ST3,
    "100" when ST4,
    "101" when ST5,
    "110" when ST6,
    "111" when ST7,
    "000" when others;
end arch_FSM;

Projeto02/ClockDivider/ClockDivider.vhd
-- CLK_COUNTER_MAX = (1/2) * (fo / fd)
-- fo: freq original do clock. fd: freq desejada do clock

library ieee;
use ieee.std_logic_1164.all;

entity ClockDivider is
  port (
    clk_50Mhz : in std_logic;
    clk_2Hz : out std_logic
  );
end ClockDivider;

architecture arch_ClockDivider of ClockDivider is
  signal clk_aux : std_logic := '0';

  -- constantes
  constant CLK_COUNTER_MAX : integer := 12499999;
  constant TESTBENCH_CLK_COUNTER_MAX : integer := 10;
begin

  -- converte clock de 50Mhz na entrada para 2Hz na saida
  -- process (clk_50Mhz, clk_aux)
  --   variable count : integer range 0 to 2 ** 26 - 1;
  -- begin
  --   if (rising_edge(clk_50Mhz)) then
  --     count := count + 1;
  --     if (count = CLK_COUNTER_MAX) then
  --       clk_aux <= not clk_aux;
  --       count := 0;
  --     end if;
  --   end if;
  --   clk_2Hz <= clk_aux;
  -- end process;

  -- para fins exclusivos de testbench: converte clock de 50Mhz na entrada para 5MHz na saida
  process (clk_50Mhz, clk_aux)
    variable count : integer range 0 to 2 ** 26 - 1;
  begin
    if (rising_edge(clk_50Mhz)) then
      count := count + 1;
      if (count = TESTBENCH_CLK_COUNTER_MAX) then
        clk_aux <= not clk_aux;
        count := 0;
      end if;
    end if;
    clk_2Hz <= clk_aux;
  end process;
end arch_ClockDivider;

Projeto02/Projeto02.vhd
library ieee;

use ieee.std_logic_1164.all;
use ieee.numeric_std.all;

entity Projeto02 is
  port (
    CLK, RESET : in std_logic;
    PROJ_OUT : out std_logic_vector(1 downto 0)
  );
end Projeto02;

architecture arch_Projeto02 of Projeto02 is
  -- puxa o divisor de clock
  component ClockDivider is
    port (
      clk_50Mhz : in std_logic;
      clk_2Hz : out std_logic
    );
  end component;

  -- puxa a FSM
  component FSM is
    port (
      CLK_FSM : in std_logic;
      X : in std_logic; -- entradas da FSM
      Y : out std_logic_vector(2 downto 0); -- saidas para os proximos estados da FSM
      Z : out std_logic_vector(1 downto 0) -- saida efetiva da FSM
    );
  end component FSM;

  -- signals intermediarios (internos ao componente de alto nivel)
  signal INTERNAL_CLK_2HZ : std_logic;
  signal INTERNAL_Y : std_logic_vector(2 downto 0);

begin
  my_ClockDivider : ClockDivider port map(
    clk_50Mhz => CLK,
    clk_2Hz => INTERNAL_CLK_2HZ
  );

  my_FSM : FSM port map(
    CLK_FSM => INTERNAL_CLK_2HZ,
    X => RESET,
    Y => INTERNAL_Y,
    Z => PROJ_OUT
  );

end arch_Projeto02;

Projeto02/tb_Projeto02.vhd
library IEEE;
use IEEE.STD_LOGIC_1164.all;
use ieee.numeric_std.all;

entity tb_Projeto02 is
end tb_Projeto02;

architecture arch_tb_Projeto02 of tb_Projeto02 is

  component Projeto02 is
    port (
      CLK, RESET : in std_logic;
      PROJ_OUT : out std_logic_vector(1 downto 0)
    );
  end component;

  constant PERIODO : time := 10 ns;
  signal ent_clk : std_logic := '0'; -- deve ser inicializado
  signal ent_clk_enable : std_logic := '1'; -- Sinal de Enable do clock só para efeito de controle do fim da simulação
  signal sai_proj_out : std_logic_vector(1 downto 0);
  signal ent_reset : std_logic;

begin
  -- geração do clock com periodo PERIODO
  ent_clk <= ent_clk_enable and not ent_clk after PERIODO/2;
  ent_clk_enable <= '1', '0' after 200 * PERIODO; -- a simulação termina após transcorrer 20 períodos de clock.

  -- instanciação do DUT
  DUT : Projeto02 port map(
    CLK => ent_clk,
    RESET => ent_reset,
    PROJ_OUT => sai_proj_out
  );

  --  process para os estímulos das entradas
  stimulus : process
  begin
    ent_reset <= '0';
    wait for 4 * PERIODO;
    ent_reset <= '1';
    wait for 4 * PERIODO;
    ent_reset <= '0';
    wait for 4 * PERIODO;
    ent_reset <= '1';
    wait for 4 * PERIODO;
    wait;
  end process stimulus;

end arch_tb_Projeto02;

Projeto02/tb_Projeto02.vcd
$date
  Wed Nov 23 15:52:47 2022
$end
$version
  GHDL v0
$end
$timescale
  1 fs
$end
$scope module standard $end
$upscope $end
$scope module std_logic_1164 $end
$upscope $end
$scope module numeric_std $end
$upscope $end
$scope module tb_projeto02 $end
$var reg 1 ! ent_clk $end
$var reg 1 " ent_clk_enable $end
$var reg 2 # sai_proj_out[1:0] $end
$var reg 1 $ ent_reset $end
$scope module dut $end
$var reg 1 % clk $end
$var reg 1 & reset $end
$var reg 2 ' proj_out[1:0] $end
$var reg 1 ( internal_clk_2hz $end
$var reg 3 ) internal_y[2:0] $end
$scope module my_clockdivider $end
$var reg 1 * clk_50mhz $end
$var reg 1 + clk_2hz $end
$var reg 1 , clk_aux $end
$upscope $end
$scope module my_fsm $end
$var reg 1 - clk_fsm $end
$var reg 1 . x $end
$var reg 3 / y[2:0] $end
$var reg 2 0 z[1:0] $end
$comment ps is not handled $end
$comment ns is not handled $end
$upscope $end
$upscope $end
$upscope $end
$enddefinitions $end
#0
0!
1"
b00 #
0$
0%
0&
b00 '
0(
b000 )
0*
0+
0,
0-
0.
b000 /
b00 0
#5000000
1!
1%
1*
#10000000
0!
0%
0*
#15000000
1!
1%
1*
#20000000
0!
0%
0*
#25000000
1!
1%
1*
#30000000
0!
0%
0*
#35000000
1!
1%
1*
#40000000
0!
1$
0%
1&
0*
1.
#45000000
1!
1%
1*
#50000000
0!
0%
0*
#55000000
1!
1%
1*
#60000000
0!
0%
0*
#65000000
1!
1%
1*
#70000000
0!
0%
0*
#75000000
1!
1%
1*
#80000000
0!
0$
0%
0&
0*
0.
#85000000
1!
1%
1*
#90000000
0!
0%
0*
#95000000
1!
1%
1(
1*
1+
1,
1-
#100000000
0!
0%
0*
#105000000
1!
1%
1*
#110000000
0!
0%
0*
#115000000
1!
1%
1*
#120000000
0!
1$
0%
1&
0*
1.
#125000000
1!
1%
1*
#130000000
0!
0%
0*
#135000000
1!
1%
1*
#140000000
0!
0%
0*
#145000000
1!
1%
1*
#150000000
0!
0%
0*
#155000000
1!
1%
1*
#160000000
0!
0%
0*
#165000000
1!
1%
1*
#170000000
0!
0%
0*
#175000000
1!
1%
1*
#180000000
0!
0%
0*
#185000000
1!
1%
1*
#190000000
0!
0%
0*
#195000000
1!
1%
0(
1*
0+
0,
0-
#200000000
0!
0%
0*
#205000000
1!
1%
1*
#210000000
0!
0%
0*
#215000000
1!
1%
1*
#220000000
0!
0%
0*
#225000000
1!
1%
1*
#230000000
0!
0%
0*
#235000000
1!
1%
1*
#240000000
0!
0%
0*
#245000000
1!
1%
1*
#250000000
0!
0%
0*
#255000000
1!
1%
1*
#260000000
0!
0%
0*
#265000000
1!
1%
1*
#270000000
0!
0%
0*
#275000000
1!
1%
1*
#280000000
0!
0%
0*
#285000000
1!
1%
1*
#290000000
0!
0%
0*
#295000000
1!
1%
1(
b001 )
1*
1+
1,
1-
b001 /
#300000000
0!
0%
0*
#305000000
1!
1%
1*
#310000000
0!
0%
0*
#315000000
1!
1%
1*
#320000000
0!
0%
0*
#325000000
1!
1%
1*
#330000000
0!
0%
0*
#335000000
1!
1%
1*
#340000000
0!
0%
0*
#345000000
1!
1%
1*
#350000000
0!
0%
0*
#355000000
1!
1%
1*
#360000000
0!
0%
0*
#365000000
1!
1%
1*
#370000000
0!
0%
0*
#375000000
1!
1%
1*
#380000000
0!
0%
0*
#385000000
1!
1%
1*
#390000000
0!
0%
0*
#395000000
1!
1%
0(
1*
0+
0,
0-
#400000000
0!
0%
0*
#405000000
1!
1%
1*
#410000000
0!
0%
0*
#415000000
1!
1%
1*
#420000000
0!
0%
0*
#425000000
1!
1%
1*
#430000000
0!
0%
0*
#435000000
1!
1%
1*
#440000000
0!
0%
0*
#445000000
1!
1%
1*
#450000000
0!
0%
0*
#455000000
1!
1%
1*
#460000000
0!
0%
0*
#465000000
1!
1%
1*
#470000000
0!
0%
0*
#475000000
1!
1%
1*
#480000000
0!
0%
0*
#485000000
1!
1%
1*
#490000000
0!
0%
0*
#495000000
1!
1%
1(
b010 )
1*
1+
1,
1-
b010 /
#500000000
0!
0%
0*
#505000000
1!
1%
1*
#510000000
0!
0%
0*
#515000000
1!
1%
1*
#520000000
0!
0%
0*
#525000000
1!
1%
1*
#530000000
0!
0%
0*
#535000000
1!
1%
1*
#540000000
0!
0%
0*
#545000000
1!
1%
1*
#550000000
0!
0%
0*
#555000000
1!
1%
1*
#560000000
0!
0%
0*
#565000000
1!
1%
1*
#570000000
0!
0%
0*
#575000000
1!
1%
1*
#580000000
0!
0%
0*
#585000000
1!
1%
1*
#590000000
0!
0%
0*
#595000000
1!
1%
0(
1*
0+
0,
0-
#600000000
0!
0%
0*
#605000000
1!
1%
1*
#610000000
0!
0%
0*
#615000000
1!
1%
1*
#620000000
0!
0%
0*
#625000000
1!
1%
1*
#630000000
0!
0%
0*
#635000000
1!
1%
1*
#640000000
0!
0%
0*
#645000000
1!
1%
1*
#650000000
0!
0%
0*
#655000000
1!
1%
1*
#660000000
0!
0%
0*
#665000000
1!
1%
1*
#670000000
0!
0%
0*
#675000000
1!
1%
1*
#680000000
0!
0%
0*
#685000000
1!
1%
1*
#690000000
0!
0%
0*
#695000000
1!
b10 #
1%
b10 '
1(
b011 )
1*
1+
1,
1-
b011 /
b10 0
#700000000
0!
0%
0*
#705000000
1!
1%
1*
#710000000
0!
0%
0*
#715000000
1!
1%
1*
#720000000
0!
0%
0*
#725000000
1!
1%
1*
#730000000
0!
0%
0*
#735000000
1!
1%
1*
#740000000
0!
0%
0*
#745000000
1!
1%
1*
#750000000
0!
0%
0*
#755000000
1!
1%
1*
#760000000
0!
0%
0*
#765000000
1!
1%
1*
#770000000
0!
0%
0*
#775000000
1!
1%
1*
#780000000
0!
0%
0*
#785000000
1!
1%
1*
#790000000
0!
0%
0*
#795000000
1!
1%
0(
1*
0+
0,
0-
#800000000
0!
0%
0*
#805000000
1!
1%
1*
#810000000
0!
0%
0*
#815000000
1!
1%
1*
#820000000
0!
0%
0*
#825000000
1!
1%
1*
#830000000
0!
0%
0*
#835000000
1!
1%
1*
#840000000
0!
0%
0*
#845000000
1!
1%
1*
#850000000
0!
0%
0*
#855000000
1!
1%
1*
#860000000
0!
0%
0*
#865000000
1!
1%
1*
#870000000
0!
0%
0*
#875000000
1!
1%
1*
#880000000
0!
0%
0*
#885000000
1!
1%
1*
#890000000
0!
0%
0*
#895000000
1!
b01 #
1%
b01 '
1(
b100 )
1*
1+
1,
1-
b100 /
b01 0
#900000000
0!
0%
0*
#905000000
1!
1%
1*
#910000000
0!
0%
0*
#915000000
1!
1%
1*
#920000000
0!
0%
0*
#925000000
1!
1%
1*
#930000000
0!
0%
0*
#935000000
1!
1%
1*
#940000000
0!
0%
0*
#945000000
1!
1%
1*
#950000000
0!
0%
0*
#955000000
1!
1%
1*
#960000000
0!
0%
0*
#965000000
1!
1%
1*
#970000000
0!
0%
0*
#975000000
1!
1%
1*
#980000000
0!
0%
0*
#985000000
1!
1%
1*
#990000000
0!
0%
0*
#995000000
1!
1%
0(
1*
0+
0,
0-
#1000000000
0!
0%
0*
#1005000000
1!
1%
1*
#1010000000
0!
0%
0*
#1015000000
1!
1%
1*
#1020000000
0!
0%
0*
#1025000000
1!
1%
1*
#1030000000
0!
0%
0*
#1035000000
1!
1%
1*
#1040000000
0!
0%
0*
#1045000000
1!
1%
1*
#1050000000
0!
0%
0*
#1055000000
1!
1%
1*
#1060000000
0!
0%
0*
#1065000000
1!
1%
1*
#1070000000
0!
0%
0*
#1075000000
1!
1%
1*
#1080000000
0!
0%
0*
#1085000000
1!
1%
1*
#1090000000
0!
0%
0*
#1095000000
1!
b11 #
1%
b11 '
1(
b101 )
1*
1+
1,
1-
b101 /
b11 0
#1100000000
0!
0%
0*
#1105000000
1!
1%
1*
#1110000000
0!
0%
0*
#1115000000
1!
1%
1*
#1120000000
0!
0%
0*
#1125000000
1!
1%
1*
#1130000000
0!
0%
0*
#1135000000
1!
1%
1*
#1140000000
0!
0%
0*
#1145000000
1!
1%
1*
#1150000000
0!
0%
0*
#1155000000
1!
1%
1*
#1160000000
0!
0%
0*
#1165000000
1!
1%
1*
#1170000000
0!
0%
0*
#1175000000
1!
1%
1*
#1180000000
0!
0%
0*
#1185000000
1!
1%
1*
#1190000000
0!
0%
0*
#1195000000
1!
1%
0(
1*
0+
0,
0-
#1200000000
0!
0%
0*
#1205000000
1!
1%
1*
#1210000000
0!
0%
0*
#1215000000
1!
1%
1*
#1220000000
0!
0%
0*
#1225000000
1!
1%
1*
#1230000000
0!
0%
0*
#1235000000
1!
1%
1*
#1240000000
0!
0%
0*
#1245000000
1!
1%
1*
#1250000000
0!
0%
0*
#1255000000
1!
1%
1*
#1260000000
0!
0%
0*
#1265000000
1!
1%
1*
#1270000000
0!
0%
0*
#1275000000
1!
1%
1*
#1280000000
0!
0%
0*
#1285000000
1!
1%
1*
#1290000000
0!
0%
0*
#1295000000
1!
1%
b11 '
1(
b110 )
1*
1+
1,
1-
b110 /
b11 0
#1300000000
0!
0%
0*
#1305000000
1!
1%
1*
#1310000000
0!
0%
0*
#1315000000
1!
1%
1*
#1320000000
0!
0%
0*
#1325000000
1!
1%
1*
#1330000000
0!
0%
0*
#1335000000
1!
1%
1*
#1340000000
0!
0%
0*
#1345000000
1!
1%
1*
#1350000000
0!
0%
0*
#1355000000
1!
1%
1*
#1360000000
0!
0%
0*
#1365000000
1!
1%
1*
#1370000000
0!
0%
0*
#1375000000
1!
1%
1*
#1380000000
0!
0%
0*
#1385000000
1!
1%
1*
#1390000000
0!
0%
0*
#1395000000
1!
1%
0(
1*
0+
0,
0-
#1400000000
0!
0%
0*
#1405000000
1!
1%
1*
#1410000000
0!
0%
0*
#1415000000
1!
1%
1*
#1420000000
0!
0%
0*
#1425000000
1!
1%
1*
#1430000000
0!
0%
0*
#1435000000
1!
1%
1*
#1440000000
0!
0%
0*
#1445000000
1!
1%
1*
#1450000000
0!
0%
0*
#1455000000
1!
1%
1*
#1460000000
0!
0%
0*
#1465000000
1!
1%
1*
#1470000000
0!
0%
0*
#1475000000
1!
1%
1*
#1480000000
0!
0%
0*
#1485000000
1!
1%
1*
#1490000000
0!
0%
0*
#1495000000
1!
1%
b11 '
1(
b111 )
1*
1+
1,
1-
b111 /
b11 0
#1500000000
0!
0%
0*
#1505000000
1!
1%
1*
#1510000000
0!
0%
0*
#1515000000
1!
1%
1*
#1520000000
0!
0%
0*
#1525000000
1!
1%
1*
#1530000000
0!
0%
0*
#1535000000
1!
1%
1*
#1540000000
0!
0%
0*
#1545000000
1!
1%
1*
#1550000000
0!
0%
0*
#1555000000
1!
1%
1*
#1560000000
0!
0%
0*
#1565000000
1!
1%
1*
#1570000000
0!
0%
0*
#1575000000
1!
1%
1*
#1580000000
0!
0%
0*
#1585000000
1!
1%
1*
#1590000000
0!
0%
0*
#1595000000
1!
1%
0(
1*
0+
0,
0-
#1600000000
0!
0%
0*
#1605000000
1!
1%
1*
#1610000000
0!
0%
0*
#1615000000
1!
1%
1*
#1620000000
0!
0%
0*
#1625000000
1!
1%
1*
#1630000000
0!
0%
0*
#1635000000
1!
1%
1*
#1640000000
0!
0%
0*
#1645000000
1!
1%
1*
#1650000000
0!
0%
0*
#1655000000
1!
1%
1*
#1660000000
0!
0%
0*
#1665000000
1!
1%
1*
#1670000000
0!
0%
0*
#1675000000
1!
1%
1*
#1680000000
0!
0%
0*
#1685000000
1!
1%
1*
#1690000000
0!
0%
0*
#1695000000
1!
b00 #
1%
b00 '
1(
b000 )
1*
1+
1,
1-
b000 /
b00 0
#1700000000
0!
0%
0*
#1705000000
1!
1%
1*
#1710000000
0!
0%
0*
#1715000000
1!
1%
1*
#1720000000
0!
0%
0*
#1725000000
1!
1%
1*
#1730000000
0!
0%
0*
#1735000000
1!
1%
1*
#1740000000
0!
0%
0*
#1745000000
1!
1%
1*
#1750000000
0!
0%
0*
#1755000000
1!
1%
1*
#1760000000
0!
0%
0*
#1765000000
1!
1%
1*
#1770000000
0!
0%
0*
#1775000000
1!
1%
1*
#1780000000
0!
0%
0*
#1785000000
1!
1%
1*
#1790000000
0!
0%
0*
#1795000000
1!
1%
0(
1*
0+
0,
0-
#1800000000
0!
0%
0*
#1805000000
1!
1%
1*
#1810000000
0!
0%
0*
#1815000000
1!
1%
1*
#1820000000
0!
0%
0*
#1825000000
1!
1%
1*
#1830000000
0!
0%
0*
#1835000000
1!
1%
1*
#1840000000
0!
0%
0*
#1845000000
1!
1%
1*
#1850000000
0!
0%
0*
#1855000000
1!
1%
1*
#1860000000
0!
0%
0*
#1865000000
1!
1%
1*
#1870000000
0!
0%
0*
#1875000000
1!
1%
1*
#1880000000
0!
0%
0*
#1885000000
1!
1%
1*
#1890000000
0!
0%
0*
#1895000000
1!
1%
1(
b001 )
1*
1+
1,
1-
b001 /
