Projeto02/FSM/FSM.vhd
-- Atividade pratica da Guia de Aula 08
-- Exercicio 8, pagina 114 do livro Free Range VHDL (2018)

library IEEE;
use IEEE.std_logic_1164.all;

entity FSM is
  port (
    CLK_FSM : in std_logic;
    X : in std_logic; -- entrada da FSM
    Y : out std_logic_vector(2 downto 0); -- saidas para os proximos estados da FSM
    Z0 : out std_logic_vector(0 to 7)); -- saidas efetivas da FSM
end FSM;

architecture arch_FSM of FSM is
  type state_type is (ST0, ST1, ST2, ST3, ST4, ST5);
  attribute ENUM_ENCODING : string;
  attribute ENUM_ENCODING of state_type : type is "000 001 010 011 100 101";
  signal PS, NS : state_type;
begin
  sync_process : process (CLK_FSM, NS)
  begin
    if (rising_edge(CLK_FSM)) then
      PS <= NS;
    end if;
  end process sync_process;

  comb_process : process (PS, X)
  begin
    Z0 <= "01111111";

    case PS is
      when ST0 =>
        if (X = '1') then
          NS <= ST0;
          Z0 <= "01111111";
        elsif (X = '0') then
          NS <= ST1;
          Z0 <= "01111111";
        else -- catch all
          NS <= ST0;
          Z0 <= "01111111";
        end if;

      when ST1 =>
        if (X = '1') then
          NS <= ST0;
          Z0 <= "01111111";
        elsif (X = '0') then
          NS <= ST2;
          Z0 <= "10111111";
        else -- catch all
          NS <= ST0;
          Z0 <= "01111111";
        end if;

      when ST2 =>
        if (X = '1') then
          NS <= ST0;
          Z0 <= "01111111";
        elsif (X = '0') then
          NS <= ST0;
          Z0 <= "11011111";
        else -- catch all
          NS <= ST0;
          Z0 <= "01111111";
        end if;

      when others => -- catch all, nunca deve chegar aqui
        NS <= ST0;
        Z0 <= "01111111";
    end case;
  end process comb_process;

  -- codificação dos estados Y
  with PS select
    Y <=
    "000" when ST0,
    "001" when ST1,
    "010" when ST2,
    "011" when ST3,
    "100" when ST4,
    "101" when ST5,
    "000" when others;
end arch_FSM;

Projeto02/FSM/tb_FSM.vhd
library IEEE;
use IEEE.STD_LOGIC_1164.all;
use ieee.numeric_std.all;

entity tb_FSM is
end tb_FSM;

architecture arch_tb_FSM of tb_FSM is

  component FSM is
    port (
      CLK_FSM : in std_logic;
      X : in std_logic; -- entrada da FSM
      Y : out std_logic_vector(2 downto 0); -- saidas para os proximos estados da FSM
      Z0 : out std_logic_vector(0 to 7)); -- saidas efetivas da FSM
  end component;

  constant PERIODO : time := 20 ns; -- 50MHz
  signal ENT_CLK : std_logic := '0'; -- deve ser inicializado
  signal ENT_CLK_ENABLE : std_logic := '1'; -- Sinal de Enable do clock só para efeito de controle do fim da simulação
  signal ENT_X : std_logic; 
  signal SAI_Y : std_logic_vector(2 downto 0);
  signal SAI_Z0 : std_logic_vector(0 to 7);

begin
  -- geração do clock com periodo PERIODO
  ENT_CLK <= ENT_CLK_ENABLE and not ENT_CLK after PERIODO/2;
  ENT_CLK_ENABLE <= '1', '0' after 20 * PERIODO; -- a simulação termina após transcorrer 20 períodos de clock.

  -- instanciação do DUT
  DUT : FSM port map(
    CLK_FSM => ENT_CLK,
    X => ENT_X,
    Y => SAI_Y,
    Z0 => SAI_Z0
  );

  --  process para os estímulos das entradas
  stimulus : process
  begin
    ENT_X <= '0';
    wait for 12 * PERIODO;
    ENT_X <= '1';
    wait;
  end process stimulus;
end arch_tb_FSM;

Projeto02/FSM/tb_FSM.vcd
$date
  Wed Nov 23 17:40:54 2022
$end
$version
  GHDL v0
$end
$timescale
  1 fs
$end
$scope module standard $end
$upscope $end
$scope module std_logic_1164 $end
$upscope $end
$scope module numeric_std $end
$upscope $end
$scope module tb_fsm $end
$var reg 1 ! ent_clk $end
$var reg 1 " ent_clk_enable $end
$var reg 1 # ent_x $end
$var reg 3 $ sai_y[2:0] $end
$var reg 8 % sai_z0[0:7] $end
$scope module dut $end
$var reg 1 & clk_fsm $end
$var reg 1 ' x $end
$var reg 3 ( y[2:0] $end
$var reg 8 ) z0[0:7] $end
$comment ps is not handled $end
$comment ns is not handled $end
$upscope $end
$upscope $end
$enddefinitions $end
#0
0!
1"
0#
b000 $
b01111111 %
0&
0'
b000 (
b01111111 )
#10000000
1!
b001 $
b10111111 %
1&
b001 (
b10111111 )
#20000000
0!
0&
#30000000
1!
b010 $
b11011111 %
1&
b010 (
b11011111 )
#40000000
0!
0&
#50000000
1!
b000 $
b01111111 %
1&
b000 (
b01111111 )
#60000000
0!
0&
#70000000
1!
b001 $
b10111111 %
1&
b001 (
b10111111 )
#80000000
0!
0&
#90000000
1!
b010 $
b11011111 %
1&
b010 (
b11011111 )
#100000000
0!
0&
#110000000
1!
b000 $
b01111111 %
1&
b000 (
b01111111 )
#120000000
0!
0&
#130000000
1!
b001 $
b10111111 %
1&
b001 (
b10111111 )
#140000000
0!
0&
#150000000
1!
b010 $
b11011111 %
1&
b010 (
b11011111 )
#160000000
0!
0&
#170000000
1!
b000 $
b01111111 %
1&
b000 (
b01111111 )
#180000000
0!
0&
#190000000
1!
b001 $
b10111111 %
1&
b001 (
b10111111 )
#200000000
0!
0&
#210000000
1!
b010 $
b11011111 %
1&
b010 (
b11011111 )
#220000000
0!
0&
#230000000
1!
b000 $
b01111111 %
1&
b000 (
b01111111 )
#240000000
0!
1#
0&
1'
