Projeto02/FSM/FSM.vhd
library IEEE;
use IEEE.std_logic_1164.all;

entity FSM is
  port (
    CLK_FSM : in std_logic;
    X : in std_logic; -- entrada da FSM
    Z0, Z1, Z2, Z3, Z4, Z5 : out std_logic_vector(0 to 7)); -- saidas efetivas da FSM
end FSM;

architecture arch_FSM of FSM is
  type state_type is (ST0, ST1, ST2, ST3, ST4, ST5, ST6, ST7, ST8, ST9, ST10, ST11, ST12, ST13, ST14, ST15, ST16, ST17, ST18, ST19, ST20, ST21);
  attribute ENUM_ENCODING : string;
  attribute ENUM_ENCODING of state_type : type is
  "00000 00001 00010 00011 00100 00101 00110 00111 01000 01001 01010 01011 01100 01101 01110 01111 10000 10001 10010 10011 10100 10101";
  signal PS, NS : state_type;
  signal Y : std_logic_vector(4 downto 0); -- signal para os proximos estados da FSM
begin
  sync_process : process (CLK_FSM, NS)
  begin
    if (rising_edge(CLK_FSM)) then
      PS <= NS;
    end if;
  end process sync_process;

  comb_process : process (PS, X)
  begin
    -- pre-assign saidas, assim nao precisa definir todas em cada estado
    Z0 <= "11111111";
    Z1 <= "11111111";
    Z2 <= "11111111";
    Z3 <= "11111111";
    Z4 <= "11111111";
    Z5 <= "11111111";

    -- condicao de RESET e a mesma para todos os estados, pode ir fora dos CASES
    if (X /= '0') then
      NS <= ST0;
      Z0 <= "10111111";
    else
      case PS is
        when ST0 =>
          NS <= ST1;
          Z0 <= "10111111";

        when ST1 =>
          NS <= ST2;
          Z0 <= "01111111";

        when ST2 =>
          NS <= ST3;
          Z1 <= "01111111";

        when ST3 =>
          NS <= ST4;
          Z2 <= "01111111";

        when ST4 =>
          NS <= ST5;
          Z3 <= "01111111";

        when ST5 =>
          NS <= ST6;
          Z4 <= "01111111";

        when ST6 =>
          NS <= ST7;
          Z5 <= "01111111";

        when ST7 =>
          NS <= ST8;
          Z5 <= "11111011";

        when ST8 =>
          NS <= ST9;
          Z5 <= "11110111";

        when ST9 =>
          NS <= ST10;
          Z5 <= "11101111";

        when ST10 =>
          NS <= ST11;
          Z4 <= "11101111";

        when ST11 =>
          NS <= ST12;
          Z3 <= "11101111";

        when ST12 =>
          NS <= ST13;
          Z2 <= "11101111";

        when ST13 =>
          NS <= ST14;
          Z1 <= "11101111";

        when ST14 =>
          NS <= ST15;
          Z0 <= "11101111";

        when ST15 =>
          NS <= ST16;
          Z0 <= "11011111";

        when ST16 =>
          NS <= ST17;
          Z0 <= "11111101";

        when ST17 =>
          NS <= ST18;
          Z1 <= "11111101";

        when ST18 =>
          NS <= ST19;
          Z2 <= "11111101";

        when ST19 =>
          NS <= ST20;
          Z3 <= "11111101";

        when ST20 =>
          NS <= ST21;
          Z4 <= "11111101";

        when ST21 =>
          NS <= ST0;
          Z5 <= "11111101";

        when others => -- catch all, nunca deve chegar aqui
          NS <= ST0;
          Z0 <= "10111111";
      end case;
    end if;
  end process comb_process;

  -- codificação dos estados Y
  with PS select
    Y <=
    "00000" when ST0,
    "00001" when ST1,
    "00010" when ST2,
    "00011" when ST3,
    "00100" when ST4,
    "00101" when ST5,
    "00110" when ST6,
    "00111" when ST7,
    "01000" when ST8,
    "01001" when ST9,
    "01010" when ST10,
    "01011" when ST11,
    "01100" when ST12,
    "01101" when ST13,
    "01110" when ST14,
    "01111" when ST15,
    "10000" when ST16,
    "10001" when ST17,
    "10010" when ST18,
    "10011" when ST19,
    "10100" when ST20,
    "10101" when ST21,
    "00000" when others;
end arch_FSM;

Projeto02/FSM/tb_FSM.vhd
library IEEE;
use IEEE.STD_LOGIC_1164.all;
use ieee.numeric_std.all;

entity tb_FSM is
end tb_FSM;

architecture arch_tb_FSM of tb_FSM is

  component FSM is
    port (
      CLK_FSM : in std_logic;
      X : in std_logic; -- entrada da FSM
      Z0, Z1, Z2, Z3, Z4, Z5 : out std_logic_vector(0 to 7)); -- saidas efetivas da FSM
  end component;

  constant PERIODO : time := 20 ns; -- 50MHz
  signal ENT_CLK : std_logic := '0'; -- deve ser inicializado
  signal ENT_CLK_ENABLE : std_logic := '1'; -- Sinal de Enable do clock só para efeito de controle do fim da simulação
  signal ENT_X : std_logic; 
  signal SAI_Z0, SAI_Z1, SAI_Z2, SAI_Z3, SAI_Z4, SAI_Z5 : std_logic_vector(0 to 7);

begin
  -- geração do clock com periodo PERIODO
  ENT_CLK <= ENT_CLK_ENABLE and not ENT_CLK after PERIODO/2;
  ENT_CLK_ENABLE <= '1', '0' after 50 * PERIODO; -- a simulação termina após transcorrer 20 períodos de clock.

  -- instanciação do DUT
  DUT : FSM port map(
    CLK_FSM => ENT_CLK,
    X => ENT_X,
    Z0 => SAI_Z0,
    Z1 => SAI_Z1,
    Z2 => SAI_Z2,
    Z3 => SAI_Z3,
    Z4 => SAI_Z4,
    Z5 => SAI_Z5
  );

  --  process para os estímulos das entradas
  stimulus : process
  begin
    ENT_X <= '0';
    wait for 25 * PERIODO;
    ENT_X <= '1';
    wait for 10 * PERIODO;
    ENT_X <= '0';

    wait;
  end process stimulus;
end arch_tb_FSM;

Projeto02/FSM/tb_FSM.vcd
$date
  Sun Nov 27 18:48:28 2022
$end
$version
  GHDL v0
$end
$timescale
  1 fs
$end
$scope module standard $end
$upscope $end
$scope module std_logic_1164 $end
$upscope $end
$scope module numeric_std $end
$upscope $end
$scope module tb_fsm $end
$var reg 1 ! ent_clk $end
$var reg 1 " ent_clk_enable $end
$var reg 1 # ent_x $end
$var reg 8 $ sai_z0[0:7] $end
$var reg 8 % sai_z1[0:7] $end
$var reg 8 & sai_z2[0:7] $end
$var reg 8 ' sai_z3[0:7] $end
$var reg 8 ( sai_z4[0:7] $end
$var reg 8 ) sai_z5[0:7] $end
$scope module dut $end
$var reg 1 * clk_fsm $end
$var reg 1 + x $end
$var reg 8 , z0[0:7] $end
$var reg 8 - z1[0:7] $end
$var reg 8 . z2[0:7] $end
$var reg 8 / z3[0:7] $end
$var reg 8 0 z4[0:7] $end
$var reg 8 1 z5[0:7] $end
$comment ps is not handled $end
$comment ns is not handled $end
$var reg 5 2 y[4:0] $end
$upscope $end
$upscope $end
$enddefinitions $end
#0
0!
1"
0#
b10111111 $
b11111111 %
b11111111 &
b11111111 '
b11111111 (
b11111111 )
0*
0+
b10111111 ,
b11111111 -
b11111111 .
b11111111 /
b11111111 0
b11111111 1
b00000 2
#10000000
1!
b01111111 $
1*
b01111111 ,
b00001 2
#20000000
0!
0*
#30000000
1!
b11111111 $
b01111111 %
1*
b11111111 ,
b01111111 -
b00010 2
#40000000
0!
0*
#50000000
1!
b11111111 %
b01111111 &
1*
b11111111 -
b01111111 .
b00011 2
#60000000
0!
0*
#70000000
1!
b11111111 &
b01111111 '
1*
b11111111 .
b01111111 /
b00100 2
#80000000
0!
0*
#90000000
1!
b11111111 '
b01111111 (
1*
b11111111 /
b01111111 0
b00101 2
#100000000
0!
0*
#110000000
1!
b11111111 (
b01111111 )
1*
b11111111 0
b01111111 1
b00110 2
#120000000
0!
0*
#130000000
1!
b11111011 )
1*
b11111011 1
b00111 2
#140000000
0!
0*
#150000000
1!
b11110111 )
1*
b11110111 1
b01000 2
#160000000
0!
0*
#170000000
1!
b11101111 )
1*
b11101111 1
b01001 2
#180000000
0!
0*
#190000000
1!
b11101111 (
b11111111 )
1*
b11101111 0
b11111111 1
b01010 2
#200000000
0!
0*
#210000000
1!
b11101111 '
b11111111 (
1*
b11101111 /
b11111111 0
b01011 2
#220000000
0!
0*
#230000000
1!
b11101111 &
b11111111 '
1*
b11101111 .
b11111111 /
b01100 2
#240000000
0!
0*
#250000000
1!
b11101111 %
b11111111 &
1*
b11101111 -
b11111111 .
b01101 2
#260000000
0!
0*
#270000000
1!
b11101111 $
b11111111 %
1*
b11101111 ,
b11111111 -
b01110 2
#280000000
0!
0*
#290000000
1!
b11011111 $
1*
b11011111 ,
b01111 2
#300000000
0!
0*
#310000000
1!
b11111101 $
1*
b11111101 ,
b10000 2
#320000000
0!
0*
#330000000
1!
b11111111 $
b11111101 %
1*
b11111111 ,
b11111101 -
b10001 2
#340000000
0!
0*
#350000000
1!
b11111111 %
b11111101 &
1*
b11111111 -
b11111101 .
b10010 2
#360000000
0!
0*
#370000000
1!
b11111111 &
b11111101 '
1*
b11111111 .
b11111101 /
b10011 2
#380000000
0!
0*
#390000000
1!
b11111111 '
b11111101 (
1*
b11111111 /
b11111101 0
b10100 2
#400000000
0!
0*
#410000000
1!
b11111111 (
b11111101 )
1*
b11111111 0
b11111101 1
b10101 2
#420000000
0!
0*
#430000000
1!
b10111111 $
b11111111 )
1*
b10111111 ,
b11111111 1
b00000 2
#440000000
0!
0*
#450000000
1!
b01111111 $
1*
b01111111 ,
b00001 2
#460000000
0!
0*
#470000000
1!
b11111111 $
b01111111 %
1*
b11111111 ,
b01111111 -
b00010 2
#480000000
0!
0*
#490000000
1!
b11111111 %
b01111111 &
1*
b11111111 -
b01111111 .
b00011 2
#500000000
0!
1#
b10111111 $
b11111111 &
0*
1+
b10111111 ,
b11111111 .
#510000000
1!
1*
b10111111 ,
b00000 2
#520000000
0!
0*
#530000000
1!
1*
#540000000
0!
0*
#550000000
1!
1*
#560000000
0!
0*
#570000000
1!
1*
#580000000
0!
0*
#590000000
1!
1*
#600000000
0!
0*
#610000000
1!
1*
#620000000
0!
0*
#630000000
1!
1*
#640000000
0!
0*
#650000000
1!
1*
#660000000
0!
0*
#670000000
1!
1*
#680000000
0!
0*
#690000000
1!
1*
#700000000
0!
0#
0*
0+
b10111111 ,
#710000000
1!
b01111111 $
1*
b01111111 ,
b00001 2
#720000000
0!
0*
#730000000
1!
b11111111 $
b01111111 %
1*
b11111111 ,
b01111111 -
b00010 2
#740000000
0!
0*
#750000000
1!
b11111111 %
b01111111 &
1*
b11111111 -
b01111111 .
b00011 2
#760000000
0!
0*
#770000000
1!
b11111111 &
b01111111 '
1*
b11111111 .
b01111111 /
b00100 2
#780000000
0!
0*
#790000000
1!
b11111111 '
b01111111 (
1*
b11111111 /
b01111111 0
b00101 2
#800000000
0!
0*
#810000000
1!
b11111111 (
b01111111 )
1*
b11111111 0
b01111111 1
b00110 2
#820000000
0!
0*
#830000000
1!
b11111011 )
1*
b11111011 1
b00111 2
#840000000
0!
0*
#850000000
1!
b11110111 )
1*
b11110111 1
b01000 2
#860000000
0!
0*
#870000000
1!
b11101111 )
1*
b11101111 1
b01001 2
#880000000
0!
0*
#890000000
1!
b11101111 (
b11111111 )
1*
b11101111 0
b11111111 1
b01010 2
#900000000
0!
0*
#910000000
1!
b11101111 '
b11111111 (
1*
b11101111 /
b11111111 0
b01011 2
#920000000
0!
0*
#930000000
1!
b11101111 &
b11111111 '
1*
b11101111 .
b11111111 /
b01100 2
#940000000
0!
0*
#950000000
1!
b11101111 %
b11111111 &
1*
b11101111 -
b11111111 .
b01101 2
#960000000
0!
0*
#970000000
1!
b11101111 $
b11111111 %
1*
b11101111 ,
b11111111 -
b01110 2
#980000000
0!
0*
#990000000
1!
b11011111 $
1*
b11011111 ,
b01111 2
