Projeto03/Calculator/Datapath/ALU/ALU.vhd

library ieee;
use ieee.std_logic_1164.all;
use ieee.numeric_std.all;  

entity ALU is
  port (
    OPERATOR : in std_logic_vector(1 downto 0);
    NUM1, NUM2 : in std_logic_vector(3 downto 0);
    RESULT : out std_logic_vector(3 downto 0)
  );
end ALU;

architecture arch_ALU of ALU is
begin
  operationProcess : process (OPERATOR, NUM1, NUM2)
  begin
    case (OPERATOR) is
      when "00" =>
        RESULT <= std_logic_vector(unsigned(NUM1) + unsigned(NUM2));      
      when "01" =>
        RESULT <= std_logic_vector(unsigned(NUM1) - unsigned(NUM2));      
      when "10" =>
        RESULT <= std_logic_vector(shift_left(unsigned(NUM1), to_integer(unsigned(NUM2)))); 
      when "11" =>
        RESULT <= std_logic_vector(shift_right(unsigned(NUM1), to_integer(unsigned(NUM2))));
      when others => RESULT <= "0000";
    end case;
  end process operationProcess;
end arch_ALU;

Projeto03/Calculator/Datapath/SelectorTwoStack/SelectorTwoStack.vhd

library ieee;
use ieee.std_logic_1164.all;
use ieee.numeric_std.all;

entity SelectorTwoStack is
  port (
    X0, X1, X2 : in std_logic_vector(3 downto 0);
    sel : in std_logic_vector(2 downto 0);
    Y0, Y1 : out std_logic_vector(3 downto 0)
  );
end SelectorTwoStack;

architecture arch_SelectorTwoStack of SelectorTwoStack is
begin
  Y1 <= X2 when sel = "110" else
    X1 when sel = "011" else 
    X0 when sel = "001";
  Y0 <= X1 when sel = "110" else
    X0 when sel = "011" else
    "0000" when sel = "001";

end arch_SelectorTwoStack;

Projeto03/Calculator/Datapath/StackRegister/StackRegister.vhd
-- O proprio registrador da stack e uma FSM

library IEEE;
use IEEE.std_logic_1164.all;

entity StackRegister is
  port (
    X : in std_logic_vector(3 downto 0);
    load, clear, clk : in std_logic;
    isEmpty : out std_logic;
    Z : out std_logic_vector(3 downto 0)
  );
end StackRegister;

architecture arch_StackRegister of StackRegister is
  type state_type is (HOLD_ST, LOAD_ST, CLEAR_ST);
  attribute ENUM_ENCODING : string;
  attribute ENUM_ENCODING of state_type : type is "00 01 10";
  signal PS, NS : state_type;

  signal Y : std_logic_vector(1 downto 0); -- para os estados da FSM
begin
  sync_process : process (CLK, NS)
  begin
    if (rising_edge(CLK)) then
      PS <= NS;
    end if;
  end process sync_process;

  comb_process : process (PS, load, clear, X)
  begin
    
    case PS is

      when HOLD_ST =>
        if (clear = '1') then
          NS <= CLEAR_ST;
        elsif (load = '1') then
          NS <= LOAD_ST;
        else
          NS <= HOLD_ST;
        end if;

      when LOAD_ST =>
        Z <= X;
        isEmpty <= '0'; 
        NS <= HOLD_ST;

      when CLEAR_ST =>
        Z <= "0000";
        isEmpty <= '1'; 

        if (clear = '0') then
          NS <= HOLD_ST;
        else 
          NS <= CLEAR_ST;
        end if;

      when others => -- catch all, nunca deve chegar aqui
        NS <= HOLD_ST;
    end case;
  end process comb_process;

  -- codificação dos estados Y
  with PS select
    Y <= "00" when HOLD_ST,
    "01" when LOAD_ST,
    "10" when CLEAR_ST,
    "00" when others;
end arch_StackRegister;

Projeto03/Calculator/Datapath/SelectorALU_NUM/SelectorALU_NUM.vhd

library ieee;
use ieee.std_logic_1164.all;
use ieee.numeric_std.all;

entity SelectorALU_NUM is
  port (
    X0, X1 : in std_logic_vector(3 downto 0);
    sel0 : in std_logic;
    sel1 : in std_logic_vector(2 downto 0);
    Y0, Y1, Y2 : out std_logic_vector(3 downto 0)
  );
end SelectorALU_NUM;

architecture arch_SelectorALU_NUM of SelectorALU_NUM is
begin
  Y2 <= X0 when (sel0 = '0' and sel1 = "100") else
    X1 when (sel0 = '1' and sel1 = "100");
  Y1 <= X0 when (sel0 = '0' and sel1 = "010") else
    X1 when (sel0 = '1' and sel1 = "010");
  Y0 <= X0 when (sel0 = '0' and sel1 = "001") else
    X1 when (sel0 = '1' and sel1 = "001");

end arch_SelectorALU_NUM;

Projeto03/Calculator/Datapath/Datapath.vhd
library IEEE;
use IEEE.std_logic_1164.all;

entity Datapath is
  port (
    clk : in std_logic;
    num : in std_logic_vector(3 downto 0);
    opr : in std_logic_vector(1 downto 0);
    sel_alu_num : in std_logic;
    sel_two_stack_pos, sel_stack_pos : in std_logic_vector(2 downto 0);
    clear_stack0, clear_stack1, clear_stack2, load_stack0, load_stack1, load_stack2 : in std_logic;

    isEmpty_stack0, isEmpty_stack1, isEmpty_stack2 : out std_logic;
    result_output : out std_logic_vector(3 downto 0)
  );
end Datapath;

architecture arch_Datapath of Datapath is
  type state_type is (RESET_BOOT, WAIT_ENTER, UPDATE_NUM, WAIT_ENTER_NUM_DOWN, EXECUTE_OPERATION, WAIT_ENTER_OPR_DOWN);
  attribute ENUM_ENCODING : string;
  attribute ENUM_ENCODING of state_type : type is
  "000 001 010 011 100 101";
  signal PS, NS : state_type;
  signal Y : std_logic_vector(2 downto 0); -- signal para os proximos estados da FSM

  -- signals internos do bloco datapath
  signal stack2_in, stack1_in, stack0_in, stack2_out, stack1_out, stack0_out : std_logic_vector(3 downto 0);
  signal alu_num1, alu_num2, result_alu : std_logic_vector(3 downto 0);

  component ALU is
    port (
      OPERATOR : in std_logic_vector(1 downto 0);
      NUM1, NUM2 : in std_logic_vector(3 downto 0);
      RESULT : out std_logic_vector(3 downto 0)
    );
  end component;

  component SelectorALU_NUM is
    port (
      X0, X1 : in std_logic_vector(3 downto 0);
      sel0 : in std_logic;
      sel1 : in std_logic_vector(2 downto 0);
      Y0, Y1, Y2 : out std_logic_vector(3 downto 0)
    );
  end component;

  component SelectorTwoStack is
    port (
      X0, X1, X2 : in std_logic_vector(3 downto 0);
      sel : in std_logic_vector(2 downto 0);
      Y0, Y1 : out std_logic_vector(3 downto 0)
    );
  end component;

  component StackRegister is
    port (
      X : in std_logic_vector(3 downto 0);
      load, clear, clk : in std_logic;
      isEmpty : out std_logic;
      Z : out std_logic_vector(3 downto 0)
    );
  end component;

begin
  inputSelector : SelectorALU_NUM port map(
    X0 => result_alu,
    X1 => num,
    sel0 => sel_alu_num,
    sel1 => sel_stack_pos,
    Y0 => stack0_in,
    Y1 => stack1_in,
    Y2 => stack2_in
  );

  stack0 : StackRegister port map(
    clk => clk,
    X => stack0_in,
    load => load_stack0,
    clear => clear_stack0,
    isEmpty => isEmpty_stack0,
    Z => stack0_out
  );

  stack1 : StackRegister port map(
    clk => clk,
    X => stack1_in,
    load => load_stack1,
    clear => clear_stack1,
    isEmpty => isEmpty_stack1,
    Z => stack1_out
  );

  stack2 : StackRegister port map(
    clk => clk,
    X => stack2_in,
    load => load_stack2,
    clear => clear_stack2,
    isEmpty => isEmpty_stack2,
    Z => stack2_out
  );

  outputSelector : SelectorTwoStack port map(
    X0 => stack0_out,
    X1 => stack1_out,
    X2 => stack2_out,
    sel => sel_two_stack_pos,
    Y0 => alu_num1,
    Y1 => alu_num2
  );

  stackALU : ALU port map(
    OPERATOR => opr,
    NUM1 => alu_num1, 
    NUM2 => alu_num2,
    RESULT => result_alu
  );

  result_output <= alu_num2;

end arch_Datapath;

Projeto03/Calculator/ControlBlock/ControlBlock.vhd
library IEEE;
use IEEE.std_logic_1164.all;

entity ControlBlock is
  port (
    clk : in std_logic;
    enter_num, enter_opr, reset : in std_logic;
    is_empty0, is_empty1, is_empty2 : in std_logic;
    load_stack0, load_stack1, load_stack2 : out std_logic;
    clear_stack0, clear_stack1, clear_stack2 : out std_logic;
    select_alu_num : out std_logic;
    select_stack_pos, select_two_stack_pos : out std_logic_vector(2 downto 0)
  );
end ControlBlock;

architecture arch_ControlBlock of ControlBlock is
  type state_type is (RESET_BOOT, WAIT_ENTER, UPDATE_NUM, WAIT_ENTER_NUM_DOWN, EXECUTE_OPERATION, WAIT_ENTER_OPR_DOWN);
  attribute ENUM_ENCODING : string;
  attribute ENUM_ENCODING of state_type : type is
  "000 001 010 011 100 101";
  signal PS, NS : state_type;
  signal Y : std_logic_vector(2 downto 0); -- signal para os proximos estados da FSM
begin
  sync_process : process (clk, NS)
  begin
    if (rising_edge(clk)) then
      PS <= NS;
    end if;
  end process sync_process;

  comb_process : process (
    PS, 
    reset,
    enter_num,
    enter_opr,
    reset,
    is_empty0,
    is_empty1,
    is_empty2
  )
  begin
    -- pre-assign saidas, assim nao precisa definir todas em cada estado
    load_stack0 <= '0';
    load_stack1 <= '0';
    load_stack2 <= '0';

    clear_stack0 <= '0';
    clear_stack1 <= '0';
    clear_stack2 <= '0';

    case PS is
      when RESET_BOOT =>
        if (reset = '1') then
          NS <= RESET_BOOT;
        else
          NS <= WAIT_ENTER;
        end if;

        clear_stack0 <= '1';
        clear_stack1 <= '1';
        clear_stack2 <= '1';

      when WAIT_ENTER =>
        if (reset = '1') then
          NS <= RESET_BOOT;
        elsif (enter_num = '1') then
          NS <= UPDATE_NUM;
        elsif (enter_opr = '1') then
          NS <= EXECUTE_OPERATION;
        else
          NS <= WAIT_ENTER;
        end if;

      when UPDATE_NUM =>
        NS <= WAIT_ENTER_NUM_DOWN;
        select_alu_num <= '1'; -- puxa do num conectado nas chaves

        -- identifica a posicao da stack que precisa carregar o conteudo das chaves
        -- e sempre a mais alta que a stack permite
        -- se todas as posicoes estao cheias, nao faz nada (nao adiciona na stack)
        if (is_empty0 = '1') then
          select_stack_pos <= "001";
          select_two_stack_pos <= "001";
          load_stack0 <= '1';
        elsif (is_empty1 = '1') then
          select_stack_pos <= "010";
          select_two_stack_pos <= "011";
          load_stack1 <= '1';
        elsif (is_empty2 = '1') then
          select_stack_pos <= "100";
          select_two_stack_pos <= "110";
          load_stack2 <= '1';
        end if;

      when WAIT_ENTER_NUM_DOWN =>
        if (enter_num = '1') then
          NS <= WAIT_ENTER_NUM_DOWN;
        else
          NS <= WAIT_ENTER;
        end if;

      when EXECUTE_OPERATION =>
        NS <= WAIT_ENTER_OPR_DOWN;
        select_alu_num <= '0'; -- puxa da ALU do datapath
        -- a linha acima está dando pau no testbench (simlation stopped). Se atribuir '1' resolve

        -- identifica a posicao da stack que precisa carregar o conteudo das chaves
        -- e sempre a mais alta que a stack permite
        -- se todas as posicoes estao cheias, nao faz nada (nao adiciona na stack)
        if (is_empty0 = '1') then
          select_stack_pos <= "001";
          select_two_stack_pos <= "001";
          load_stack0 <= '1';
        elsif (is_empty1 = '1') then
          select_stack_pos <= "010";
          select_two_stack_pos <= "011";
          load_stack1 <= '1';
        elsif (is_empty2 = '1') then
          select_stack_pos <= "100";
          select_two_stack_pos <= "110";
          load_stack2 <= '1';
        end if;

        -- onde e feito aqui o clear dos dois mais altos da stack?

      when WAIT_ENTER_OPR_DOWN =>
        if (enter_opr = '1') then
          NS <= WAIT_ENTER_OPR_DOWN;
        else
          NS <= WAIT_ENTER;
        end if;
        
      when others => -- catch all, nunca deve chegar aqui
        NS <= RESET_BOOT;
    end case;
end process comb_process;

-- codificação dos estados Y
with PS select
  Y <=
    "000" when RESET_BOOT,
    "001" when WAIT_ENTER,
    "010" when UPDATE_NUM,
    "011" when WAIT_ENTER_NUM_DOWN,
    "100" when EXECUTE_OPERATION,
    "101" when WAIT_ENTER_OPR_DOWN,
    "000" when others;
end arch_ControlBlock;

Projeto03/Calculator/Calculator.vhd
library IEEE;
use IEEE.std_logic_1164.all;

entity Calculator is
  port (
    CLK : in std_logic;
    RST, ENTER_NUM, ENTER_OPR : in std_logic;
    NUM : in std_logic_vector(3 downto 0);
    OPR : in std_logic_vector(1 downto 0);
    -- Z0, Z1, Z2, Z3 : out std_logic_vector(0 to 7));
    Z0 : out std_logic_vector(0 to 3)); -- para teste no projeto reduzido
end Calculator;

architecture arch_Calculator of Calculator is
  component ControlBlock is
    port (
      clk : in std_logic;
      enter_num, enter_opr, reset : in std_logic;
      is_empty0, is_empty1, is_empty2 : in std_logic;
      load_stack0, load_stack1, load_stack2 : out std_logic;
      clear_stack0, clear_stack1, clear_stack2 : out std_logic;
      select_alu_num : out std_logic;
      select_stack_pos, select_two_stack_pos : out std_logic_vector(2 downto 0)
    );
  end component;

  component Datapath is
    port (
      clk : in std_logic;
      num : in std_logic_vector(3 downto 0);
      opr : in std_logic_vector(1 downto 0);
      sel_alu_num : in std_logic;
      sel_two_stack_pos, sel_stack_pos : in std_logic_vector(2 downto 0);
      clear_stack0, clear_stack1, clear_stack2, load_stack0, load_stack1, load_stack2 : in std_logic;
  
      isEmpty_stack0, isEmpty_stack1, isEmpty_stack2 : out std_logic;
      result_output : out std_logic_vector(3 downto 0)
    );
  end component;

  -- signals intermediarios (conexao entre os blocos)
  signal interm_is_empty0 : std_logic;
  signal interm_is_empty1 : std_logic;
  signal interm_is_empty2 : std_logic;
  signal interm_load_stack0 : std_logic;
  signal interm_load_stack1 : std_logic;
  signal interm_load_stack2 : std_logic;
  signal interm_clear_stack0 : std_logic;
  signal interm_clear_stack1 : std_logic;
  signal interm_clear_stack2 : std_logic;
  signal interm_select_alu_num : std_logic;
  signal interm_select_stack_pos : std_logic_vector(2 downto 0);
  signal interm_select_two_stack_pos  : std_logic_vector(2 downto 0);

begin
  blocoDeControle : ControlBlock port map(
    clk => CLK,
    enter_num => ENTER_NUM,
    enter_opr => ENTER_OPR,
    reset => RST,

    is_empty0 => interm_is_empty0,
    is_empty1 => interm_is_empty1,
    is_empty2 => interm_is_empty2,
    load_stack0 => interm_load_stack0,
    load_stack1 => interm_load_stack1,
    load_stack2 => interm_load_stack2,
    clear_stack0 => interm_clear_stack0,
    clear_stack1 => interm_clear_stack1,
    clear_stack2 => interm_clear_stack2,
    select_alu_num => interm_select_alu_num,
    select_stack_pos => interm_select_stack_pos,
    select_two_stack_pos => interm_select_two_stack_pos
  );

  blocoOperacional : Datapath port map(
    clk => CLK,
    num => NUM,
    opr => OPR,
    result_output => Z0,

    sel_alu_num => interm_select_alu_num,
    sel_stack_pos => interm_select_stack_pos,
    sel_two_stack_pos => interm_select_two_stack_pos,
    clear_stack0 => interm_clear_stack0,
    clear_stack1 => interm_clear_stack1,
    clear_stack2 => interm_clear_stack2,
    load_stack0 => interm_load_stack0,
    load_stack1 => interm_load_stack1,
    load_stack2 => interm_load_stack2,

    isEmpty_stack0 => interm_is_empty0,
    isEmpty_stack1 => interm_is_empty1,
    isEmpty_stack2 => interm_is_empty2
  );


end arch_Calculator;

Projeto03/Calculator/tb_Calculator.vhd
library IEEE;
use IEEE.STD_LOGIC_1164.all;
use ieee.numeric_std.all;

entity tb_Calculator is
end tb_Calculator;

architecture arch_tb_Calculator of tb_Calculator is

  component Calculator is
    port (
      CLK : in std_logic;
      RST, ENTER_NUM, ENTER_OPR : in std_logic;
      NUM : in std_logic_vector(3 downto 0);
      OPR : in std_logic_vector(1 downto 0);
      -- Z0, Z1, Z2, Z3 : out std_logic_vector(0 to 7));
      Z0 : out std_logic_vector(0 to 3)); -- para teste no modelo reduzido
  end component;

  constant PERIODO : time := 20 ns; -- 50MHz
  signal ENT_CLK : std_logic := '0'; -- deve ser inicializado
  signal ENT_CLK_ENABLE : std_logic := '1'; -- Sinal de Enable do clock só para efeito de controle do fim da simulação

  signal tb_RST, tb_ENTER_NUM, tb_ENTER_OPR : std_logic;
  signal tb_NUM : std_logic_vector(3 downto 0);
  signal tb_OPR : std_logic_vector(1 downto 0);
  signal tb_Z0 : std_logic_vector(0 to 3); 

begin
  -- geração do clock com periodo PERIODO
  ENT_CLK <= ENT_CLK_ENABLE and not ENT_CLK after PERIODO/2;
  ENT_CLK_ENABLE <= '1', '0' after 50 * PERIODO; -- a simulação termina após transcorrer 20 períodos de clock.

  -- instanciação do DUT
  DUT : Calculator port map(
    CLK => ENT_CLK,
    RST => tb_RST,
    ENTER_NUM => tb_ENTER_NUM,
    ENTER_OPR => tb_ENTER_OPR,
    NUM => tb_NUM,
    OPR => tb_OPR,
    Z0 => tb_Z0
    -- Z1 => SAI_Z1,
    -- Z2 => SAI_Z2,
    -- Z3 => SAI_Z3
  );

  --  process para os estímulos das entradas
  stimulus : process
  begin
    tb_RST <= '0';
    tb_ENTER_NUM <= '0';
    tb_ENTER_OPR<= '0';

    tb_NUM <= "0010";
    tb_OPR <= "00";
    wait for 5 * PERIODO;

    tb_ENTER_NUM <= '1';
    wait for 5 * PERIODO;

    tb_ENTER_NUM <= '0';
    wait for 5 * PERIODO;

    tb_NUM <= "0011";
    wait for 5 * PERIODO;

    tb_ENTER_NUM <= '1';
    wait for 5 * PERIODO;

    tb_ENTER_NUM <= '0';
    wait for 5 * PERIODO;

    tb_ENTER_OPR <= '1';
    wait for 5 * PERIODO;
    tb_ENTER_OPR <= '0';
    wait for 5 * PERIODO;

    wait;
  end process stimulus;
end arch_tb_Calculator;

Projeto03/Calculator/tb_Calculator.vcd
$date
  Mon Dec 12 14:35:17 2022
$end
$version
  GHDL v0
$end
$timescale
  1 fs
$end
$scope module standard $end
$upscope $end
$scope module std_logic_1164 $end
$upscope $end
$scope module numeric_std $end
$upscope $end
$scope module tb_calculator $end
$var reg 1 ! ent_clk $end
$var reg 1 " ent_clk_enable $end
$var reg 1 # tb_rst $end
$var reg 1 $ tb_enter_num $end
$var reg 1 % tb_enter_opr $end
$var reg 4 & tb_num[3:0] $end
$var reg 2 ' tb_opr[1:0] $end
$var reg 4 ( tb_z0[0:3] $end
$scope module dut $end
$var reg 1 ) clk $end
$var reg 1 * rst $end
$var reg 1 + enter_num $end
$var reg 1 , enter_opr $end
$var reg 4 - num[3:0] $end
$var reg 2 . opr[1:0] $end
$var reg 4 / z0[0:3] $end
$var reg 1 0 interm_is_empty0 $end
$var reg 1 1 interm_is_empty1 $end
$var reg 1 2 interm_is_empty2 $end
$var reg 1 3 interm_load_stack0 $end
$var reg 1 4 interm_load_stack1 $end
$var reg 1 5 interm_load_stack2 $end
$var reg 1 6 interm_clear_stack0 $end
$var reg 1 7 interm_clear_stack1 $end
$var reg 1 8 interm_clear_stack2 $end
$var reg 1 9 interm_select_alu_num $end
$var reg 3 : interm_select_stack_pos[2:0] $end
$var reg 3 ; interm_select_two_stack_pos[2:0] $end
$scope module blocodecontrole $end
$var reg 1 < clk $end
$var reg 1 = enter_num $end
$var reg 1 > enter_opr $end
$var reg 1 ? reset $end
$var reg 1 @ is_empty0 $end
$var reg 1 A is_empty1 $end
$var reg 1 B is_empty2 $end
$var reg 1 C load_stack0 $end
$var reg 1 D load_stack1 $end
$var reg 1 E load_stack2 $end
$var reg 1 F clear_stack0 $end
$var reg 1 G clear_stack1 $end
$var reg 1 H clear_stack2 $end
$var reg 1 I select_alu_num $end
$var reg 3 J select_stack_pos[2:0] $end
$var reg 3 K select_two_stack_pos[2:0] $end
$comment ps is not handled $end
$comment ns is not handled $end
$var reg 3 L y[2:0] $end
$upscope $end
$scope module blocooperacional $end
$var reg 1 M clk $end
$var reg 4 N num[3:0] $end
$var reg 2 O opr[1:0] $end
$var reg 1 P sel_alu_num $end
$var reg 3 Q sel_two_stack_pos[2:0] $end
$var reg 3 R sel_stack_pos[2:0] $end
$var reg 1 S clear_stack0 $end
$var reg 1 T clear_stack1 $end
$var reg 1 U clear_stack2 $end
$var reg 1 V load_stack0 $end
$var reg 1 W load_stack1 $end
$var reg 1 X load_stack2 $end
$var reg 1 Y isempty_stack0 $end
$var reg 1 Z isempty_stack1 $end
$var reg 1 [ isempty_stack2 $end
$var reg 4 \ result_output[3:0] $end
$comment ps is not handled $end
$comment ns is not handled $end
$var reg 3 ] y[2:0] $end
$var reg 4 ^ stack2_in[3:0] $end
$var reg 4 _ stack1_in[3:0] $end
$var reg 4 ` stack0_in[3:0] $end
$var reg 4 a stack2_out[3:0] $end
$var reg 4 b stack1_out[3:0] $end
$var reg 4 c stack0_out[3:0] $end
$var reg 4 d alu_num1[3:0] $end
$var reg 4 e alu_num2[3:0] $end
$var reg 4 f result_alu[3:0] $end
$scope module inputselector $end
$var reg 4 g x0[3:0] $end
$var reg 4 h x1[3:0] $end
$var reg 1 i sel0 $end
$var reg 3 j sel1[2:0] $end
$var reg 4 k y0[3:0] $end
$var reg 4 l y1[3:0] $end
$var reg 4 m y2[3:0] $end
$upscope $end
$scope module stack0 $end
$var reg 4 n x[3:0] $end
$var reg 1 o load $end
$var reg 1 p clear $end
$var reg 1 q clk $end
$var reg 1 r isempty $end
$var reg 4 s z[3:0] $end
$comment ps is not handled $end
$comment ns is not handled $end
$var reg 2 t y[1:0] $end
$upscope $end
$scope module stack1 $end
$var reg 4 u x[3:0] $end
$var reg 1 v load $end
$var reg 1 w clear $end
$var reg 1 x clk $end
$var reg 1 y isempty $end
$var reg 4 z z[3:0] $end
$comment ps is not handled $end
$comment ns is not handled $end
$var reg 2 { y[1:0] $end
$upscope $end
$scope module stack2 $end
$var reg 4 | x[3:0] $end
$var reg 1 } load $end
$var reg 1 !" clear $end
$var reg 1 "" clk $end
$var reg 1 #" isempty $end
$var reg 4 $" z[3:0] $end
$comment ps is not handled $end
$comment ns is not handled $end
$var reg 2 %" y[1:0] $end
$upscope $end
$scope module outputselector $end
$var reg 4 &" x0[3:0] $end
$var reg 4 '" x1[3:0] $end
$var reg 4 (" x2[3:0] $end
$var reg 3 )" sel[2:0] $end
$var reg 4 *" y0[3:0] $end
$var reg 4 +" y1[3:0] $end
$upscope $end
$scope module stackalu $end
$var reg 2 ," operator[1:0] $end
$var reg 4 -" num1[3:0] $end
$var reg 4 ." num2[3:0] $end
$var reg 4 /" result[3:0] $end
$upscope $end
$upscope $end
$upscope $end
$upscope $end
$enddefinitions $end
#0
0!
1"
0#
0$
0%
b0010 &
b00 '
bUUUU (
0)
0*
0+
0,
b0010 -
b00 .
bUUUU /
U0
U1
U2
03
04
05
16
17
18
U9
bUUU :
bUUU ;
0<
0=
0>
0?
U@
UA
UB
0C
0D
0E
1F
1G
1H
UI
bUUU J
bUUU K
b000 L
0M
b0010 N
b00 O
UP
bUUU Q
bUUU R
1S
1T
1U
0V
0W
0X
UY
UZ
U[
bUUUU \
bUUU ]
bUUUU ^
bUUUU _
bUUUU `
bUUUU a
bUUUU b
bUUUU c
bUUUU d
bUUUU e
bXXXX f
bXXXX g
b0010 h
Ui
bUUU j
bUUUU k
bUUUU l
bUUUU m
bUUUU n
0o
1p
0q
Ur
bUUUU s
b00 t
bUUUU u
0v
1w
0x
Uy
bUUUU z
b00 {
bUUUU |
0}
1!"
0""
U#"
bUUUU $"
b00 %"
bUUUU &"
bUUUU '"
bUUUU ("
bUUU )"
bUUUU *"
bUUUU +"
b00 ,"
bUUUU -"
bUUUU ."
bXXXX /"
#10000000
1!
1)
10
11
12
06
07
08
1<
1@
1A
1B
0F
0G
0H
b001 L
1M
0S
0T
0U
1Y
1Z
1[
b0000 a
b0000 b
b0000 c
0p
1q
1r
b0000 s
b10 t
0w
1x
1y
b0000 z
b10 {
0!"
1""
1#"
b0000 $"
b10 %"
b0000 &"
b0000 '"
b0000 ("
#20000000
0!
0)
0<
0M
0q
0x
0""
#30000000
1!
1)
1<
1M
1q
b00 t
1x
b00 {
1""
b00 %"
#40000000
0!
0)
0<
0M
0q
0x
0""
#50000000
1!
1)
1<
1M
1q
1x
1""
#60000000
0!
0)
0<
0M
0q
0x
0""
#70000000
1!
1)
1<
1M
1q
1x
1""
#80000000
0!
0)
0<
0M
0q
0x
0""
#90000000
1!
1)
1<
1M
1q
1x
1""
#100000000
0!
1$
0)
1+
0<
1=
0M
0q
0x
0""
#110000000
1!
b0000 (
1)
b0000 /
13
19
b001 :
b001 ;
1<
1C
1I
b001 J
b001 K
b010 L
1M
1P
b001 Q
b001 R
1V
b0000 \
b0010 `
b0000 d
b0000 e
b0000 f
b0000 g
1i
b001 j
b0010 k
b0010 n
1o
1q
1x
1""
b001 )"
b0000 *"
b0000 +"
b0000 -"
b0000 ."
b0000 /"
#120000000
0!
0)
0<
0M
0q
0x
0""
#130000000
1!
b0010 (
1)
b0010 /
00
03
1<
0@
0C
b011 L
1M
0V
0Y
b0010 \
b0010 c
b0010 e
b0010 f
b0010 g
0o
1q
0r
b0010 s
b01 t
1x
1""
b0010 &"
b0010 +"
b0010 ."
b0010 /"
#140000000
0!
0)
0<
0M
0q
0x
0""
#150000000
1!
1)
1<
1M
1q
b00 t
1x
1""
#160000000
0!
0)
0<
0M
0q
0x
0""
#170000000
1!
1)
1<
1M
1q
1x
1""
#180000000
0!
0)
0<
0M
0q
0x
0""
#190000000
1!
1)
1<
1M
1q
1x
1""
#200000000
0!
0$
0)
0+
0<
0=
0M
0q
0x
0""
#210000000
1!
1)
1<
b001 L
1M
1q
1x
1""
#220000000
0!
0)
0<
0M
0q
0x
0""
#230000000
1!
1)
1<
1M
1q
1x
1""
#240000000
0!
0)
0<
0M
0q
0x
0""
#250000000
1!
1)
1<
1M
1q
1x
1""
#260000000
0!
0)
0<
0M
0q
0x
0""
#270000000
1!
1)
1<
1M
1q
1x
1""
#280000000
0!
0)
0<
0M
0q
0x
0""
#290000000
1!
1)
1<
1M
1q
1x
1""
#300000000
0!
b0011 &
0)
b0011 -
0<
0M
b0011 N
b0011 `
b0011 h
b0011 k
b0011 n
0q
0x
0""
#310000000
1!
1)
1<
1M
1q
1x
1""
#320000000
0!
0)
0<
0M
0q
0x
0""
#330000000
1!
1)
1<
1M
1q
1x
1""
#340000000
0!
0)
0<
0M
0q
0x
0""
#350000000
1!
1)
1<
1M
1q
1x
1""
#360000000
0!
0)
0<
0M
0q
0x
0""
#370000000
1!
1)
1<
1M
1q
1x
1""
#380000000
0!
0)
0<
0M
0q
0x
0""
#390000000
1!
1)
1<
1M
1q
1x
1""
#400000000
0!
1$
0)
1+
0<
1=
0M
0q
0x
0""
#410000000
1!
b0000 (
1)
b0000 /
14
b010 :
b011 ;
1<
1D
b010 J
b011 K
b010 L
1M
b011 Q
b010 R
1W
b0000 \
b0011 _
b0010 d
b0000 e
b010 j
b0011 l
1q
b0011 u
1v
1x
1""
b011 )"
b0010 *"
b0000 +"
b0010 -"
b0000 ."
#420000000
0!
0)
0<
0M
0q
0x
0""
#430000000
1!
b0011 (
1)
b0011 /
01
04
1<
0A
0D
b011 L
1M
0W
0Z
b0011 \
b0011 b
b0011 e
b0101 f
b0101 g
1q
0v
1x
0y
b0011 z
b01 {
1""
b0011 '"
b0011 +"
b0011 ."
b0101 /"
#440000000
0!
0)
0<
0M
0q
0x
0""
#450000000
1!
1)
1<
1M
1q
1x
b00 {
1""
#460000000
0!
0)
0<
0M
0q
0x
0""
#470000000
1!
1)
1<
1M
1q
1x
1""
#480000000
0!
0)
0<
0M
0q
0x
0""
#490000000
1!
1)
1<
1M
1q
1x
1""
#500000000
0!
0$
0)
0+
0<
0=
0M
0q
0x
0""
#510000000
1!
1)
1<
b001 L
1M
1q
1x
1""
#520000000
0!
0)
0<
0M
0q
0x
0""
#530000000
1!
1)
1<
1M
1q
1x
1""
#540000000
0!
0)
0<
0M
0q
0x
0""
#550000000
1!
1)
1<
1M
1q
1x
1""
#560000000
0!
0)
0<
0M
0q
0x
0""
#570000000
1!
1)
1<
1M
1q
1x
1""
#580000000
0!
0)
0<
0M
0q
0x
0""
#590000000
1!
1)
1<
1M
1q
1x
1""
#600000000
0!
1%
0)
1,
0<
1>
0M
0q
0x
0""
#610000000
1!
b0000 (
1)
b0000 /
15
09
b100 :
b110 ;
1<
1E
0I
b100 J
b110 K
b100 L
1M
0P
b110 Q
b100 R
1X
b0000 \
b0011 ^
b0011 d
b0000 e
b0011 f
b0011 g
0i
b100 j
b0011 m
1q
1x
b0011 |
1}
1""
b110 )"
b0011 *"
b0000 +"
b0011 -"
b0000 ."
b0011 /"
