Projeto03/Calculator/Calculator.vhd
library IEEE;
use IEEE.std_logic_1164.all;

entity Calculator is
  port (
    CLK : in std_logic;
    RST, ENTER_NUM, ENTER_OPR : in std_logic;
    NUM : in std_logic_vector(3 downto 0);
    OPR : in std_logic_vector(1 downto 0);
    Z0, Z1, Z2, Z3 : out std_logic_vector(0 to 7));
end Calculator;

architecture arch_Calculator of Calculator is
  type state_type is (RESET, WAIT_ENTER, SAVE_NUM);
  attribute ENUM_ENCODING : string;
  attribute ENUM_ENCODING of state_type : type is
  "000 001 010";
  signal PS, NS : state_type;
  signal Y : std_logic_vector(2 downto 0); -- signal para os proximos estados da FSM
  signal STACK_ENABLE : std_logic;
begin
  sync_process : process (CLK, NS)
  begin
    if (rising_edge(CLK)) then
      PS <= NS;
    end if;
  end process sync_process;

  comb_process : process (PS)
  begin
    -- pre-assign saidas, assim nao precisa definir todas em cada estado
    Z0 <= "11111111";
    Z1 <= "11111111";
    Z2 <= "11111111";
    Z3 <= "11111111";

    case PS is
      when RESET =>
        NS <= WAIT_ENTER;

      when WAIT_ENTER =>
        if (RST = '1') then
          NS <= RESET;
        end if;

        if (ENTER_NUM = '1') then
          NS <= SAVE_NUM;
        else 
          NS <= WAIT_ENTER;
        end if;

        STACK_ENABLE <= '0';

      when SAVE_NUM =>
        NS <= WAIT_ENTER;

      when others => -- catch all, nunca deve chegar aqui
        NS <= WAIT_ENTER;
    end case;
end process comb_process;

-- codificação dos estados Y
with PS select
  Y <=
  "000" when RESET,
  "001" when WAIT_ENTER,
  "010" when SAVE_NUM,
  "000" when others;
end arch_Calculator;

Projeto03/Calculator/tb_Calculator.vhd
library IEEE;
use IEEE.STD_LOGIC_1164.all;
use ieee.numeric_std.all;

entity tb_Calculator is
end tb_Calculator;

architecture arch_tb_Calculator of tb_Calculator is

  component Calculator is
    port (
      CLK : in std_logic;
      RST, ENTER_NUM, ENTER_OPR : in std_logic;
      NUM : in std_logic_vector(3 downto 0);
      OPR : in std_logic_vector(1 downto 0);
      Z0, Z1, Z2, Z3 : out std_logic_vector(0 to 7));
  end component;

  constant PERIODO : time := 20 ns; -- 50MHz
  signal ENT_CLK : std_logic := '0'; -- deve ser inicializado
  signal ENT_CLK_ENABLE : std_logic := '1'; -- Sinal de Enable do clock só para efeito de controle do fim da simulação
  signal ENT_RST, ENT_ENTER_NUM, ENT_ENTER_OPR : std_logic; 
  signal ENT_NUM : std_logic_vector(3 downto 0); 
  signal ENT_OPR: std_logic_vector(1 downto 0); 
  signal SAI_Z0, SAI_Z1, SAI_Z2, SAI_Z3 : std_logic_vector(0 to 7);

begin
  -- geração do clock com periodo PERIODO
  ENT_CLK <= ENT_CLK_ENABLE and not ENT_CLK after PERIODO/2;
  ENT_CLK_ENABLE <= '1', '0' after 50 * PERIODO; -- a simulação termina após transcorrer 20 períodos de clock.

  -- instanciação do DUT
  DUT : Calculator port map(
    CLK => ENT_CLK,
    RST => ENT_RST,
    ENTER_NUM => ENT_ENTER_NUM,
    ENTER_OPR => ENT_ENTER_OPR,
    NUM => ENT_NUM,
    OPR => ENT_OPR,
    Z0 => SAI_Z0,
    Z1 => SAI_Z1,
    Z2 => SAI_Z2,
    Z3 => SAI_Z3
  );

  --  process para os estímulos das entradas
  stimulus : process
  begin
    ENT_RST <= '0';
    ENT_ENTER_NUM <= '1';
    wait for 5 * PERIODO;
    ENT_ENTER_NUM <= '0';
    wait for 5 * PERIODO;
    ENT_ENTER_NUM <= '1';
    wait for 25 * PERIODO;
    ENT_RST <= '1';
    wait for 10 * PERIODO;
    ENT_RST <= '0';

    wait;
  end process stimulus;
end arch_tb_Calculator;

Projeto03/Calculator/ControlBlock/tb_Calculator.vcd
$date
  Fri Dec 09 10:05:46 2022
$end
$version
  GHDL v0
$end
$timescale
  1 fs
$end
$scope module standard $end
$upscope $end
$scope module std_logic_1164 $end
$upscope $end
$scope module numeric_std $end
$upscope $end
$scope module tb_calculator $end
$var reg 1 ! ent_clk $end
$var reg 1 " ent_clk_enable $end
$var reg 1 # ent_rst $end
$var reg 1 $ ent_enter_num $end
$var reg 1 % ent_enter_opr $end
$var reg 4 & ent_num[3:0] $end
$var reg 2 ' ent_opr[1:0] $end
$var reg 8 ( sai_z0[0:7] $end
$var reg 8 ) sai_z1[0:7] $end
$var reg 8 * sai_z2[0:7] $end
$var reg 8 + sai_z3[0:7] $end
$scope module dut $end
$var reg 1 , clk $end
$var reg 1 - rst $end
$var reg 1 . enter_num $end
$var reg 1 / enter_opr $end
$var reg 4 0 num[3:0] $end
$var reg 2 1 opr[1:0] $end
$var reg 8 2 z0[0:7] $end
$var reg 8 3 z1[0:7] $end
$var reg 8 4 z2[0:7] $end
$var reg 8 5 z3[0:7] $end
$comment ps is not handled $end
$comment ns is not handled $end
$var reg 3 6 y[2:0] $end
$var reg 1 7 stack_enable $end
$upscope $end
$upscope $end
$enddefinitions $end
#0
0!
1"
0#
1$
U%
bUUUU &
bUU '
b11111111 (
b11111111 )
b11111111 *
b11111111 +
0,
0-
1.
U/
bUUUU 0
bUU 1
b11111111 2
b11111111 3
b11111111 4
b11111111 5
b000 6
U7
#10000000
1!
1,
b001 6
07
#20000000
0!
0,
#30000000
1!
1,
b010 6
#40000000
0!
0,
#50000000
1!
1,
b001 6
#60000000
0!
0,
#70000000
1!
1,
b010 6
#80000000
0!
0,
#90000000
1!
1,
b001 6
#100000000
0!
0$
0,
0.
#110000000
1!
1,
b010 6
#120000000
0!
0,
#130000000
1!
1,
b001 6
#140000000
0!
0,
#150000000
1!
1,
#160000000
0!
0,
#170000000
1!
1,
#180000000
0!
0,
#190000000
1!
1,
#200000000
0!
1$
0,
1.
