Aula08/Ex2OneHot/ComponentEx2OneHot.vhd
-- Atividade pratica da Guia de Aula 08
-- Exercicio 2, pagina 108 do livro Free Range VHDL (2018)

library IEEE;
use IEEE.std_logic_1164.all;

entity ComponentEx2OneHot is
  port (
    CLK : in std_logic;
    X : in std_logic_vector(1 downto 0); -- entradas da FSM
    Y : out std_logic_vector(2 downto 0); -- saidas para os proximos estados da FSM
    Z : out std_logic); -- saida efetiva da FSM
end ComponentEx2OneHot;

architecture arch_ComponentEx2OneHot of ComponentEx2OneHot is
  type state_type is (ST0, ST1, ST2);
  attribute ENUM_ENCODING : string;
  attribute ENUM_ENCODING of state_type : type is "001 010 100";
  signal PS, NS : state_type;
begin
  sync_process : process (CLK, NS)
  begin
    if (rising_edge(CLK)) then
      PS <= NS;
    end if;
  end process sync_process;

  comb_process : process (PS, X)
  begin
    Z <= '0'; -- pre-assing saidas

    case PS is

      when ST0 =>
        if (X(0) = '0') then
          NS <= ST0;
          Z <= '0';
        elsif (X(0) = '1') then
          NS <= ST1;
          Z <= '0';
        else -- catch all, deixa igual o anterior mesmo
          NS <= ST1;
          Z <= '0';
        end if;

      when ST1 =>
        if (X(1) = '1') then
          NS <= ST2;
          Z <= '0';
        elsif (X(1) = '0') then
          NS <= ST0;
          Z <= '1';
        else -- catch all, deixa igual o anterior mesmo
          NS <= ST0;
          Z <= '1';
        end if;

      when ST2 =>
        if (X(1) = '1') then
          NS <= ST2;
          Z <= '0';
        elsif (X(1) = '0') then
          NS <= ST0;
          Z <= '1';
        else -- catch all, deixa igual o anterior mesmo
          NS <= ST0;
          Z <= '1';
        end if;

      when others => -- catch all, nunca deve chegar aqui
        Z <= '0';
        NS <= ST0;
    end case;
  end process comb_process;

  -- codificação dos estados Y
  with PS select
    Y <= "001" when ST0,
    "010" when ST1,
    "100" when ST2,
    "001" when others;
end arch_ComponentEx2OneHot;

Aula08/Ex2OneHot/tb_ComponentEx2OneHot.vhd
library IEEE;
use IEEE.STD_LOGIC_1164.all;
use ieee.numeric_std.all;

entity tb_ComponentEx2OneHot is
end tb_ComponentEx2OneHot;

architecture arch_tb_ComponentEx2OneHot of tb_ComponentEx2OneHot is

  component ComponentEx2OneHot is
    port (
      CLK : in std_logic;
      X : in std_logic_vector(1 downto 0); -- entradas da FSM
      Y : out std_logic_vector(2 downto 0); -- saidas para os proximos estados da FSM
      Z : out std_logic); -- saida efetiva da FSM
  end component;

  constant PERIODO : time := 10 ns;
  signal ENT_CLK : std_logic := '0'; -- deve ser inicializado
  signal ENT_CLK_ENABLE : std_logic := '1'; -- Sinal de Enable do clock só para efeito de controle do fim da simulação
  signal ENT_X : std_logic_vector(1 downto 0); 
  signal SAI_Y : std_logic_vector(2 downto 0);
  signal SAI_Z : std_logic;

begin
  -- geração do clock com periodo PERIODO
  ENT_CLK <= ENT_CLK_ENABLE and not ENT_CLK after PERIODO/2;
  ENT_CLK_ENABLE <= '1', '0' after 20 * PERIODO; -- a simulação termina após transcorrer 20 períodos de clock.

  -- instanciação do DUT, que nesse exemplo é um ffd
  DUT : ComponentEx2OneHot port map(
    CLK => ENT_CLK,
    X => ENT_X,
    Y => SAI_Y,
    Z => SAI_Z
  );

  --  process para os estímulos das entradas
  stimulus : process
  begin
    ENT_X <= "00";
    wait for 4 * PERIODO;
    ENT_X <= "01";
    wait for 4 * PERIODO;
    ENT_X <= "10";
    wait for 4 * PERIODO;
    ENT_X <= "11";
    wait for 4 * PERIODO;
    wait;
  end process stimulus;
end arch_tb_ComponentEx2OneHot;

Aula08/Ex2OneHot/tb_ComponentEx2OneHot.vcd
$date
  Mon Oct 24 17:35:02 2022
$end
$version
  GHDL v0
$end
$timescale
  1 fs
$end
$scope module standard $end
$upscope $end
$scope module std_logic_1164 $end
$upscope $end
$scope module numeric_std $end
$upscope $end
$scope module tb_componentex2onehot $end
$var reg 1 ! ent_clk $end
$var reg 1 " ent_clk_enable $end
$var reg 2 # ent_x[1:0] $end
$var reg 3 $ sai_y[2:0] $end
$var reg 1 % sai_z $end
$scope module dut $end
$var reg 1 & clk $end
$var reg 2 ' x[1:0] $end
$var reg 3 ( y[2:0] $end
$var reg 1 ) z $end
$comment ps is not handled $end
$comment ns is not handled $end
$upscope $end
$upscope $end
$enddefinitions $end
#0
0!
1"
b00 #
b001 $
0%
0&
b00 '
b001 (
0)
#5000000
1!
1&
#10000000
0!
0&
#15000000
1!
1&
#20000000
0!
0&
#25000000
1!
1&
#30000000
0!
0&
#35000000
1!
1&
#40000000
0!
b01 #
0&
b01 '
#45000000
1!
b010 $
1%
1&
b010 (
1)
#50000000
0!
0&
#55000000
1!
b001 $
0%
1&
b001 (
0)
#60000000
0!
0&
#65000000
1!
b010 $
1%
1&
b010 (
1)
#70000000
0!
0&
#75000000
1!
b001 $
0%
1&
b001 (
0)
#80000000
0!
b10 #
0&
b10 '
#85000000
1!
1&
#90000000
0!
0&
#95000000
1!
1&
#100000000
0!
0&
#105000000
1!
1&
#110000000
0!
0&
#115000000
1!
1&
#120000000
0!
b11 #
0&
b11 '
#125000000
1!
b010 $
1&
b010 (
#130000000
0!
0&
#135000000
1!
b100 $
1&
b100 (
