Projeto03/Calculator/Datapath/Stack/Stack.vhd
--Empty descending stack implementation in VHDL.
library IEEE;
use IEEE.STD_LOGIC_1164.all;
use IEEE.NUMERIC_STD.all;

entity Stack is
  port (
    Clk : in std_logic; --Clock for the stack.
    Reset : in std_logic; --active high reset.    
    Enable : in std_logic; --Enable the stack. Otherwise neither push nor pop will happen.
    Data_In : in std_logic_vector(15 downto 0); --Data to be pushed to stack
    Data_Out : out std_logic_vector(15 downto 0); --Data popped from the stack.
    PUSH_barPOP : in std_logic; --active low for POP and active high for PUSH.
    Stack_Full : out std_logic; --Goes high when the stack is full.
    Stack_Empty : out std_logic --Goes high when the stack is empty.
  );
end Stack;

architecture Behavioral of Stack is

  type mem_type is array (0 to 2) of std_logic_vector(15 downto 0);
  signal stack_mem : mem_type := (others => (others => '0'));
  signal full, empty : std_logic := '0';
  signal prev_PP : std_logic := '0';
  signal SP : integer := 0; --for simulation and debugging. 

begin

  Stack_Full <= full;
  Stack_Empty <= empty;

  --PUSH and POP process for the stack.
  PUSH : process (Clk, reset)
    variable stack_ptr : integer := 2;
  begin
    if (reset = '1') then
      stack_ptr := 2; --stack grows downwards.
      full <= '0';
      empty <= '0';
      Data_out <= (others => '0');
      prev_PP <= '0';
    elsif (rising_edge(Clk)) then
      --value of PUSH_barPOP with one clock cycle delay.
      if (Enable = '1') then
        prev_PP <= PUSH_barPOP;
      else
        prev_PP <= '0';
      end if;
      --POP section.
      if (Enable = '1' and PUSH_barPOP = '0' and empty = '0') then
        --setting empty flag.           
        if (stack_ptr = 2) then
          full <= '0';
          empty <= '1';
        else
          full <= '0';
          empty <= '0';
        end if;
        --when the push becomes pop, before stack is full. 
        if (prev_PP = '1' and full = '0') then
          stack_ptr := stack_ptr + 1;
        end if;
        --Data has to be taken from the next highest address(empty descending type stack).              
        Data_Out <= stack_mem(stack_ptr);
        if (stack_ptr /= 2) then
          stack_ptr := stack_ptr + 1;
        end if;
      end if;

      --PUSH section.
      -- se quiser dar overwrite quando tiver full, so remover a condicao do full = '0', mas assim tem perda de info
      if (Enable = '1' and PUSH_barPOP = '1' and full = '0') then
        --setting full flag.
        if (stack_ptr = 0) then
          full <= '1';
          empty <= '0';
        else
          full <= '0';
          empty <= '0';
        end if;
        --when the pop becomes push, before stack is empty.
        if (prev_PP = '0' and empty = '0') then
          stack_ptr := stack_ptr - 1;
        end if;
        --Data pushed to the current address.       
        stack_mem(stack_ptr) <= Data_In;
        if (stack_ptr /= 0) then
          stack_ptr := stack_ptr - 1;
        end if;
      end if;
      SP <= stack_ptr; --for debugging/simulation.

    end if;
  end process;

end Behavioral;

Projeto03/Stack/tb_Stack.vhd
library IEEE;
use IEEE.STD_LOGIC_1164.all;
use ieee.numeric_std.all;

entity tb_Stack is
end tb_Stack;

architecture arch_tb_Stack of tb_Stack is

  component Stack is
    port (
      Clk : in std_logic; --Clock for the stack.
      Reset : in std_logic; --active high reset.    
      Enable : in std_logic; --Enable the stack. Otherwise neither push nor pop will happen.
      Data_In : in std_logic_vector(15 downto 0); --Data to be pushed to stack
      Data_Out : out std_logic_vector(15 downto 0); --Data popped from the stack.
      PUSH_barPOP : in std_logic; --active low for POP and active high for PUSH.
      Stack_Full : out std_logic; --Goes high when the stack is full.
      Stack_Empty : out std_logic); --Goes high when the stack is empty.); -- saidas efetivas da FSM
  end component;

  constant PERIODO : time := 20 ns; -- 50MHz
  signal ENT_CLK : std_logic := '0'; -- deve ser inicializado
  signal ENT_CLK_ENABLE : std_logic := '1'; -- Sinal de Enable do clock só para efeito de controle do fim da simulação
  signal ENT_RST, ENT_ENABLE, ENT_PUSH_barPOP, SAI_STACK_FULL, SAI_STACK_EMPTY : std_logic;
  signal ENT_DATA_IN, SAI_DATA_OUT : std_logic_vector(15 downto 0);

begin
  -- geração do clock com periodo PERIODO
  ENT_CLK <= ENT_CLK_ENABLE and not ENT_CLK after PERIODO/2;
  ENT_CLK_ENABLE <= '1', '0' after 50 * PERIODO; -- a simulação termina após transcorrer 20 períodos de clock.

  -- instanciação do DUT
  DUT : Stack port map(
    CLK => ENT_CLK,
    Reset => ENT_RST,
    Enable => ENT_ENABLE,
    Data_In => ENT_DATA_IN,
    Data_Out => SAI_DATA_OUT,
    PUSH_barPOP => ENT_PUSH_barPOP,
    Stack_Full => SAI_STACK_FULL,
    Stack_Empty => SAI_STACK_EMPTY
  );

  --  process para os estímulos das entradas
  -- stimulus : process
  -- begin
  --   ENT_RST <= '0';
  --   wait for 25 * PERIODO;
  --   ENT_RST <= '1';
  --   wait for 10 * PERIODO;
  --   ENT_RST <= '0';

  --   wait;
  -- end process stimulus;

  -- Stimulus process
  stim_proc : process
  begin
    ENT_RST <= '1'; --apply ENT_RST for one clock cycle.
    wait for PERIODO;
    ENT_RST <= '0';
    wait for PERIODO * 3; --wait for 3 clock periods(simply)
    ENT_ENABLE <= '1'; --ENT_ENABLE stack
    wait for PERIODO * 3; --wait for 3 clock periods(simply)
    ENT_PUSH_barPOP <= '1'; --Set for push operation.
    ENT_DATA_IN <= X"FFFF"; --Push something to stack.
    wait for PERIODO;
    ENT_DATA_IN <= X"7FFF"; --Push something to stack.
    wait for PERIODO;
    ENT_DATA_IN <= X"2FFF"; --Push something to stack.
    wait for PERIODO;
    ENT_DATA_IN <= X"AAFF"; --Push something to stack.
    wait for PERIODO;
    ENT_DATA_IN <= X"BBFF"; --Push something to stack.
    wait for PERIODO;
    ENT_PUSH_barPOP <= '0'; --POP two of the above pushed values.
    wait for PERIODO * 2;
    ENT_PUSH_barPOP <= '1'; --Set for push operation.
    ENT_DATA_IN <= X"1234"; --Push something to stack.
    wait for PERIODO;
    ENT_DATA_IN <= X"5678"; --Push something to stack.
    wait for PERIODO;

    -- ENT_RST <= '1';
    -- wait for 15 * PERIODO;
    -- ENT_RST <= '0';

    ENT_PUSH_barPOP <= '0'; --POP all the above pushed values.
    wait for PERIODO * 10; --wait for some time.
    ENT_PUSH_barPOP <= '1'; --Set for push operation.
    ENT_DATA_IN <= X"0020"; --Push something to stack.
    wait for PERIODO;
    ENT_PUSH_barPOP <= '0'; --pop what was pushed.
    wait for PERIODO * 10;
    ENT_ENABLE <= '0'; --disable stack.

    wait for PERIODO * 10; --wait for some time.
    wait;
  end process;
end arch_tb_Stack;

Projeto03/Stack/tb_Stack.vcd
$date
  Fri Dec 09 09:25:14 2022
$end
$version
  GHDL v0
$end
$timescale
  1 fs
$end
$scope module standard $end
$upscope $end
$scope module std_logic_1164 $end
$upscope $end
$scope module numeric_std $end
$upscope $end
$scope module tb_stack $end
$var reg 1 ! ent_clk $end
$var reg 1 " ent_clk_enable $end
$var reg 1 # ent_rst $end
$var reg 1 $ ent_enable $end
$var reg 1 % ent_push_barpop $end
$var reg 1 & sai_stack_full $end
$var reg 1 ' sai_stack_empty $end
$var reg 16 ( ent_data_in[15:0] $end
$var reg 16 ) sai_data_out[15:0] $end
$scope module dut $end
$var reg 1 * clk $end
$var reg 1 + reset $end
$var reg 1 , enable $end
$var reg 16 - data_in[15:0] $end
$var reg 16 . data_out[15:0] $end
$var reg 1 / push_barpop $end
$var reg 1 0 stack_full $end
$var reg 1 1 stack_empty $end
$comment stack_mem is not handled $end
$var reg 1 2 full $end
$var reg 1 3 empty $end
$var reg 1 4 prev_pp $end
$var integer 32 5 sp $end
$upscope $end
$upscope $end
$enddefinitions $end
#0
0!
1"
1#
U$
U%
0&
0'
bUUUUUUUUUUUUUUUU (
b0000000000000000 )
0*
1+
U,
bUUUUUUUUUUUUUUUU -
b0000000000000000 .
U/
00
01
02
03
04
b0 5
#10000000
1!
1*
#20000000
0!
0#
0*
0+
#30000000
1!
1*
b10 5
#40000000
0!
0*
#50000000
1!
1*
#60000000
0!
0*
#70000000
1!
1*
#80000000
0!
1$
0*
1,
#90000000
1!
1*
U4
#100000000
0!
0*
#110000000
1!
1*
#120000000
0!
0*
#130000000
1!
1*
#140000000
0!
1%
b1111111111111111 (
0*
b1111111111111111 -
1/
#150000000
1!
1*
14
b1 5
#160000000
0!
b0111111111111111 (
0*
b0111111111111111 -
#170000000
1!
1*
b0 5
#180000000
0!
b0010111111111111 (
0*
b0010111111111111 -
#190000000
1!
1&
1*
10
12
#200000000
0!
b1010101011111111 (
0*
b1010101011111111 -
#210000000
1!
1*
#220000000
0!
b1011101111111111 (
0*
b1011101111111111 -
#230000000
1!
1*
#240000000
0!
0%
0*
0/
#250000000
1!
0&
b1011101111111111 )
1*
b1011101111111111 .
00
02
04
b1 5
#260000000
0!
0*
#270000000
1!
b0111111111111111 )
1*
b0111111111111111 .
b10 5
#280000000
0!
1%
b0001001000110100 (
0*
b0001001000110100 -
1/
#290000000
1!
1*
14
b0 5
#300000000
0!
b0101011001111000 (
0*
b0101011001111000 -
#310000000
1!
1&
1*
10
12
#320000000
0!
0%
0*
0/
#330000000
1!
0&
b0101011001111000 )
1*
b0101011001111000 .
00
02
04
b1 5
#340000000
0!
0*
#350000000
1!
b0001001000110100 )
1*
b0001001000110100 .
b10 5
#360000000
0!
0*
#370000000
1!
1'
b1111111111111111 )
1*
b1111111111111111 .
11
13
#380000000
0!
0*
#390000000
1!
1*
#400000000
0!
0*
#410000000
1!
1*
#420000000
0!
0*
#430000000
1!
1*
#440000000
0!
0*
#450000000
1!
1*
#460000000
0!
0*
#470000000
1!
1*
#480000000
0!
0*
#490000000
1!
1*
#500000000
0!
0*
#510000000
1!
1*
#520000000
0!
1%
b0000000000100000 (
0*
b0000000000100000 -
1/
#530000000
1!
0'
1*
01
03
14
b1 5
#540000000
0!
0%
0*
0/
#550000000
1!
b0000000000100000 )
1*
b0000000000100000 .
04
b10 5
#560000000
0!
0*
#570000000
1!
1'
1*
11
13
#580000000
0!
0*
#590000000
1!
1*
#600000000
0!
0*
#610000000
1!
1*
#620000000
0!
0*
#630000000
1!
1*
#640000000
0!
0*
#650000000
1!
1*
#660000000
0!
0*
#670000000
1!
1*
#680000000
0!
0*
#690000000
1!
1*
#700000000
0!
0*
#710000000
1!
1*
#720000000
0!
0*
#730000000
1!
1*
#740000000
0!
0$
0*
0,
