Aula07/Ex2/ComponentEx2.vhd
-- Componente 1 da Atividade pratica da Guia de Aula 07
-- Exercicio 2, pagina 86 do livro Free Range VHDL (2018)

library ieee;
use ieee.std_logic_1164.all;
use ieee.numeric_std.all;

entity ComponentEx2 is
  port (
    S, D, R, CLK : in std_logic;
    Q, Q_NOT : out std_logic);
end ComponentEx2;

architecture arch_ComponentEx2 of ComponentEx2 is
begin
  dff : process (CLK, R, S) -- R e S sao assincronos
  begin
    if (S = '0') then -- S tem precendencia sobre R
      Q <= '1';
      Q_NOT <= '0';
    elsif (R = '0') then
      Q <= '0';
      Q_NOT <= '1';
    elsif (rising_edge(CLK)) then
      Q <= D;
      Q_NOT <= not D;
    end if;
  end process dff;
end arch_ComponentEx2;

Aula07/Ex2/tb_ComponentEx2.vhd
library IEEE;
use IEEE.STD_LOGIC_1164.all;
use ieee.numeric_std.all;

entity tb_ComponentEx2 is
end tb_ComponentEx2;

architecture arch_tb_ComponentEx2 of tb_ComponentEx2 is

  component ComponentEx2 is
    port (
      S, D, R, CLK : in std_logic;
      Q, Q_NOT : out std_logic);
  end component;

  constant PERIODO : time := 10 ns;
  signal ENT_CLK : std_logic := '0'; -- deve ser inicializado
  signal ENT_CLK_ENABLE : std_logic := '1'; -- Sinal de Enable do clock só para efeito de controle do fim da simulação
  signal ENT_R : std_logic;
  signal ENT_S : std_logic;
  signal ENT_D : std_logic;
  signal SAI_Q : std_logic;
  signal SAI_Q_NOT : std_logic;

begin
  -- geração do clock com periodo PERIODO
  ENT_CLK <= ENT_CLK_ENABLE and not ENT_CLK after PERIODO/2;
  ENT_CLK_ENABLE <= '1', '0' after 20 * PERIODO; -- a simulação termina após transcorrer 20 períodos de clock.

  -- instanciação do DUT, que nesse exemplo é um ffd
  DUT : ComponentEx2 port map(
    CLK => ENT_CLK,
    R => ENT_R,
    S => ENT_S,
    D => ENT_D,
    Q => SAI_Q,
    Q_NOT => SAI_Q_NOT);
  -- a partir daqui declaro os estímulos de entrada, ou a injecao de sinais
  -- um process para o reset
  reset : process
  begin
    ENT_R <= '1';
    ENT_S <= '1';
    wait for 2 * PERIODO; -- um reset de duração de 2 períodos de clock
    ENT_R <= '0';
    ENT_S <= '0';
    wait for 4 * PERIODO; 
    ENT_R <= '0';
    ENT_S <= '1';
    wait for 4 * PERIODO; 
    ENT_R <= '1';
    ENT_S <= '1';
    
    wait;
  end process reset;
  -- um outro process para os estímulos da entrada D
  stimulus : process
  begin
    ENT_D <= '0';
    wait for 4 * PERIODO;
    ENT_D <= '1';
    wait for 6 * PERIODO;
    ENT_D <= '0';
    wait for 3 * PERIODO;
    ENT_D <= '1';
    wait;
  end process stimulus;
end arch_tb_ComponentEx2;

Aula07/Ex2/tb_ComponentEx2.vcd
$date
  Mon Oct 17 21:16:54 2022
$end
$version
  GHDL v0
$end
$timescale
  1 fs
$end
$scope module standard $end
$upscope $end
$scope module std_logic_1164 $end
$upscope $end
$scope module numeric_std $end
$upscope $end
$scope module tb_componentex2 $end
$var reg 1 ! ent_clk $end
$var reg 1 " ent_clk_enable $end
$var reg 1 # ent_r $end
$var reg 1 $ ent_s $end
$var reg 1 % ent_d $end
$var reg 1 & sai_q $end
$var reg 1 ' sai_q_not $end
$scope module dut $end
$var reg 1 ( s $end
$var reg 1 ) d $end
$var reg 1 * r $end
$var reg 1 + clk $end
$var reg 1 , q $end
$var reg 1 - q_not $end
$upscope $end
$upscope $end
$enddefinitions $end
#0
0!
1"
1#
1$
0%
U&
U'
1(
0)
1*
0+
U,
U-
#5000000
1!
0&
1'
1+
0,
1-
#10000000
0!
0+
#15000000
1!
1+
#20000000
0!
0#
0$
1&
0'
0(
0*
0+
1,
0-
#25000000
1!
1+
#30000000
0!
0+
#35000000
1!
1+
#40000000
0!
1%
1)
0+
#45000000
1!
1+
#50000000
0!
0+
#55000000
1!
1+
#60000000
0!
1$
0&
1'
1(
0+
0,
1-
#65000000
1!
1+
#70000000
0!
0+
#75000000
1!
1+
#80000000
0!
0+
#85000000
1!
1+
#90000000
0!
0+
#95000000
1!
1+
#100000000
0!
1#
0%
0)
1*
0+
#105000000
1!
1+
#110000000
0!
0+
#115000000
1!
1+
#120000000
0!
0+
#125000000
1!
1+
#130000000
0!
1%
1)
0+
#135000000
1!
1&
0'
1+
1,
0-
